Workbook

Sheet Cover
B2: Profound
B3: Five Year Operating Model
B6: HOW THIS MODEL IS BUILT
B7: Revenue is an output, not a target | C7: The hiring plan is the input. Sales capacity, ramp and attrition determine new bookings, and growth falls out.
B8: NRR, GRR and gross margin are outputs | C8: They are computed from retention and expansion drivers and from query volume, then compared against benchmark on the KPIs tab.
B9: Cohorts are dollar denominated | C9: Correct basis for NRR and GRR. A separate logo view uses a worse churn rate and does not feed the ARR calculation.
B10: Every input lives on the Inputs tab | C10: A hardcoded value anywhere else in this workbook is a defect. Change any blue cell and the model recalculates.
B11: Checks ship inside the workbook | C11: The Checks tab reconciles cohorts to the ARR bridge, the deferred revenue roll and the cash roll on every period.
B13: FORMATTING KEY
B14: Hardcoded input | C14: Inputs tab only
B15: Calculation | C15: Formula computed on this sheet
B16: Same sheet reference | C16: Points at another cell on this sheet
B17: Link to another sheet | C17: Cross sheet reference
B19: TAB MAP
B20: Inputs | C20: Every assumption. Scenario switch in cell D5 drives the whole model.
B21: Rev-Capacity | C21: AE hiring, ramp, attrition, productive capacity, new bookings. Self serve.
B22: Rev-Cohorts | C22: Dollar cohort triangle. Renewal events, expansion, churn.
B23: Rev-ARR Bridge | C23: Beginning plus new plus expansion less churn. Agents and self serve.
B24: Headcount | C24: Roster by function, hiring, attrition, payroll, stock compensation.
B25: P&L | C25: Revenue recognition, volume driven cost of revenue, operating expense, EBITDA.
B26: Cash Flow | C26: Billings, deferred revenue, working capital, capital expenditure, cash roll.
B27: KPIs | C27: Computed outputs against benchmark. Runway and raise decision date.
B28: Scenarios | C28: Five cases. Base, upside, downside, downside with hiring freeze, Agents led.
B29: Checks | C29: Live reconciliations. Everything should read OK.

Sheet Inputs
B2: Inputs
B5: SCENARIO SWITCH | D5: 1 | E5: =INDEX({"Base";"Upside";"Downside";"Agents-Led";"Downside + Freeze"},$D$5,1) | F5: 1=Base 2=Upside 3=Downside 4=Downside+Freeze 5=Agents-Led
D7: 2026 | E7: 2027 | F7: 2028 | G7: 2029 | H7: 2030
B8: GIVEN
B9: Opening ARR at 1 Jan 2026 | C9: $ | D9: 55000000 | J9: Given. Interpreted as ending contracted ARR.
B10: Opening cash | C10: $ | D10: 110000000 | J10: Given. Assumed post Series C. No further financing in base case.
B11: Opening headcount | C11: # | D11: 250 | J11: Given.
B12: Minimum cash balance | C12: $ | D12: 25000000 | J12: Given. Board operating floor, not zero. Usable cash is $85M.
B14: OPENING BASE
B15: Enterprise ARR | C15: $ | D15: 53500000 | J15: Ties to given total with self serve below.
B16: Enterprise customers | C16: # | D16: 700 | J16: Public: 700+ enterprise customers. Source: Fortune, February 2026: 700+ enterprise customers at the Series C.
B17: Self serve ARR | C17: $ | D17: 1500000
B18: Self serve customers | C18: # | D18: 500 | J18: Published tiers: $99 and $399 per month.
B20: SALES CAPACITY
B21: Opening quota carrying AEs | C21: # | D21: 30
B22: AE annual quota, fully ramped | C22: $ | D22: 1300000 | J22: Benchmark commercial band $0.9M to $1.4M.
B23: Quota growth per year | C23: % | D23: -0.05 | J23: Negative. Territories thin as the org scales.
J24: Ramp lengthens from four months to five as ACV climbs and Agents makes it a two product sale.
B25: Ramp productivity, month 1 | C25: % | D25: 0.25 | E25: 0.25 | F25: 0.2 | G25: 0.2 | H25: 0.2
B26: Ramp productivity, month 2 | C26: % | D26: 0.5 | E26: 0.5 | F26: 0.4 | G26: 0.4 | H26: 0.4
B27: Ramp productivity, month 3 | C27: % | D27: 0.75 | E27: 0.75 | F27: 0.6 | G27: 0.6 | H27: 0.6
B28: Ramp productivity, month 4 | C28: % | D28: 1 | E28: 1 | F28: 0.8 | G28: 0.8 | H28: 0.8
B29: Ramp productivity, month 5 | C29: % | D29: 1 | E29: 1 | F29: 1 | G29: 1 | H29: 1
B30: Time to hire, months | C30: # | D30: 2 | J30: Benchmark 6 to 10 weeks.
B31: SDRs per AE | C31: x | D31: 0.8
B32: Marketing per AE | C32: x | D32: 0.45
B33: Sales ops per AE | C33: x | D33: 0.3
B34: Enablement per AE | C34: x | D34: 0.05 | J34: Explicit enablement investment holding ramp at the short end.
B36: Quota attainment
B37: Base | C37: % | D37: 0.78 | E37: 0.78 | F37: 0.78 | G37: 0.78 | H37: 0.78
B38: Upside | C38: % | D38: 0.85 | E38: 0.85 | F38: 0.85 | G38: 0.85 | H38: 0.85
B39: Downside | C39: % | D39: 0.74 | E39: 0.74 | F39: 0.74 | G39: 0.74 | H39: 0.74
B40: Agents-Led | C40: % | D40: 0.78 | E40: 0.78 | F40: 0.78 | G40: 0.78 | H40: 0.78
B41: Downside + Freeze | C41: % | D41: 0.74 | E41: 0.74 | F41: 0.74 | G41: 0.74 | H41: 0.74
B42: Active | C42: % | D42: =INDEX($D$37:$H$41,$D$5,1) | E42: =INDEX($D$37:$H$41,$D$5,2) | F42: =INDEX($D$37:$H$41,$D$5,3) | G42: =INDEX($D$37:$H$41,$D$5,4) | H42: =INDEX($D$37:$H$41,$D$5,5) | J42: Benchmark 70% median, 80% top quartile.
B44: AE hires per month
B45: Base | C45: # | D45: 2.2 | E45: 2.6 | F45: 2.8 | G45: 2.6 | H45: 2.2
B46: Upside | C46: # | D46: 4 | E46: 5.2 | F46: 5.8 | G46: 5.8 | H46: 5.2
B47: Downside | C47: # | D47: 2.2 | E47: 2.6 | F47: 2.8 | G47: 2.6 | H47: 2.2
B48: Agents-Led | C48: # | D48: 2.2 | E48: 2.6 | F48: 2.8 | G48: 2.6 | H48: 2.2
B49: Downside + Freeze | C49: # | D49: 2.2 | E49: 1 | F49: 0.8 | G49: 0.8 | H49: 0.8
B50: Active | C50: # | D50: =INDEX($D$45:$H$49,$D$5,1) | E50: =INDEX($D$45:$H$49,$D$5,2) | F50: =INDEX($D$45:$H$49,$D$5,3) | G50: =INDEX($D$45:$H$49,$D$5,4) | H50: =INDEX($D$45:$H$49,$D$5,5)
B52: RETENTION AND EXPANSION
B53: First renewal dollar survival
B54: Base | C54: % | D54: 0.92 | E54: 0.92 | F54: 0.92 | G54: 0.92 | H54: 0.92
B55: Upside | C55: % | D55: 0.94 | E55: 0.94 | F55: 0.94 | G55: 0.94 | H55: 0.94
B56: Downside | C56: % | D56: 0.885 | E56: 0.885 | F56: 0.885 | G56: 0.885 | H56: 0.885
B57: Agents-Led | C57: % | D57: 0.92 | E57: 0.92 | F57: 0.92 | G57: 0.92 | H57: 0.92
B58: Downside + Freeze | C58: % | D58: 0.885 | E58: 0.885 | F58: 0.885 | G58: 0.885 | H58: 0.885
B59: Active | C59: % | D59: =INDEX($D$54:$H$58,$D$5,1) | E59: =INDEX($D$54:$H$58,$D$5,2) | F59: =INDEX($D$54:$H$58,$D$5,3) | G59: =INDEX($D$54:$H$58,$D$5,4) | H59: =INDEX($D$54:$H$58,$D$5,5) | J59: Least proven number in the business. Nothing in the base has renewed yet.
B61: Later renewal dollar survival | C61: % | D61: 0.95 | E61: 0.95 | F61: 0.955 | G61: 0.96 | H61: 0.96
B62: In contract churn per year | C62: % | D62: 0.005 | J62: Low by design. Annual terms concentrate churn at renewal.
B63: Seat and usage expansion per year
B64: Base | C64: % | D64: 0.22 | E64: 0.16 | F64: 0.1 | G64: 0.065 | H64: 0.045
B65: Upside | C65: % | D65: 0.27 | E65: 0.21 | F65: 0.135 | G65: 0.09 | H65: 0.06
B66: Downside | C66: % | D66: 0.185 | E66: 0.13 | F66: 0.08 | G66: 0.05 | H66: 0.035
B67: Agents-Led | C67: % | D67: 0.22 | E67: 0.16 | F67: 0.1 | G67: 0.065 | H67: 0.045
B68: Downside + Freeze | C68: % | D68: 0.185 | E68: 0.13 | F68: 0.08 | G68: 0.05 | H68: 0.035
B69: Active | C69: % | D69: =INDEX($D$64:$H$68,$D$5,1) | E69: =INDEX($D$64:$H$68,$D$5,2) | F69: =INDEX($D$64:$H$68,$D$5,3) | G69: =INDEX($D$64:$H$68,$D$5,4) | H69: =INDEX($D$64:$H$68,$D$5,5) | J69: Must decay. Expansion compresses as accounts saturate.
B71: Renewal price uplift | C71: % | D71: 0.08
B72: Cross sell uplift at renewal | C72: % | D72: 0.11 | E72: 0.08 | F72: 0.05 | G72: 0.035 | H72: 0.025
B73: Logo churn premium over dollar churn | C73: % | D73: 0.03 | J73: Churned accounts are systematically smaller. Reporting view only.
B75: PRICING
B76: Enterprise new logo ACV | C76: $ | D76: 76428.57 | J76: $55.0M given ARR less ~$1.5M self-serve (500 accounts at ~$3.0K blended, per published $99 and $399 monthly tiers), over 700+ enterprise customers
B77: Enterprise ACV growth per year | C77: % | D77: 0.1
B78: Self serve ACV | C78: $ | D78: 3000
B79: Self serve ACV growth per year | C79: % | D79: 0.05
B81: SELF SERVE
B82: New self serve customers per month | C82: # | D82: 45
B83: Growth in monthly adds per year | C83: % | D83: 0.25
B84: Monthly churn | C84: % | D84: 0.04
B85: Monthly conversion into enterprise | C85: % | D85: 0.01 | J85: The strategic value of self serve. Feeds enterprise bookings.
B87: AGENTS
B88: Attach rate, share of enterprise customers at year end
B89: Base | C89: % | D89: 0.08 | E89: 0.18 | F89: 0.3 | G89: 0.38 | H89: 0.45
B90: Upside | C90: % | D90: 0.1 | E90: 0.24 | F90: 0.38 | G90: 0.47 | H90: 0.55
B91: Downside | C91: % | D91: 0.05 | E91: 0.11 | F91: 0.18 | G91: 0.23 | H91: 0.27
B92: Agents-Led | C92: % | D92: 0.14 | E92: 0.35 | F92: 0.55 | G92: 0.7 | H92: 0.8
B93: Downside + Freeze | C93: % | D93: 0.05 | E93: 0.11 | F93: 0.18 | G93: 0.23 | H93: 0.27
B94: Active | C94: % | D94: =INDEX($D$89:$H$93,$D$5,1) | E94: =INDEX($D$89:$H$93,$D$5,2) | F94: =INDEX($D$89:$H$93,$D$5,3) | G94: =INDEX($D$89:$H$93,$D$5,4) | H94: =INDEX($D$89:$H$93,$D$5,5) | J94: Biggest swing factor, weakest benchmark.
B96: Agents ACV as share of core ACV
B97: Base | C97: % | D97: 0.45 | E97: 0.45 | F97: 0.45 | G97: 0.45 | H97: 0.45
B98: Upside | C98: % | D98: 0.45 | E98: 0.45 | F98: 0.45 | G98: 0.45 | H98: 0.45
B99: Downside | C99: % | D99: 0.45 | E99: 0.45 | F99: 0.45 | G99: 0.45 | H99: 0.45
B100: Agents-Led | C100: % | D100: 0.8 | E100: 0.8 | F100: 0.8 | G100: 0.8 | H100: 0.8
B101: Downside + Freeze | C101: % | D101: 0.45 | E101: 0.45 | F101: 0.45 | G101: 0.45 | H101: 0.45
B102: Active | C102: % | D102: =INDEX($D$97:$H$101,$D$5,1) | E102: =INDEX($D$97:$H$101,$D$5,2) | F102: =INDEX($D$97:$H$101,$D$5,3) | G102: =INDEX($D$97:$H$101,$D$5,4) | H102: =INDEX($D$97:$H$101,$D$5,5)
B104: Agents ACV growth per year
B105: Base | C105: % | D105: 0.12 | E105: 0.12 | F105: 0.12 | G105: 0.12 | H105: 0.12
B106: Upside | C106: % | D106: 0.12 | E106: 0.12 | F106: 0.12 | G106: 0.12 | H106: 0.12
B107: Downside | C107: % | D107: 0.12 | E107: 0.12 | F107: 0.12 | G107: 0.12 | H107: 0.12
B108: Agents-Led | C108: % | D108: 0.18 | E108: 0.18 | F108: 0.18 | G108: 0.18 | H108: 0.18
B109: Downside + Freeze | C109: % | D109: 0.12 | E109: 0.12 | F109: 0.12 | G109: 0.12 | H109: 0.12
B110: Active | C110: % | D110: =INDEX($D$105:$H$109,$D$5,1) | E110: =INDEX($D$105:$H$109,$D$5,2) | F110: =INDEX($D$105:$H$109,$D$5,3) | G110: =INDEX($D$105:$H$109,$D$5,4) | H110: =INDEX($D$105:$H$109,$D$5,5)
B113: COST OF REVENUE
B114: Tracked prompts per enterprise customer | C114: # | D114: 2000 | J114: Set for a large multi brand enterprise.
B115: AI engines monitored | C115: # | D115: 10 | J115: Published product fact. The Enterprise tier covers all ten engines.
B116: Runs per prompt per month | C116: # | D116: 30 | J116: Daily refresh. Tracking change over time is the core value proposition.
B118: Query volume growth per year | C118: % | D118: 0.15
B119: Cost per query | C119: $ | D119: 0.0012
...

Sheet Rev-Capacity
B2: Revenue: Sales Capacity and Bookings
B5: Month ending | D5: 46053 | E5: 46081 | F5: 46112 | G5: 46142 | H5: 46173 | I5: 46203 | J5: 46234 | K5: 46265 | L5: 46295 | M5: 46326 | N5: 46356 | O5: 46387 | P5: 46418 | Q5: 46446 | R5: 46477 | S5: 46507 | T5: 46538 | U5: 46568 | V5: 46599 | W5: 46630 | X5: 46660 | Y5: 46691 | Z5: 46721 | AA5: 46752 | AB5: 46783 | AC5: 46812 | AD5: 46843 | AE5: 46873 | AF5: 46904 | AG5: 46934 | AH5: 46965 | AI5: 46996 | AJ5: 47026 | AK5: 47057 | AL5: 47087 | AM5: 47118 | AN5: 47149 | AO5: 47177 | AP5: 47208 | AQ5: 47238 | AR5: 47269 | AS5: 47299 | AT5: 47330 | AU5: 47361 | AV5: 47391 | AW5: 47422 | AX5: 47452 | AY5: 47483 | AZ5: 47514 | BA5: 47542 | BB5: 47573 | BC5: 47603 | BD5: 47634 | BE5: 47664 | BF5: 47695 | BG5: 47726 | BH5: 47756 | BI5: 47787 | BJ5: 47817 | BK5: 47848 | BM5: FY2026 | BN5: FY2027 | BO5: FY2028 | BP5: FY2029 | BQ5: FY2030
B6: Fiscal year | D6: 2026 | E6: 2026 | F6: 2026 | G6: 2026 | H6: 2026 | I6: 2026 | J6: 2026 | K6: 2026 | L6: 2026 | M6: 2026 | N6: 2026 | O6: 2026 | P6: 2027 | Q6: 2027 | R6: 2027 | S6: 2027 | T6: 2027 | U6: 2027 | V6: 2027 | W6: 2027 | X6: 2027 | Y6: 2027 | Z6: 2027 | AA6: 2027 | AB6: 2028 | AC6: 2028 | AD6: 2028 | AE6: 2028 | AF6: 2028 | AG6: 2028 | AH6: 2028 | AI6: 2028 | AJ6: 2028 | AK6: 2028 | AL6: 2028 | AM6: 2028 | AN6: 2029 | AO6: 2029 | AP6: 2029 | AQ6: 2029 | AR6: 2029 | AS6: 2029 | AT6: 2029 | AU6: 2029 | AV6: 2029 | AW6: 2029 | AX6: 2029 | AY6: 2029 | AZ6: 2030 | BA6: 2030 | BB6: 2030 | BC6: 2030 | BD6: 2030 | BE6: 2030 | BF6: 2030 | BG6: 2030 | BH6: 2030 | BI6: 2030 | BJ6: 2030 | BK6: 2030
B7: Period | D7: 1 | E7: 2 | F7: 3 | G7: 4 | H7: 5 | I7: 6 | J7: 7 | K7: 8 | L7: 9 | M7: 10 | N7: 11 | O7: 12 | P7: 13 | Q7: 14 | R7: 15 | S7: 16 | T7: 17 | U7: 18 | V7: 19 | W7: 20 | X7: 21 | Y7: 22 | Z7: 23 | AA7: 24 | AB7: 25 | AC7: 26 | AD7: 27 | AE7: 28 | AF7: 29 | AG7: 30 | AH7: 31 | AI7: 32 | AJ7: 33 | AK7: 34 | AL7: 35 | AM7: 36 | AN7: 37 | AO7: 38 | AP7: 39 | AQ7: 40 | AR7: 41 | AS7: 42 | AT7: 43 | AU7: 44 | AV7: 45 | AW7: 46 | AX7: 47 | AY7: 48 | AZ7: 49 | BA7: 50 | BB7: 51 | BC7: 52 | BD7: 53 | BE7: 54 | BF7: 55 | BG7: 56 | BH7: 57 | BI7: 58 | BJ7: 59 | BK7: 60
B9: QUOTA CARRYING CAPACITY
B10: AE hires arriving | C10: # | D10: =INDEX(Inputs!$D$50:$H$50,1,D$6-2025) | E10: =INDEX(Inputs!$D$50:$H$50,1,D$6-2025) | F10: =INDEX(Inputs!$D$50:$H$50,1,D$6-2025) | G10: =INDEX(Inputs!$D$50:$H$50,1,E$6-2025) | H10: =INDEX(Inputs!$D$50:$H$50,1,F$6-2025) | I10: =INDEX(Inputs!$D$50:$H$50,1,G$6-2025) | J10: =INDEX(Inputs!$D$50:$H$50,1,H$6-2025) | K10: =INDEX(Inputs!$D$50:$H$50,1,I$6-2025) | L10: =INDEX(Inputs!$D$50:$H$50,1,J$6-2025) | M10: =INDEX(Inputs!$D$50:$H$50,1,K$6-2025) | ... BK10: =INDEX(Inputs!$D$50:$H$50,1,BI$6-2025) | BM10: =SUM(D10:O10) | BN10: =SUM(P10:AA10) | BO10: =SUM(AB10:AM10) | BP10: =SUM(AN10:AY10) | BQ10: =SUM(AZ10:BK10)
B11: AE attrition | C11: # | D11: =Inputs!$D$21*Inputs!$D$140/12 | E11: =D12*Inputs!$D$140/12 | F11: =E12*Inputs!$D$140/12 | G11: =F12*Inputs!$D$140/12 | H11: =G12*Inputs!$D$140/12 | I11: =H12*Inputs!$D$140/12 | J11: =I12*Inputs!$D$140/12 | K11: =J12*Inputs!$D$140/12 | L11: =K12*Inputs!$D$140/12 | ... BK11: =BJ12*Inputs!$D$140/12 | BM11: =SUM(D11:O11) | BN11: =SUM(P11:AA11) | BO11: =SUM(AB11:AM11) | BP11: =SUM(AN11:AY11) | BQ11: =SUM(AZ11:BK11)
B12: AE headcount, closing | C12: # | D12: =Inputs!$D$21*(1-Inputs!$D$140/12)+D10 | E12: =D12*(1-Inputs!$D$140/12)+E10 | F12: =E12*(1-Inputs!$D$140/12)+F10 | G12: =F12*(1-Inputs!$D$140/12)+G10 | H12: =G12*(1-Inputs!$D$140/12)+H10 | I12: =H12*(1-Inputs!$D$140/12)+I10 | J12: =I12*(1-Inputs!$D$140/12)+J10 | K12: =J12*(1-Inputs!$D$140/12)+K10 | L12: =K12*(1-Inputs!$D$140/12)+L10 | ... BK12: =BJ12*(1-Inputs!$D$140/12)+BK10 | BM12: =O12 | BN12: =AA12 | BO12: =AM12 | BP12: =AY12 | BQ12: =BK12
B13: Unramped drag | C13: # | D13: =D10*(1-INDEX(Inputs!$D$25:$H$25,1,D$6-2025)) | E13: =E10*(1-INDEX(Inputs!$D$25:$H$25,1,E$6-2025))+D10*(1-INDEX(Inputs!$D$26:$H$26,1,E$6-2025)) | F13: =F10*(1-INDEX(Inputs!$D$25:$H$25,1,F$6-2025))+E10*(1-INDEX(Inputs!$D$26:$H$26,1,F$6-2025))+D10*(1-INDEX(Inputs!$D$27:$H$27,1,F$6-2025)) | G13: =G10*(1-INDEX(Inputs!$D$25:$H$25,1,G$6-2025))+F10*(1-INDEX(Inputs!$D$26:$H$26,1,G$6-2025))+E10*(1-INDEX(Inputs!$D$27:$H$27,1,G$6-2025))+D10*(1-INDEX(Inputs!$D$28:$H$28,1,G$6-2025)) | H13: =H10*(1-INDEX(Inputs!$D$25:$H$25,1,H$6-2025))+G10*(1-INDEX(Inputs!$D$26:$H$26,1,H$6-2025))+F10*(1-INDEX(Inputs!$D$27:$H$27,1,H$6-2025))+E10*(1-INDEX(Inputs!$D$28:$H$28,1,H$6-2025))+D10*(1-INDEX(Inputs!$D$29:$H$29,1,H$6-2025)) | I13: =I10*(1-INDEX(Inputs!$D$25:$H$25,1,I$6-2025))+H10*(1-INDEX(Inputs!$D$26:$H$26,1,I$6-2025))+G10*(1-INDEX(Inputs!$D$27:$H$27,1,I$6-2025))+F10*(1-INDEX(Inputs!$D$28:$H$28,1,I$6-2025))+E10*(1-INDEX(Inputs!$D$29:$H$29,1,I$6-2025)) | J13: =J10*(1-INDEX(Inputs!$D$25:$H$25,1,J$6-2025))+I10*(1-INDEX(Inputs!$D$26:$H$26,1,J$6-2025))+H10*(1-INDEX(Inputs!$D$27:$H$27,1,J$6-2025))+G10*(1-INDEX(Inputs!$D$28:$H$28,1,J$6-2025))+F10*(1-INDEX(Inputs!$D$29:$H$29,1,J$6-2025)) | K13: =K10*(1-INDEX(Inputs!$D$25:$H$25,1,K$6-2025))+J10*(1-INDEX(Inputs!$D$26:$H$26,1,K$6-2025))+I10*(1-INDEX(Inputs!$D$27:$H$27,1,K$6-2025))+H10*(1-INDEX(Inputs!$D$28:$H$28,1,K$6-2025))+G10*(1-INDEX(Inputs!$D$29:$H$29,1,K$6-2025)) | L13: =L10*(1-INDEX(Inputs!$D$25:$H$25,1,L$6-2025))+K10*(1-INDEX(Inputs!$D$26:$H$26,1,L$6-2025))+J10*(1-INDEX(Inputs!$D$27:$H$27,1,L$6-2025))+I10*(1-INDEX(Inputs!$D$28:$H$28,1,L$6-2025))+H10*(1-INDEX(Inputs!$D$29:$H$29,1,L$6-2025)) | M13: =M10*(1-INDEX(Inputs!$D$25:$H$25,1,M$6-2025))+L10*(1-INDEX(Inputs!$D$26:$H$26,1,M$6-2025))+K10*(1-INDEX(Inputs!$D$27:$H$27,1,M$6-2025))+J10*(1-INDEX(Inputs!$D$28:$H$28,1,M$6-2025))+I10*(1-INDEX(Inputs!$D$29:$H$29,1,M$6-2025)) | N13: =N10*(1-INDEX(Inputs!$D$25:$H$25,1,N$6-2025))+M10*(1-INDEX(Inputs!$D$26:$H$26,1,N$6-2025))+L10*(1-INDEX(Inputs!$D$27:$H$27,1,N$6-2025))+K10*(1-INDEX(Inputs!$D$28:$H$28,1,N$6-2025))+J10*(1-INDEX(Inputs!$D$29:$H$29,1,N$6-2025)) | O13: =O10*(1-INDEX(Inputs!$D$25:$H$25,1,O$6-2025))+N10*(1-INDEX(Inputs!$D$26:$H$26,1,O$6-2025))+M10*(1-INDEX(Inputs!$D$27:$H$27,1,O$6-2025))+L10*(1-INDEX(Inputs!$D$28:$H$28,1,O$6-2025))+K10*(1-INDEX(Inputs!$D$29:$H$29,1,O$6-2025)) | ... BK13: =BK10*(1-INDEX(Inputs!$D$25:$H$25,1,BK$6-2025))+BJ10*(1-INDEX(Inputs!$D$26:$H$26,1,BK$6-2025))+BI10*(1-INDEX(Inputs!$D$27:$H$27,1,BK$6-2025))+BH10*(1-INDEX(Inputs!$D$28:$H$28,1,BK$6-2025))+BG10*(1-INDEX(Inputs!$D$29:$H$29,1,BK$6-2025))
B14: Productive AE equivalents | C14: # | D14: =MAX(D12-D13,0) | E14: =MAX(E12-E13,0) | F14: =MAX(F12-F13,0) | G14: =MAX(G12-G13,0) | H14: =MAX(H12-H13,0) | I14: =MAX(I12-I13,0) | J14: =MAX(J12-J13,0) | K14: =MAX(K12-K13,0) | ... BK14: =MAX(BK12-BK13,0) | BM14: =O14 | BN14: =AA14 | BO14: =AM14 | BP14: =AY14 | BQ14: =BK14
B16: SELF SERVE
B17: New customers added | C17: # | D17: =Inputs!$D$82*(1+((1+Inputs!$D$83)^(1/12)-1))^0 | E17: =Inputs!$D$82*(1+((1+Inputs!$D$83)^(1/12)-1))^1 | F17: =Inputs!$D$82*(1+((1+Inputs!$D$83)^(1/12)-1))^2 | G17: =Inputs!$D$82*(1+((1+Inputs!$D$83)^(1/12)-1))^3 | H17: =Inputs!$D$82*(1+((1+Inputs!$D$83)^(1/12)-1))^4 | I17: =Inputs!$D$82*(1+((1+Inputs!$D$83)^(1/12)-1))^5 | J17: =Inputs!$D$82*(1+((1+Inputs!$D$83)^(1/12)-1))^6 | K17: =Inputs!$D$82*(1+((1+Inputs!$D$83)^(1/12)-1))^7 | L17: =Inputs!$D$82*(1+((1+Inputs!$D$83)^(1/12)-1))^8 | M17: =Inputs!$D$82*(1+((1+Inputs!$D$83)^(1/12)-1))^9 | N17: =Inputs!$D$82*(1+((1+Inputs!$D$83)^(1/12)-1))^10 | O17: =Inputs!$D$82*(1+((1+Inputs!$D$83)^(1/12)-1))^11 | P17: =Inputs!$D$82*(1+((1+Inputs!$D$83)^(1/12)-1))^12 | Q17: =Inputs!$D$82*(1+((1+Inputs!$D$83)^(1/12)-1))^13 | R17: =Inputs!$D$82*(1+((1+Inputs!$D$83)^(1/12)-1))^14 | S17: =Inputs!$D$82*(1+((1+Inputs!$D$83)^(1/12)-1))^15 | T17: =Inputs!$D$82*(1+((1+Inputs!$D$83)^(1/12)-1))^16 | U17: =Inputs!$D$82*(1+((1+Inputs!$D$83)^(1/12)-1))^17 | V17: =Inputs!$D$82*(1+((1+Inputs!$D$83)^(1/12)-1))^18 | W17: =Inputs!$D$82*(1+((1+Inputs!$D$83)^(1/12)-1))^19 | X17: =Inputs!$D$82*(1+((1+Inputs!$D$83)^(1/12)-1))^20 | Y17: =Inputs!$D$82*(1+((1+Inputs!$D$83)^(1/12)-1))^21 | Z17: =Inputs!$D$82*(1+((1+Inputs!$D$83)^(1/12)-1))^22 | AA17: =Inputs!$D$82*(1+((1+Inputs!$D$83)^(1/12)-1))^23 | AB17: =Inputs!$D$82*(1+((1+Inputs!$D$83)^(1/12)-1))^24 | AC17: =Inputs!$D$82*(1+((1+Inputs!$D$83)^(1/12)-1))^25 | AD17: =Inputs!$D$82*(1+((1+Inputs!$D$83)^(1/12)-1))^26 | AE17: =Inputs!$D$82*(1+((1+Inputs!$D$83)^(1/12)-1))^27 | AF17: =Inputs!$D$82*(1+((1+Inputs!$D$83)^(1/12)-1))^28 | AG17: =Inputs!$D$82*(1+((1+Inputs!$D$83)^(1/12)-1))^29 | AH17: =Inputs!$D$82*(1+((1+Inputs!$D$83)^(1/12)-1))^30 | AI17: =Inputs!$D$82*(1+((1+Inputs!$D$83)^(1/12)-1))^31 | AJ17: =Inputs!$D$82*(1+((1+Inputs!$D$83)^(1/12)-1))^32 | AK17: =Inputs!$D$82*(1+((1+Inputs!$D$83)^(1/12)-1))^33 | AL17: =Inputs!$D$82*(1+((1+Inputs!$D$83)^(1/12)-1))^34 | AM17: =Inputs!$D$82*(1+((1+Inputs!$D$83)^(1/12)-1))^35 | AN17: =Inputs!$D$82*(1+((1+Inputs!$D$83)^(1/12)-1))^36 | AO17: =Inputs!$D$82*(1+((1+Inputs!$D$83)^(1/12)-1))^37 | AP17: =Inputs!$D$82*(1+((1+Inputs!$D$83)^(1/12)-1))^38 | AQ17: =Inputs!$D$82*(1+((1+Inputs!$D$83)^(1/12)-1))^39 | AR17: =Inputs!$D$82*(1+((1+Inputs!$D$83)^(1/12)-1))^40 | AS17: =Inputs!$D$82*(1+((1+Inputs!$D$83)^(1/12)-1))^41 | AT17: =Inputs!$D$82*(1+((1+Inputs!$D$83)^(1/12)-1))^42 | AU17: =Inputs!$D$82*(1+((1+Inputs!$D$83)^(1/12)-1))^43 | AV17: =Inputs!$D$82*(1+((1+Inputs!$D$83)^(1/12)-1))^44 | AW17: =Inputs!$D$82*(1+((1+Inputs!$D$83)^(1/12)-1))^45 | AX17: =Inputs!$D$82*(1+((1+Inputs!$D$83)^(1/12)-1))^46 | AY17: =Inputs!$D$82*(1+((1+Inputs!$D$83)^(1/12)-1))^47 | AZ17: =Inputs!$D$82*(1+((1+Inputs!$D$83)^(1/12)-1))^48 | BA17: =Inputs!$D$82*(1+((1+Inputs!$D$83)^(1/12)-1))^49 | BB17: =Inputs!$D$82*(1+((1+Inputs!$D$83)^(1/12)-1))^50 | BC17: =Inputs!$D$82*(1+((1+Inputs!$D$83)^(1/12)-1))^51 | BD17: =Inputs!$D$82*(1+((1+Inputs!$D$83)^(1/12)-1))^52 | BE17: =Inputs!$D$82*(1+((1+Inputs!$D$83)^(1/12)-1))^53 | BF17: =Inputs!$D$82*(1+((1+Inputs!$D$83)^(1/12)-1))^54 | BG17: =Inputs!$D$82*(1+((1+Inputs!$D$83)^(1/12)-1))^55 | BH17: =Inputs!$D$82*(1+((1+Inputs!$D$83)^(1/12)-1))^56 | BI17: =Inputs!$D$82*(1+((1+Inputs!$D$83)^(1/12)-1))^57 | BJ17: =Inputs!$D$82*(1+((1+Inputs!$D$83)^(1/12)-1))^58 | BK17: =Inputs!$D$82*(1+((1+Inputs!$D$83)^(1/12)-1))^59
B18: Churned customers | C18: # | D18: =Inputs!$D$18*Inputs!$D$84 | E18: =D20*Inputs!$D$84 | F18: =E20*Inputs!$D$84 | G18: =F20*Inputs!$D$84 | H18: =G20*Inputs!$D$84 | I18: =H20*Inputs!$D$84 | J18: =I20*Inputs!$D$84 | K18: =J20*Inputs!$D$84 | L18: =K20*Inputs!$D$84 | ... BK18: =BJ20*Inputs!$D$84
B19: Converted into enterprise | C19: # | D19: =Inputs!$D$18*Inputs!$D$85 | E19: =D20*Inputs!$D$85 | F19: =E20*Inputs!$D$85 | G19: =F20*Inputs!$D$85 | H19: =G20*Inputs!$D$85 | I19: =H20*Inputs!$D$85 | J19: =I20*Inputs!$D$85 | K19: =J20*Inputs!$D$85 | L19: =K20*Inputs!$D$85 | ... BK19: =BJ20*Inputs!$D$85
B20: Self serve customers, closing | C20: # | D20: =Inputs!$D$18+D17-D18-D19 | E20: =D20+E17-E18-E19 | F20: =E20+F17-F18-F19 | G20: =F20+G17-G18-G19 | H20: =G20+H17-H18-H19 | I20: =H20+I17-I18-I19 | J20: =I20+J17-J18-J19 | K20: =J20+K17-K18-K19 | L20: =K20+L17-L18-L19 | ... BK20: =BJ20+BK17-BK18-BK19 | BM20: =O20 | BN20: =AA20 | BO20: =AM20 | BP20: =AY20 | BQ20: =BK20
B21: Self serve ARR | C21: $ | D21: =D20*Inputs!$D$78*(1+((1+Inputs!$D$79)^(1/12)-1))^0 | E21: =E20*Inputs!$D$78*(1+((1+Inputs!$D$79)^(1/12)-1))^1 | F21: =F20*Inputs!$D$78*(1+((1+Inputs!$D$79)^(1/12)-1))^2 | G21: =G20*Inputs!$D$78*(1+((1+Inputs!$D$79)^(1/12)-1))^3 | H21: =H20*Inputs!$D$78*(1+((1+Inputs!$D$79)^(1/12)-1))^4 | I21: =I20*Inputs!$D$78*(1+((1+Inputs!$D$79)^(1/12)-1))^5 | J21: =J20*Inputs!$D$78*(1+((1+Inputs!$D$79)^(1/12)-1))^6 | K21: =K20*Inputs!$D$78*(1+((1+Inputs!$D$79)^(1/12)-1))^7 | L21: =L20*Inputs!$D$78*(1+((1+Inputs!$D$79)^(1/12)-1))^8 | M21: =M20*Inputs!$D$78*(1+((1+Inputs!$D$79)^(1/12)-1))^9 | N21: =N20*Inputs!$D$78*(1+((1+Inputs!$D$79)^(1/12)-1))^10 | O21: =O20*Inputs!$D$78*(1+((1+Inputs!$D$79)^(1/12)-1))^11 | P21: =P20*Inputs!$D$78*(1+((1+Inputs!$D$79)^(1/12)-1))^12 | Q21: =Q20*Inputs!$D$78*(1+((1+Inputs!$D$79)^(1/12)-1))^13 | R21: =R20*Inputs!$D$78*(1+((1+Inputs!$D$79)^(1/12)-1))^14 | S21: =S20*Inputs!$D$78*(1+((1+Inputs!$D$79)^(1/12)-1))^15 | T21: =T20*Inputs!$D$78*(1+((1+Inputs!$D$79)^(1/12)-1))^16 | U21: =U20*Inputs!$D$78*(1+((1+Inputs!$D$79)^(1/12)-1))^17 | V21: =V20*Inputs!$D$78*(1+((1+Inputs!$D$79)^(1/12)-1))^18 | W21: =W20*Inputs!$D$78*(1+((1+Inputs!$D$79)^(1/12)-1))^19 | X21: =X20*Inputs!$D$78*(1+((1+Inputs!$D$79)^(1/12)-1))^20 | Y21: =Y20*Inputs!$D$78*(1+((1+Inputs!$D$79)^(1/12)-1))^21 | Z21: =Z20*Inputs!$D$78*(1+((1+Inputs!$D$79)^(1/12)-1))^22 | AA21: =AA20*Inputs!$D$78*(1+((1+Inputs!$D$79)^(1/12)-1))^23 | AB21: =AB20*Inputs!$D$78*(1+((1+Inputs!$D$79)^(1/12)-1))^24 | AC21: =AC20*Inputs!$D$78*(1+((1+Inputs!$D$79)^(1/12)-1))^25 | AD21: =AD20*Inputs!$D$78*(1+((1+Inputs!$D$79)^(1/12)-1))^26 | AE21: =AE20*Inputs!$D$78*(1+((1+Inputs!$D$79)^(1/12)-1))^27 | AF21: =AF20*Inputs!$D$78*(1+((1+Inputs!$D$79)^(1/12)-1))^28 | AG21: =AG20*Inputs!$D$78*(1+((1+Inputs!$D$79)^(1/12)-1))^29 | AH21: =AH20*Inputs!$D$78*(1+((1+Inputs!$D$79)^(1/12)-1))^30 | AI21: =AI20*Inputs!$D$78*(1+((1+Inputs!$D$79)^(1/12)-1))^31 | AJ21: =AJ20*Inputs!$D$78*(1+((1+Inputs!$D$79)^(1/12)-1))^32 | AK21: =AK20*Inputs!$D$78*(1+((1+Inputs!$D$79)^(1/12)-1))^33 | AL21: =AL20*Inputs!$D$78*(1+((1+Inputs!$D$79)^(1/12)-1))^34 | AM21: =AM20*Inputs!$D$78*(1+((1+Inputs!$D$79)^(1/12)-1))^35 | AN21: =AN20*Inputs!$D$78*(1+((1+Inputs!$D$79)^(1/12)-1))^36 | AO21: =AO20*Inputs!$D$78*(1+((1+Inputs!$D$79)^(1/12)-1))^37 | AP21: =AP20*Inputs!$D$78*(1+((1+Inputs!$D$79)^(1/12)-1))^38 | AQ21: =AQ20*Inputs!$D$78*(1+((1+Inputs!$D$79)^(1/12)-1))^39 | AR21: =AR20*Inputs!$D$78*(1+((1+Inputs!$D$79)^(1/12)-1))^40 | AS21: =AS20*Inputs!$D$78*(1+((1+Inputs!$D$79)^(1/12)-1))^41 | AT21: =AT20*Inputs!$D$78*(1+((1+Inputs!$D$79)^(1/12)-1))^42 | AU21: =AU20*Inputs!$D$78*(1+((1+Inputs!$D$79)^(1/12)-1))^43 | AV21: =AV20*Inputs!$D$78*(1+((1+Inputs!$D$79)^(1/12)-1))^44 | AW21: =AW20*Inputs!$D$78*(1+((1+Inputs!$D$79)^(1/12)-1))^45 | AX21: =AX20*Inputs!$D$78*(1+((1+Inputs!$D$79)^(1/12)-1))^46 | AY21: =AY20*Inputs!$D$78*(1+((1+Inputs!$D$79)^(1/12)-1))^47 | AZ21: =AZ20*Inputs!$D$78*(1+((1+Inputs!$D$79)^(1/12)-1))^48 | BA21: =BA20*Inputs!$D$78*(1+((1+Inputs!$D$79)^(1/12)-1))^49 | BB21: =BB20*Inputs!$D$78*(1+((1+Inputs!$D$79)^(1/12)-1))^50 | BC21: =BC20*Inputs!$D$78*(1+((1+Inputs!$D$79)^(1/12)-1))^51 | BD21: =BD20*Inputs!$D$78*(1+((1+Inputs!$D$79)^(1/12)-1))^52 | BE21: =BE20*Inputs!$D$78*(1+((1+Inputs!$D$79)^(1/12)-1))^53 | BF21: =BF20*Inputs!$D$78*(1+((1+Inputs!$D$79)^(1/12)-1))^54 | BG21: =BG20*Inputs!$D$78*(1+((1+Inputs!$D$79)^(1/12)-1))^55 | BH21: =BH20*Inputs!$D$78*(1+((1+Inputs!$D$79)^(1/12)-1))^56 | BI21: =BI20*Inputs!$D$78*(1+((1+Inputs!$D$79)^(1/12)-1))^57 | BJ21: =BJ20*Inputs!$D$78*(1+((1+Inputs!$D$79)^(1/12)-1))^58 | BK21: =BK20*Inputs!$D$78*(1+((1+Inputs!$D$79)^(1/12)-1))^59 | BM21: =O21 | BN21: =AA21 | BO21: =AM21 | BP21: =AY21 | BQ21: =BK21
B23: ENTERPRISE BOOKINGS
B24: Quota per AE per month | C24: $ | D24: =Inputs!$D$22*(1+((1+Inputs!$D$23)^(1/12)-1))^0/12 | E24: =Inputs!$D$22*(1+((1+Inputs!$D$23)^(1/12)-1))^1/12 | F24: =Inputs!$D$22*(1+((1+Inputs!$D$23)^(1/12)-1))^2/12 | G24: =Inputs!$D$22*(1+((1+Inputs!$D$23)^(1/12)-1))^3/12 | H24: =Inputs!$D$22*(1+((1+Inputs!$D$23)^(1/12)-1))^4/12 | I24: =Inputs!$D$22*(1+((1+Inputs!$D$23)^(1/12)-1))^5/12 | J24: =Inputs!$D$22*(1+((1+Inputs!$D$23)^(1/12)-1))^6/12 | K24: =Inputs!$D$22*(1+((1+Inputs!$D$23)^(1/12)-1))^7/12 | L24: =Inputs!$D$22*(1+((1+Inputs!$D$23)^(1/12)-1))^8/12 | M24: =Inputs!$D$22*(1+((1+Inputs!$D$23)^(1/12)-1))^9/12 | N24: =Inputs!$D$22*(1+((1+Inputs!$D$23)^(1/12)-1))^10/12 | O24: =Inputs!$D$22*(1+((1+Inputs!$D$23)^(1/12)-1))^11/12 | P24: =Inputs!$D$22*(1+((1+Inputs!$D$23)^(1/12)-1))^12/12 | Q24: =Inputs!$D$22*(1+((1+Inputs!$D$23)^(1/12)-1))^13/12 | R24: =Inputs!$D$22*(1+((1+Inputs!$D$23)^(1/12)-1))^14/12 | S24: =Inputs!$D$22*(1+((1+Inputs!$D$23)^(1/12)-1))^15/12 | T24: =Inputs!$D$22*(1+((1+Inputs!$D$23)^(1/12)-1))^16/12 | U24: =Inputs!$D$22*(1+((1+Inputs!$D$23)^(1/12)-1))^17/12 | V24: =Inputs!$D$22*(1+((1+Inputs!$D$23)^(1/12)-1))^18/12 | W24: =Inputs!$D$22*(1+((1+Inputs!$D$23)^(1/12)-1))^19/12 | X24: =Inputs!$D$22*(1+((1+Inputs!$D$23)^(1/12)-1))^20/12 | Y24: =Inputs!$D$22*(1+((1+Inputs!$D$23)^(1/12)-1))^21/12 | Z24: =Inputs!$D$22*(1+((1+Inputs!$D$23)^(1/12)-1))^22/12 | AA24: =Inputs!$D$22*(1+((1+Inputs!$D$23)^(1/12)-1))^23/12 | AB24: =Inputs!$D$22*(1+((1+Inputs!$D$23)^(1/12)-1))^24/12 | AC24: =Inputs!$D$22*(1+((1+Inputs!$D$23)^(1/12)-1))^25/12 | AD24: =Inputs!$D$22*(1+((1+Inputs!$D$23)^(1/12)-1))^26/12 | AE24: =Inputs!$D$22*(1+((1+Inputs!$D$23)^(1/12)-1))^27/12 | AF24: =Inputs!$D$22*(1+((1+Inputs!$D$23)^(1/12)-1))^28/12 | AG24: =Inputs!$D$22*(1+((1+Inputs!$D$23)^(1/12)-1))^29/12 | AH24: =Inputs!$D$22*(1+((1+Inputs!$D$23)^(1/12)-1))^30/12 | AI24: =Inputs!$D$22*(1+((1+Inputs!$D$23)^(1/12)-1))^31/12 | AJ24: =Inputs!$D$22*(1+((1+Inputs!$D$23)^(1/12)-1))^32/12 | AK24: =Inputs!$D$22*(1+((1+Inputs!$D$23)^(1/12)-1))^33/12 | AL24: =Inputs!$D$22*(1+((1+Inputs!$D$23)^(1/12)-1))^34/12 | AM24: =Inputs!$D$22*(1+((1+Inputs!$D$23)^(1/12)-1))^35/12 | AN24: =Inputs!$D$22*(1+((1+Inputs!$D$23)^(1/12)-1))^36/12 | AO24: =Inputs!$D$22*(1+((1+Inputs!$D$23)^(1/12)-1))^37/12 | AP24: =Inputs!$D$22*(1+((1+Inputs!$D$23)^(1/12)-1))^38/12 | AQ24: =Inputs!$D$22*(1+((1+Inputs!$D$23)^(1/12)-1))^39/12 | AR24: =Inputs!$D$22*(1+((1+Inputs!$D$23)^(1/12)-1))^40/12 | AS24: =Inputs!$D$22*(1+((1+Inputs!$D$23)^(1/12)-1))^41/12 | AT24: =Inputs!$D$22*(1+((1+Inputs!$D$23)^(1/12)-1))^42/12 | AU24: =Inputs!$D$22*(1+((1+Inputs!$D$23)^(1/12)-1))^43/12 | AV24: =Inputs!$D$22*(1+((1+Inputs!$D$23)^(1/12)-1))^44/12 | AW24: =Inputs!$D$22*(1+((1+Inputs!$D$23)^(1/12)-1))^45/12 | AX24: =Inputs!$D$22*(1+((1+Inputs!$D$23)^(1/12)-1))^46/12 | AY24: =Inputs!$D$22*(1+((1+Inputs!$D$23)^(1/12)-1))^47/12 | AZ24: =Inputs!$D$22*(1+((1+Inputs!$D$23)^(1/12)-1))^48/12 | BA24: =Inputs!$D$22*(1+((1+Inputs!$D$23)^(1/12)-1))^49/12 | BB24: =Inputs!$D$22*(1+((1+Inputs!$D$23)^(1/12)-1))^50/12 | BC24: =Inputs!$D$22*(1+((1+Inputs!$D$23)^(1/12)-1))^51/12 | BD24: =Inputs!$D$22*(1+((1+Inputs!$D$23)^(1/12)-1))^52/12 | BE24: =Inputs!$D$22*(1+((1+Inputs!$D$23)^(1/12)-1))^53/12 | BF24: =Inputs!$D$22*(1+((1+Inputs!$D$23)^(1/12)-1))^54/12 | BG24: =Inputs!$D$22*(1+((1+Inputs!$D$23)^(1/12)-1))^55/12 | BH24: =Inputs!$D$22*(1+((1+Inputs!$D$23)^(1/12)-1))^56/12 | BI24: =Inputs!$D$22*(1+((1+Inputs!$D$23)^(1/12)-1))^57/12 | BJ24: =Inputs!$D$22*(1+((1+Inputs!$D$23)^(1/12)-1))^58/12 | BK24: =Inputs!$D$22*(1+((1+Inputs!$D$23)^(1/12)-1))^59/12
B25: Quota attainment | C25: % | D25: =INDEX(Inputs!$D$42:$H$42,1,D$6-2025) | E25: =INDEX(Inputs!$D$42:$H$42,1,E$6-2025) | F25: =INDEX(Inputs!$D$42:$H$42,1,F$6-2025) | G25: =INDEX(Inputs!$D$42:$H$42,1,G$6-2025) | H25: =INDEX(Inputs!$D$42:$H$42,1,H$6-2025) | I25: =INDEX(Inputs!$D$42:$H$42,1,I$6-2025) | J25: =INDEX(Inputs!$D$42:$H$42,1,J$6-2025) | K25: =INDEX(Inputs!$D$42:$H$42,1,K$6-2025) | ... BK25: =INDEX(Inputs!$D$42:$H$42,1,BK$6-2025)
B26: New ARR from sales capacity | C26: $ | D26: =D14*D24*D25 | E26: =E14*E24*E25 | F26: =F14*F24*F25 | G26: =G14*G24*G25 | H26: =H14*H24*H25 | I26: =I14*I24*I25 | J26: =J14*J24*J25 | K26: =K14*K24*K25 | ... BK26: =BK14*BK24*BK25 | BM26: =SUM(D26:O26) | BN26: =SUM(P26:AA26) | BO26: =SUM(AB26:AM26) | BP26: =SUM(AN26:AY26) | BQ26: =SUM(AZ26:BK26)
B27: Enterprise ACV | C27: $ | D27: =Inputs!$D$76*(1+((1+Inputs!$D$77)^(1/12)-1))^0 | E27: =Inputs!$D$76*(1+((1+Inputs!$D$77)^(1/12)-1))^1 | F27: =Inputs!$D$76*(1+((1+Inputs!$D$77)^(1/12)-1))^2 | G27: =Inputs!$D$76*(1+((1+Inputs!$D$77)^(1/12)-1))^3 | H27: =Inputs!$D$76*(1+((1+Inputs!$D$77)^(1/12)-1))^4 | I27: =Inputs!$D$76*(1+((1+Inputs!$D$77)^(1/12)-1))^5 | J27: =Inputs!$D$76*(1+((1+Inputs!$D$77)^(1/12)-1))^6 | K27: =Inputs!$D$76*(1+((1+Inputs!$D$77)^(1/12)-1))^7 | L27: =Inputs!$D$76*(1+((1+Inputs!$D$77)^(1/12)-1))^8 | M27: =Inputs!$D$76*(1+((1+Inputs!$D$77)^(1/12)-1))^9 | N27: =Inputs!$D$76*(1+((1+Inputs!$D$77)^(1/12)-1))^10 | O27: =Inputs!$D$76*(1+((1+Inputs!$D$77)^(1/12)-1))^11 | P27: =Inputs!$D$76*(1+((1+Inputs!$D$77)^(1/12)-1))^12 | Q27: =Inputs!$D$76*(1+((1+Inputs!$D$77)^(1/12)-1))^13 | R27: =Inputs!$D$76*(1+((1+Inputs!$D$77)^(1/12)-1))^14 | S27: =Inputs!$D$76*(1+((1+Inputs!$D$77)^(1/12)-1))^15 | T27: =Inputs!$D$76*(1+((1+Inputs!$D$77)^(1/12)-1))^16 | U27: =Inputs!$D$76*(1+((1+Inputs!$D$77)^(1/12)-1))^17 | V27: =Inputs!$D$76*(1+((1+Inputs!$D$77)^(1/12)-1))^18 | W27: =Inputs!$D$76*(1+((1+Inputs!$D$77)^(1/12)-1))^19 | X27: =Inputs!$D$76*(1+((1+Inputs!$D$77)^(1/12)-1))^20 | Y27: =Inputs!$D$76*(1+((1+Inputs!$D$77)^(1/12)-1))^21 | Z27: =Inputs!$D$76*(1+((1+Inputs!$D$77)^(1/12)-1))^22 | AA27: =Inputs!$D$76*(1+((1+Inputs!$D$77)^(1/12)-1))^23 | AB27: =Inputs!$D$76*(1+((1+Inputs!$D$77)^(1/12)-1))^24 | AC27: =Inputs!$D$76*(1+((1+Inputs!$D$77)^(1/12)-1))^25 | AD27: =Inputs!$D$76*(1+((1+Inputs!$D$77)^(1/12)-1))^26 | AE27: =Inputs!$D$76*(1+((1+Inputs!$D$77)^(1/12)-1))^27 | AF27: =Inputs!$D$76*(1+((1+Inputs!$D$77)^(1/12)-1))^28 | AG27: =Inputs!$D$76*(1+((1+Inputs!$D$77)^(1/12)-1))^29 | AH27: =Inputs!$D$76*(1+((1+Inputs!$D$77)^(1/12)-1))^30 | AI27: =Inputs!$D$76*(1+((1+Inputs!$D$77)^(1/12)-1))^31 | AJ27: =Inputs!$D$76*(1+((1+Inputs!$D$77)^(1/12)-1))^32 | AK27: =Inputs!$D$76*(1+((1+Inputs!$D$77)^(1/12)-1))^33 | AL27: =Inputs!$D$76*(1+((1+Inputs!$D$77)^(1/12)-1))^34 | AM27: =Inputs!$D$76*(1+((1+Inputs!$D$77)^(1/12)-1))^35 | AN27: =Inputs!$D$76*(1+((1+Inputs!$D$77)^(1/12)-1))^36 | AO27: =Inputs!$D$76*(1+((1+Inputs!$D$77)^(1/12)-1))^37 | AP27: =Inputs!$D$76*(1+((1+Inputs!$D$77)^(1/12)-1))^38 | AQ27: =Inputs!$D$76*(1+((1+Inputs!$D$77)^(1/12)-1))^39 | AR27: =Inputs!$D$76*(1+((1+Inputs!$D$77)^(1/12)-1))^40 | AS27: =Inputs!$D$76*(1+((1+Inputs!$D$77)^(1/12)-1))^41 | AT27: =Inputs!$D$76*(1+((1+Inputs!$D$77)^(1/12)-1))^42 | AU27: =Inputs!$D$76*(1+((1+Inputs!$D$77)^(1/12)-1))^43 | AV27: =Inputs!$D$76*(1+((1+Inputs!$D$77)^(1/12)-1))^44 | AW27: =Inputs!$D$76*(1+((1+Inputs!$D$77)^(1/12)-1))^45 | AX27: =Inputs!$D$76*(1+((1+Inputs!$D$77)^(1/12)-1))^46 | AY27: =Inputs!$D$76*(1+((1+Inputs!$D$77)^(1/12)-1))^47 | AZ27: =Inputs!$D$76*(1+((1+Inputs!$D$77)^(1/12)-1))^48 | BA27: =Inputs!$D$76*(1+((1+Inputs!$D$77)^(1/12)-1))^49 | BB27: =Inputs!$D$76*(1+((1+Inputs!$D$77)^(1/12)-1))^50 | BC27: =Inputs!$D$76*(1+((1+Inputs!$D$77)^(1/12)-1))^51 | BD27: =Inputs!$D$76*(1+((1+Inputs!$D$77)^(1/12)-1))^52 | BE27: =Inputs!$D$76*(1+((1+Inputs!$D$77)^(1/12)-1))^53 | BF27: =Inputs!$D$76*(1+((1+Inputs!$D$77)^(1/12)-1))^54 | BG27: =Inputs!$D$76*(1+((1+Inputs!$D$77)^(1/12)-1))^55 | BH27: =Inputs!$D$76*(1+((1+Inputs!$D$77)^(1/12)-1))^56 | BI27: =Inputs!$D$76*(1+((1+Inputs!$D$77)^(1/12)-1))^57 | BJ27: =Inputs!$D$76*(1+((1+Inputs!$D$77)^(1/12)-1))^58 | BK27: =Inputs!$D$76*(1+((1+Inputs!$D$77)^(1/12)-1))^59
B28: New ARR from self serve conversions | C28: $ | D28: =D19*D27 | E28: =E19*E27 | F28: =F19*F27 | G28: =G19*G27 | H28: =H19*H27 | I28: =I19*I27 | J28: =J19*J27 | K28: =K19*K27 | ... BK28: =BK19*BK27 | BM28: =SUM(D28:O28) | BN28: =SUM(P28:AA28) | BO28: =SUM(AB28:AM28) | BP28: =SUM(AN28:AY28) | BQ28: =SUM(AZ28:BK28)
B29: Total new enterprise ARR | C29: $ | D29: =D26+D28 | E29: =E26+E28 | F29: =F26+F28 | G29: =G26+G28 | H29: =H26+H28 | I29: =I26+I28 | J29: =J26+J28 | K29: =K26+K28 | ... BK29: =BK26+BK28 | BM29: =SUM(D29:O29) | BN29: =SUM(P29:AA29) | BO29: =SUM(AB29:AM29) | BP29: =SUM(AN29:AY29) | BQ29: =SUM(AZ29:BK29)
B30: New logos | C30: # | D30: =D29/D27 | E30: =E29/E27 | F30: =F29/F27 | G30: =G29/G27 | H30: =H29/H27 | I30: =I29/I27 | J30: =J29/J27 | K30: =K29/K27 | ... BK30: =BK29/BK27 | BM30: =SUM(D30:O30) | BN30: =SUM(P30:AA30) | BO30: =SUM(AB30:AM30) | BP30: =SUM(AN30:AY30) | BQ30: =SUM(AZ30:BK30)

Sheet Rev-Cohorts
B2: Revenue: Dollar Cohort Triangle
B5: Month ending | D5: 46053 | E5: 46081 | F5: 46112 | G5: 46142 | H5: 46173 | I5: 46203 | J5: 46234 | K5: 46265 | L5: 46295 | M5: 46326 | N5: 46356 | O5: 46387 | P5: 46418 | Q5: 46446 | R5: 46477 | S5: 46507 | T5: 46538 | U5: 46568 | V5: 46599 | W5: 46630 | X5: 46660 | Y5: 46691 | Z5: 46721 | AA5: 46752 | AB5: 46783 | AC5: 46812 | AD5: 46843 | AE5: 46873 | AF5: 46904 | AG5: 46934 | AH5: 46965 | AI5: 46996 | AJ5: 47026 | AK5: 47057 | AL5: 47087 | AM5: 47118 | AN5: 47149 | AO5: 47177 | AP5: 47208 | AQ5: 47238 | AR5: 47269 | AS5: 47299 | AT5: 47330 | AU5: 47361 | AV5: 47391 | AW5: 47422 | AX5: 47452 | AY5: 47483 | AZ5: 47514 | BA5: 47542 | BB5: 47573 | BC5: 47603 | BD5: 47634 | BE5: 47664 | BF5: 47695 | BG5: 47726 | BH5: 47756 | BI5: 47787 | BJ5: 47817 | BK5: 47848 | BM5: FY2026 | BN5: FY2027 | BO5: FY2028 | BP5: FY2029 | BQ5: FY2030
B6: Fiscal year | D6: 2026 | E6: 2026 | F6: 2026 | G6: 2026 | H6: 2026 | I6: 2026 | J6: 2026 | K6: 2026 | L6: 2026 | M6: 2026 | N6: 2026 | O6: 2026 | P6: 2027 | Q6: 2027 | R6: 2027 | S6: 2027 | T6: 2027 | U6: 2027 | V6: 2027 | W6: 2027 | X6: 2027 | Y6: 2027 | Z6: 2027 | AA6: 2027 | AB6: 2028 | AC6: 2028 | AD6: 2028 | AE6: 2028 | AF6: 2028 | AG6: 2028 | AH6: 2028 | AI6: 2028 | AJ6: 2028 | AK6: 2028 | AL6: 2028 | AM6: 2028 | AN6: 2029 | AO6: 2029 | AP6: 2029 | AQ6: 2029 | AR6: 2029 | AS6: 2029 | AT6: 2029 | AU6: 2029 | AV6: 2029 | AW6: 2029 | AX6: 2029 | AY6: 2029 | AZ6: 2030 | BA6: 2030 | BB6: 2030 | BC6: 2030 | BD6: 2030 | BE6: 2030 | BF6: 2030 | BG6: 2030 | BH6: 2030 | BI6: 2030 | BJ6: 2030 | BK6: 2030
B7: Period | D7: 1 | E7: 2 | F7: 3 | G7: 4 | H7: 5 | I7: 6 | J7: 7 | K7: 8 | L7: 9 | M7: 10 | N7: 11 | O7: 12 | P7: 13 | Q7: 14 | R7: 15 | S7: 16 | T7: 17 | U7: 18 | V7: 19 | W7: 20 | X7: 21 | Y7: 22 | Z7: 23 | AA7: 24 | AB7: 25 | AC7: 26 | AD7: 27 | AE7: 28 | AF7: 29 | AG7: 30 | AH7: 31 | AI7: 32 | AJ7: 33 | AK7: 34 | AL7: 35 | AM7: 36 | AN7: 37 | AO7: 38 | AP7: 39 | AQ7: 40 | AR7: 41 | AS7: 42 | AT7: 43 | AU7: 44 | AV7: 45 | AW7: 46 | AX7: 47 | AY7: 48 | AZ7: 49 | BA7: 50 | BB7: 51 | BC7: 52 | BD7: 53 | BE7: 54 | BF7: 55 | BG7: 56 | BH7: 57 | BI7: 58 | BJ7: 59 | BK7: 60
B9: RETENTION DRIVERS
B10: Seat and usage expansion, monthly | C10: % | D10: =(1+INDEX(Inputs!$D$69:$H$69,1,D$6-2025))^(1/12)-1 | E10: =(1+INDEX(Inputs!$D$69:$H$69,1,E$6-2025))^(1/12)-1 | F10: =(1+INDEX(Inputs!$D$69:$H$69,1,F$6-2025))^(1/12)-1 | G10: =(1+INDEX(Inputs!$D$69:$H$69,1,G$6-2025))^(1/12)-1 | H10: =(1+INDEX(Inputs!$D$69:$H$69,1,H$6-2025))^(1/12)-1 | I10: =(1+INDEX(Inputs!$D$69:$H$69,1,I$6-2025))^(1/12)-1 | J10: =(1+INDEX(Inputs!$D$69:$H$69,1,J$6-2025))^(1/12)-1 | K10: =(1+INDEX(Inputs!$D$69:$H$69,1,K$6-2025))^(1/12)-1 | ... BK10: =(1+INDEX(Inputs!$D$69:$H$69,1,BK$6-2025))^(1/12)-1
B11: In contract churn, monthly | C11: % | D11: =Inputs!$D$62/12 | E11: =Inputs!$D$62/12 | F11: =Inputs!$D$62/12 | G11: =Inputs!$D$62/12 | H11: =Inputs!$D$62/12 | I11: =Inputs!$D$62/12 | J11: =Inputs!$D$62/12 | K11: =Inputs!$D$62/12 | ... BK11: =Inputs!$D$62/12
B12: First renewal survival | C12: % | D12: =INDEX(Inputs!$D$59:$H$59,1,D$6-2025) | E12: =INDEX(Inputs!$D$59:$H$59,1,E$6-2025) | F12: =INDEX(Inputs!$D$59:$H$59,1,F$6-2025) | G12: =INDEX(Inputs!$D$59:$H$59,1,G$6-2025) | H12: =INDEX(Inputs!$D$59:$H$59,1,H$6-2025) | I12: =INDEX(Inputs!$D$59:$H$59,1,I$6-2025) | J12: =INDEX(Inputs!$D$59:$H$59,1,J$6-2025) | K12: =INDEX(Inputs!$D$59:$H$59,1,K$6-2025) | ... BK12: =INDEX(Inputs!$D$59:$H$59,1,BK$6-2025)
B13: Later renewal survival | C13: % | D13: =INDEX(Inputs!$D$61:$H$61,1,D$6-2025) | E13: =INDEX(Inputs!$D$61:$H$61,1,E$6-2025) | F13: =INDEX(Inputs!$D$61:$H$61,1,F$6-2025) | G13: =INDEX(Inputs!$D$61:$H$61,1,G$6-2025) | H13: =INDEX(Inputs!$D$61:$H$61,1,H$6-2025) | I13: =INDEX(Inputs!$D$61:$H$61,1,I$6-2025) | J13: =INDEX(Inputs!$D$61:$H$61,1,J$6-2025) | K13: =INDEX(Inputs!$D$61:$H$61,1,K$6-2025) | ... BK13: =INDEX(Inputs!$D$61:$H$61,1,BK$6-2025)
B14: Renewal uplift, price plus cross sell | C14: % | D14: =Inputs!$D$71+INDEX(Inputs!$D$72:$H$72,1,D$6-2025) | E14: =Inputs!$D$71+INDEX(Inputs!$D$72:$H$72,1,E$6-2025) | F14: =Inputs!$D$71+INDEX(Inputs!$D$72:$H$72,1,F$6-2025) | G14: =Inputs!$D$71+INDEX(Inputs!$D$72:$H$72,1,G$6-2025) | H14: =Inputs!$D$71+INDEX(Inputs!$D$72:$H$72,1,H$6-2025) | I14: =Inputs!$D$71+INDEX(Inputs!$D$72:$H$72,1,I$6-2025) | J14: =Inputs!$D$71+INDEX(Inputs!$D$72:$H$72,1,J$6-2025) | K14: =Inputs!$D$71+INDEX(Inputs!$D$72:$H$72,1,K$6-2025) | ... BK14: =Inputs!$D$71+INDEX(Inputs!$D$72:$H$72,1,BK$6-2025)
B16: COHORT TRIANGLE
B17: Opening base, spread evenly across the prior twelve months
B18: Opening slice, age 12 months at start | C18: $ | D18: =Inputs!$D$15/12*(1+D$10)*(1-D$11)*IF(MOD((12+D$7),12)=0,IF((12+D$7)=12,D$12,D$13)*(1+D$14),1) | E18: =D18*(1+E$10)*(1-E$11)*IF(MOD((12+E$7),12)=0,IF((12+E$7)=12,E$12,E$13)*(1+E$14),1) | F18: =E18*(1+F$10)*(1-F$11)*IF(MOD((12+F$7),12)=0,IF((12+F$7)=12,F$12,F$13)*(1+F$14),1) | G18: =F18*(1+G$10)*(1-G$11)*IF(MOD((12+G$7),12)=0,IF((12+G$7)=12,G$12,G$13)*(1+G$14),1) | H18: =G18*(1+H$10)*(1-H$11)*IF(MOD((12+H$7),12)=0,IF((12+H$7)=12,H$12,H$13)*(1+H$14),1) | I18: =H18*(1+I$10)*(1-I$11)*IF(MOD((12+I$7),12)=0,IF((12+I$7)=12,I$12,I$13)*(1+I$14),1) | J18: =I18*(1+J$10)*(1-J$11)*IF(MOD((12+J$7),12)=0,IF((12+J$7)=12,J$12,J$13)*(1+J$14),1) | K18: =J18*(1+K$10)*(1-K$11)*IF(MOD((12+K$7),12)=0,IF((12+K$7)=12,K$12,K$13)*(1+K$14),1) | L18: =K18*(1+L$10)*(1-L$11)*IF(MOD((12+L$7),12)=0,IF((12+L$7)=12,L$12,L$13)*(1+L$14),1) | ... BK18: =BJ18*(1+BK$10)*(1-BK$11)*IF(MOD((12+BK$7),12)=0,IF((12+BK$7)=12,BK$12,BK$13)*(1+BK$14),1)
B19: Opening slice, age 11 months at start | C19: $ | D19: =Inputs!$D$15/12*(1+D$10)*(1-D$11)*IF(MOD((11+D$7),12)=0,IF((11+D$7)=12,D$12,D$13)*(1+D$14),1) | E19: =D19*(1+E$10)*(1-E$11)*IF(MOD((11+E$7),12)=0,IF((11+E$7)=12,E$12,E$13)*(1+E$14),1) | F19: =E19*(1+F$10)*(1-F$11)*IF(MOD((11+F$7),12)=0,IF((11+F$7)=12,F$12,F$13)*(1+F$14),1) | G19: =F19*(1+G$10)*(1-G$11)*IF(MOD((11+G$7),12)=0,IF((11+G$7)=12,G$12,G$13)*(1+G$14),1) | H19: =G19*(1+H$10)*(1-H$11)*IF(MOD((11+H$7),12)=0,IF((11+H$7)=12,H$12,H$13)*(1+H$14),1) | I19: =H19*(1+I$10)*(1-I$11)*IF(MOD((11+I$7),12)=0,IF((11+I$7)=12,I$12,I$13)*(1+I$14),1) | J19: =I19*(1+J$10)*(1-J$11)*IF(MOD((11+J$7),12)=0,IF((11+J$7)=12,J$12,J$13)*(1+J$14),1) | K19: =J19*(1+K$10)*(1-K$11)*IF(MOD((11+K$7),12)=0,IF((11+K$7)=12,K$12,K$13)*(1+K$14),1) | L19: =K19*(1+L$10)*(1-L$11)*IF(MOD((11+L$7),12)=0,IF((11+L$7)=12,L$12,L$13)*(1+L$14),1) | ... BK19: =BJ19*(1+BK$10)*(1-BK$11)*IF(MOD((11+BK$7),12)=0,IF((11+BK$7)=12,BK$12,BK$13)*(1+BK$14),1)
B20: Opening slice, age 10 months at start | C20: $ | D20: =Inputs!$D$15/12*(1+D$10)*(1-D$11)*IF(MOD((10+D$7),12)=0,IF((10+D$7)=12,D$12,D$13)*(1+D$14),1) | E20: =D20*(1+E$10)*(1-E$11)*IF(MOD((10+E$7),12)=0,IF((10+E$7)=12,E$12,E$13)*(1+E$14),1) | F20: =E20*(1+F$10)*(1-F$11)*IF(MOD((10+F$7),12)=0,IF((10+F$7)=12,F$12,F$13)*(1+F$14),1) | G20: =F20*(1+G$10)*(1-G$11)*IF(MOD((10+G$7),12)=0,IF((10+G$7)=12,G$12,G$13)*(1+G$14),1) | H20: =G20*(1+H$10)*(1-H$11)*IF(MOD((10+H$7),12)=0,IF((10+H$7)=12,H$12,H$13)*(1+H$14),1) | I20: =H20*(1+I$10)*(1-I$11)*IF(MOD((10+I$7),12)=0,IF((10+I$7)=12,I$12,I$13)*(1+I$14),1) | J20: =I20*(1+J$10)*(1-J$11)*IF(MOD((10+J$7),12)=0,IF((10+J$7)=12,J$12,J$13)*(1+J$14),1) | K20: =J20*(1+K$10)*(1-K$11)*IF(MOD((10+K$7),12)=0,IF((10+K$7)=12,K$12,K$13)*(1+K$14),1) | L20: =K20*(1+L$10)*(1-L$11)*IF(MOD((10+L$7),12)=0,IF((10+L$7)=12,L$12,L$13)*(1+L$14),1) | ... BK20: =BJ20*(1+BK$10)*(1-BK$11)*IF(MOD((10+BK$7),12)=0,IF((10+BK$7)=12,BK$12,BK$13)*(1+BK$14),1)
B21: Opening slice, age 9 months at start | C21: $ | D21: =Inputs!$D$15/12*(1+D$10)*(1-D$11)*IF(MOD((9+D$7),12)=0,IF((9+D$7)=12,D$12,D$13)*(1+D$14),1) | E21: =D21*(1+E$10)*(1-E$11)*IF(MOD((9+E$7),12)=0,IF((9+E$7)=12,E$12,E$13)*(1+E$14),1) | F21: =E21*(1+F$10)*(1-F$11)*IF(MOD((9+F$7),12)=0,IF((9+F$7)=12,F$12,F$13)*(1+F$14),1) | G21: =F21*(1+G$10)*(1-G$11)*IF(MOD((9+G$7),12)=0,IF((9+G$7)=12,G$12,G$13)*(1+G$14),1) | H21: =G21*(1+H$10)*(1-H$11)*IF(MOD((9+H$7),12)=0,IF((9+H$7)=12,H$12,H$13)*(1+H$14),1) | I21: =H21*(1+I$10)*(1-I$11)*IF(MOD((9+I$7),12)=0,IF((9+I$7)=12,I$12,I$13)*(1+I$14),1) | J21: =I21*(1+J$10)*(1-J$11)*IF(MOD((9+J$7),12)=0,IF((9+J$7)=12,J$12,J$13)*(1+J$14),1) | K21: =J21*(1+K$10)*(1-K$11)*IF(MOD((9+K$7),12)=0,IF((9+K$7)=12,K$12,K$13)*(1+K$14),1) | L21: =K21*(1+L$10)*(1-L$11)*IF(MOD((9+L$7),12)=0,IF((9+L$7)=12,L$12,L$13)*(1+L$14),1) | ... BK21: =BJ21*(1+BK$10)*(1-BK$11)*IF(MOD((9+BK$7),12)=0,IF((9+BK$7)=12,BK$12,BK$13)*(1+BK$14),1)
B22: Opening slice, age 8 months at start | C22: $ | D22: =Inputs!$D$15/12*(1+D$10)*(1-D$11)*IF(MOD((8+D$7),12)=0,IF((8+D$7)=12,D$12,D$13)*(1+D$14),1) | E22: =D22*(1+E$10)*(1-E$11)*IF(MOD((8+E$7),12)=0,IF((8+E$7)=12,E$12,E$13)*(1+E$14),1) | F22: =E22*(1+F$10)*(1-F$11)*IF(MOD((8+F$7),12)=0,IF((8+F$7)=12,F$12,F$13)*(1+F$14),1) | G22: =F22*(1+G$10)*(1-G$11)*IF(MOD((8+G$7),12)=0,IF((8+G$7)=12,G$12,G$13)*(1+G$14),1) | H22: =G22*(1+H$10)*(1-H$11)*IF(MOD((8+H$7),12)=0,IF((8+H$7)=12,H$12,H$13)*(1+H$14),1) | I22: =H22*(1+I$10)*(1-I$11)*IF(MOD((8+I$7),12)=0,IF((8+I$7)=12,I$12,I$13)*(1+I$14),1) | J22: =I22*(1+J$10)*(1-J$11)*IF(MOD((8+J$7),12)=0,IF((8+J$7)=12,J$12,J$13)*(1+J$14),1) | K22: =J22*(1+K$10)*(1-K$11)*IF(MOD((8+K$7),12)=0,IF((8+K$7)=12,K$12,K$13)*(1+K$14),1) | L22: =K22*(1+L$10)*(1-L$11)*IF(MOD((8+L$7),12)=0,IF((8+L$7)=12,L$12,L$13)*(1+L$14),1) | ... BK22: =BJ22*(1+BK$10)*(1-BK$11)*IF(MOD((8+BK$7),12)=0,IF((8+BK$7)=12,BK$12,BK$13)*(1+BK$14),1)
B23: Opening slice, age 7 months at start | C23: $ | D23: =Inputs!$D$15/12*(1+D$10)*(1-D$11)*IF(MOD((7+D$7),12)=0,IF((7+D$7)=12,D$12,D$13)*(1+D$14),1) | E23: =D23*(1+E$10)*(1-E$11)*IF(MOD((7+E$7),12)=0,IF((7+E$7)=12,E$12,E$13)*(1+E$14),1) | F23: =E23*(1+F$10)*(1-F$11)*IF(MOD((7+F$7),12)=0,IF((7+F$7)=12,F$12,F$13)*(1+F$14),1) | G23: =F23*(1+G$10)*(1-G$11)*IF(MOD((7+G$7),12)=0,IF((7+G$7)=12,G$12,G$13)*(1+G$14),1) | H23: =G23*(1+H$10)*(1-H$11)*IF(MOD((7+H$7),12)=0,IF((7+H$7)=12,H$12,H$13)*(1+H$14),1) | I23: =H23*(1+I$10)*(1-I$11)*IF(MOD((7+I$7),12)=0,IF((7+I$7)=12,I$12,I$13)*(1+I$14),1) | J23: =I23*(1+J$10)*(1-J$11)*IF(MOD((7+J$7),12)=0,IF((7+J$7)=12,J$12,J$13)*(1+J$14),1) | K23: =J23*(1+K$10)*(1-K$11)*IF(MOD((7+K$7),12)=0,IF((7+K$7)=12,K$12,K$13)*(1+K$14),1) | L23: =K23*(1+L$10)*(1-L$11)*IF(MOD((7+L$7),12)=0,IF((7+L$7)=12,L$12,L$13)*(1+L$14),1) | ... BK23: =BJ23*(1+BK$10)*(1-BK$11)*IF(MOD((7+BK$7),12)=0,IF((7+BK$7)=12,BK$12,BK$13)*(1+BK$14),1)
B24: Opening slice, age 6 months at start | C24: $ | D24: =Inputs!$D$15/12*(1+D$10)*(1-D$11)*IF(MOD((6+D$7),12)=0,IF((6+D$7)=12,D$12,D$13)*(1+D$14),1) | E24: =D24*(1+E$10)*(1-E$11)*IF(MOD((6+E$7),12)=0,IF((6+E$7)=12,E$12,E$13)*(1+E$14),1) | F24: =E24*(1+F$10)*(1-F$11)*IF(MOD((6+F$7),12)=0,IF((6+F$7)=12,F$12,F$13)*(1+F$14),1) | G24: =F24*(1+G$10)*(1-G$11)*IF(MOD((6+G$7),12)=0,IF((6+G$7)=12,G$12,G$13)*(1+G$14),1) | H24: =G24*(1+H$10)*(1-H$11)*IF(MOD((6+H$7),12)=0,IF((6+H$7)=12,H$12,H$13)*(1+H$14),1) | I24: =H24*(1+I$10)*(1-I$11)*IF(MOD((6+I$7),12)=0,IF((6+I$7)=12,I$12,I$13)*(1+I$14),1) | J24: =I24*(1+J$10)*(1-J$11)*IF(MOD((6+J$7),12)=0,IF((6+J$7)=12,J$12,J$13)*(1+J$14),1) | K24: =J24*(1+K$10)*(1-K$11)*IF(MOD((6+K$7),12)=0,IF((6+K$7)=12,K$12,K$13)*(1+K$14),1) | L24: =K24*(1+L$10)*(1-L$11)*IF(MOD((6+L$7),12)=0,IF((6+L$7)=12,L$12,L$13)*(1+L$14),1) | ... BK24: =BJ24*(1+BK$10)*(1-BK$11)*IF(MOD((6+BK$7),12)=0,IF((6+BK$7)=12,BK$12,BK$13)*(1+BK$14),1)
B25: Opening slice, age 5 months at start | C25: $ | D25: =Inputs!$D$15/12*(1+D$10)*(1-D$11)*IF(MOD((5+D$7),12)=0,IF((5+D$7)=12,D$12,D$13)*(1+D$14),1) | E25: =D25*(1+E$10)*(1-E$11)*IF(MOD((5+E$7),12)=0,IF((5+E$7)=12,E$12,E$13)*(1+E$14),1) | F25: =E25*(1+F$10)*(1-F$11)*IF(MOD((5+F$7),12)=0,IF((5+F$7)=12,F$12,F$13)*(1+F$14),1) | G25: =F25*(1+G$10)*(1-G$11)*IF(MOD((5+G$7),12)=0,IF((5+G$7)=12,G$12,G$13)*(1+G$14),1) | H25: =G25*(1+H$10)*(1-H$11)*IF(MOD((5+H$7),12)=0,IF((5+H$7)=12,H$12,H$13)*(1+H$14),1) | I25: =H25*(1+I$10)*(1-I$11)*IF(MOD((5+I$7),12)=0,IF((5+I$7)=12,I$12,I$13)*(1+I$14),1) | J25: =I25*(1+J$10)*(1-J$11)*IF(MOD((5+J$7),12)=0,IF((5+J$7)=12,J$12,J$13)*(1+J$14),1) | K25: =J25*(1+K$10)*(1-K$11)*IF(MOD((5+K$7),12)=0,IF((5+K$7)=12,K$12,K$13)*(1+K$14),1) | L25: =K25*(1+L$10)*(1-L$11)*IF(MOD((5+L$7),12)=0,IF((5+L$7)=12,L$12,L$13)*(1+L$14),1) | ... BK25: =BJ25*(1+BK$10)*(1-BK$11)*IF(MOD((5+BK$7),12)=0,IF((5+BK$7)=12,BK$12,BK$13)*(1+BK$14),1)
B26: Opening slice, age 4 months at start | C26: $ | D26: =Inputs!$D$15/12*(1+D$10)*(1-D$11)*IF(MOD((4+D$7),12)=0,IF((4+D$7)=12,D$12,D$13)*(1+D$14),1) | E26: =D26*(1+E$10)*(1-E$11)*IF(MOD((4+E$7),12)=0,IF((4+E$7)=12,E$12,E$13)*(1+E$14),1) | F26: =E26*(1+F$10)*(1-F$11)*IF(MOD((4+F$7),12)=0,IF((4+F$7)=12,F$12,F$13)*(1+F$14),1) | G26: =F26*(1+G$10)*(1-G$11)*IF(MOD((4+G$7),12)=0,IF((4+G$7)=12,G$12,G$13)*(1+G$14),1) | H26: =G26*(1+H$10)*(1-H$11)*IF(MOD((4+H$7),12)=0,IF((4+H$7)=12,H$12,H$13)*(1+H$14),1) | I26: =H26*(1+I$10)*(1-I$11)*IF(MOD((4+I$7),12)=0,IF((4+I$7)=12,I$12,I$13)*(1+I$14),1) | J26: =I26*(1+J$10)*(1-J$11)*IF(MOD((4+J$7),12)=0,IF((4+J$7)=12,J$12,J$13)*(1+J$14),1) | K26: =J26*(1+K$10)*(1-K$11)*IF(MOD((4+K$7),12)=0,IF((4+K$7)=12,K$12,K$13)*(1+K$14),1) | L26: =K26*(1+L$10)*(1-L$11)*IF(MOD((4+L$7),12)=0,IF((4+L$7)=12,L$12,L$13)*(1+L$14),1) | ... BK26: =BJ26*(1+BK$10)*(1-BK$11)*IF(MOD((4+BK$7),12)=0,IF((4+BK$7)=12,BK$12,BK$13)*(1+BK$14),1)
B27: Opening slice, age 3 months at start | C27: $ | D27: =Inputs!$D$15/12*(1+D$10)*(1-D$11)*IF(MOD((3+D$7),12)=0,IF((3+D$7)=12,D$12,D$13)*(1+D$14),1) | E27: =D27*(1+E$10)*(1-E$11)*IF(MOD((3+E$7),12)=0,IF((3+E$7)=12,E$12,E$13)*(1+E$14),1) | F27: =E27*(1+F$10)*(1-F$11)*IF(MOD((3+F$7),12)=0,IF((3+F$7)=12,F$12,F$13)*(1+F$14),1) | G27: =F27*(1+G$10)*(1-G$11)*IF(MOD((3+G$7),12)=0,IF((3+G$7)=12,G$12,G$13)*(1+G$14),1) | H27: =G27*(1+H$10)*(1-H$11)*IF(MOD((3+H$7),12)=0,IF((3+H$7)=12,H$12,H$13)*(1+H$14),1) | I27: =H27*(1+I$10)*(1-I$11)*IF(MOD((3+I$7),12)=0,IF((3+I$7)=12,I$12,I$13)*(1+I$14),1) | J27: =I27*(1+J$10)*(1-J$11)*IF(MOD((3+J$7),12)=0,IF((3+J$7)=12,J$12,J$13)*(1+J$14),1) | K27: =J27*(1+K$10)*(1-K$11)*IF(MOD((3+K$7),12)=0,IF((3+K$7)=12,K$12,K$13)*(1+K$14),1) | L27: =K27*(1+L$10)*(1-L$11)*IF(MOD((3+L$7),12)=0,IF((3+L$7)=12,L$12,L$13)*(1+L$14),1) | ... BK27: =BJ27*(1+BK$10)*(1-BK$11)*IF(MOD((3+BK$7),12)=0,IF((3+BK$7)=12,BK$12,BK$13)*(1+BK$14),1)
B28: Opening slice, age 2 months at start | C28: $ | D28: =Inputs!$D$15/12*(1+D$10)*(1-D$11)*IF(MOD((2+D$7),12)=0,IF((2+D$7)=12,D$12,D$13)*(1+D$14),1) | E28: =D28*(1+E$10)*(1-E$11)*IF(MOD((2+E$7),12)=0,IF((2+E$7)=12,E$12,E$13)*(1+E$14),1) | F28: =E28*(1+F$10)*(1-F$11)*IF(MOD((2+F$7),12)=0,IF((2+F$7)=12,F$12,F$13)*(1+F$14),1) | G28: =F28*(1+G$10)*(1-G$11)*IF(MOD((2+G$7),12)=0,IF((2+G$7)=12,G$12,G$13)*(1+G$14),1) | H28: =G28*(1+H$10)*(1-H$11)*IF(MOD((2+H$7),12)=0,IF((2+H$7)=12,H$12,H$13)*(1+H$14),1) | I28: =H28*(1+I$10)*(1-I$11)*IF(MOD((2+I$7),12)=0,IF((2+I$7)=12,I$12,I$13)*(1+I$14),1) | J28: =I28*(1+J$10)*(1-J$11)*IF(MOD((2+J$7),12)=0,IF((2+J$7)=12,J$12,J$13)*(1+J$14),1) | K28: =J28*(1+K$10)*(1-K$11)*IF(MOD((2+K$7),12)=0,IF((2+K$7)=12,K$12,K$13)*(1+K$14),1) | L28: =K28*(1+L$10)*(1-L$11)*IF(MOD((2+L$7),12)=0,IF((2+L$7)=12,L$12,L$13)*(1+L$14),1) | ... BK28: =BJ28*(1+BK$10)*(1-BK$11)*IF(MOD((2+BK$7),12)=0,IF((2+BK$7)=12,BK$12,BK$13)*(1+BK$14),1)
B29: Opening slice, age 1 months at start | C29: $ | D29: =Inputs!$D$15/12*(1+D$10)*(1-D$11)*IF(MOD((1+D$7),12)=0,IF((1+D$7)=12,D$12,D$13)*(1+D$14),1) | E29: =D29*(1+E$10)*(1-E$11)*IF(MOD((1+E$7),12)=0,IF((1+E$7)=12,E$12,E$13)*(1+E$14),1) | F29: =E29*(1+F$10)*(1-F$11)*IF(MOD((1+F$7),12)=0,IF((1+F$7)=12,F$12,F$13)*(1+F$14),1) | G29: =F29*(1+G$10)*(1-G$11)*IF(MOD((1+G$7),12)=0,IF((1+G$7)=12,G$12,G$13)*(1+G$14),1) | H29: =G29*(1+H$10)*(1-H$11)*IF(MOD((1+H$7),12)=0,IF((1+H$7)=12,H$12,H$13)*(1+H$14),1) | I29: =H29*(1+I$10)*(1-I$11)*IF(MOD((1+I$7),12)=0,IF((1+I$7)=12,I$12,I$13)*(1+I$14),1) | J29: =I29*(1+J$10)*(1-J$11)*IF(MOD((1+J$7),12)=0,IF((1+J$7)=12,J$12,J$13)*(1+J$14),1) | K29: =J29*(1+K$10)*(1-K$11)*IF(MOD((1+K$7),12)=0,IF((1+K$7)=12,K$12,K$13)*(1+K$14),1) | L29: =K29*(1+L$10)*(1-L$11)*IF(MOD((1+L$7),12)=0,IF((1+L$7)=12,L$12,L$13)*(1+L$14),1) | ... BK29: =BJ29*(1+BK$10)*(1-BK$11)*IF(MOD((1+BK$7),12)=0,IF((1+BK$7)=12,BK$12,BK$13)*(1+BK$14),1)
B30: New cohorts, one per month of origination
B31: Cohort Jan-26 | C31: $ | D31: ='Rev-Capacity'!D29 | E31: =D31*(1+E$10)*(1-E$11)*IF(MOD((E$7-1),12)=0,IF((E$7-1)=12,E$12,E$13)*(1+E$14),1) | F31: =E31*(1+F$10)*(1-F$11)*IF(MOD((F$7-1),12)=0,IF((F$7-1)=12,F$12,F$13)*(1+F$14),1) | G31: =F31*(1+G$10)*(1-G$11)*IF(MOD((G$7-1),12)=0,IF((G$7-1)=12,G$12,G$13)*(1+G$14),1) | H31: =G31*(1+H$10)*(1-H$11)*IF(MOD((H$7-1),12)=0,IF((H$7-1)=12,H$12,H$13)*(1+H$14),1) | I31: =H31*(1+I$10)*(1-I$11)*IF(MOD((I$7-1),12)=0,IF((I$7-1)=12,I$12,I$13)*(1+I$14),1) | J31: =I31*(1+J$10)*(1-J$11)*IF(MOD((J$7-1),12)=0,IF((J$7-1)=12,J$12,J$13)*(1+J$14),1) | K31: =J31*(1+K$10)*(1-K$11)*IF(MOD((K$7-1),12)=0,IF((K$7-1)=12,K$12,K$13)*(1+K$14),1) | L31: =K31*(1+L$10)*(1-L$11)*IF(MOD((L$7-1),12)=0,IF((L$7-1)=12,L$12,L$13)*(1+L$14),1) | ... BK31: =BJ31*(1+BK$10)*(1-BK$11)*IF(MOD((BK$7-1),12)=0,IF((BK$7-1)=12,BK$12,BK$13)*(1+BK$14),1)
B32: Cohort Feb-26 | C32: $ | D32: =0 | E32: ='Rev-Capacity'!E29 | F32: =E32*(1+F$10)*(1-F$11)*IF(MOD((F$7-2),12)=0,IF((F$7-2)=12,F$12,F$13)*(1+F$14),1) | G32: =F32*(1+G$10)*(1-G$11)*IF(MOD((G$7-2),12)=0,IF((G$7-2)=12,G$12,G$13)*(1+G$14),1) | H32: =G32*(1+H$10)*(1-H$11)*IF(MOD((H$7-2),12)=0,IF((H$7-2)=12,H$12,H$13)*(1+H$14),1) | I32: =H32*(1+I$10)*(1-I$11)*IF(MOD((I$7-2),12)=0,IF((I$7-2)=12,I$12,I$13)*(1+I$14),1) | J32: =I32*(1+J$10)*(1-J$11)*IF(MOD((J$7-2),12)=0,IF((J$7-2)=12,J$12,J$13)*(1+J$14),1) | K32: =J32*(1+K$10)*(1-K$11)*IF(MOD((K$7-2),12)=0,IF((K$7-2)=12,K$12,K$13)*(1+K$14),1) | L32: =K32*(1+L$10)*(1-L$11)*IF(MOD((L$7-2),12)=0,IF((L$7-2)=12,L$12,L$13)*(1+L$14),1) | M32: =L32*(1+M$10)*(1-M$11)*IF(MOD((M$7-2),12)=0,IF((M$7-2)=12,M$12,M$13)*(1+M$14),1) | ... BK32: =BJ32*(1+BK$10)*(1-BK$11)*IF(MOD((BK$7-2),12)=0,IF((BK$7-2)=12,BK$12,BK$13)*(1+BK$14),1)
B33: Cohort Mar-26 | C33: $ | D33: =0 | E33: =0 | F33: ='Rev-Capacity'!F29 | G33: =F33*(1+G$10)*(1-G$11)*IF(MOD((G$7-3),12)=0,IF((G$7-3)=12,G$12,G$13)*(1+G$14),1) | H33: =G33*(1+H$10)*(1-H$11)*IF(MOD((H$7-3),12)=0,IF((H$7-3)=12,H$12,H$13)*(1+H$14),1) | I33: =H33*(1+I$10)*(1-I$11)*IF(MOD((I$7-3),12)=0,IF((I$7-3)=12,I$12,I$13)*(1+I$14),1) | J33: =I33*(1+J$10)*(1-J$11)*IF(MOD((J$7-3),12)=0,IF((J$7-3)=12,J$12,J$13)*(1+J$14),1) | K33: =J33*(1+K$10)*(1-K$11)*IF(MOD((K$7-3),12)=0,IF((K$7-3)=12,K$12,K$13)*(1+K$14),1) | L33: =K33*(1+L$10)*(1-L$11)*IF(MOD((L$7-3),12)=0,IF((L$7-3)=12,L$12,L$13)*(1+L$14),1) | M33: =L33*(1+M$10)*(1-M$11)*IF(MOD((M$7-3),12)=0,IF((M$7-3)=12,M$12,M$13)*(1+M$14),1) | N33: =M33*(1+N$10)*(1-N$11)*IF(MOD((N$7-3),12)=0,IF((N$7-3)=12,N$12,N$13)*(1+N$14),1) | ... BK33: =BJ33*(1+BK$10)*(1-BK$11)*IF(MOD((BK$7-3),12)=0,IF((BK$7-3)=12,BK$12,BK$13)*(1+BK$14),1)
B34: Cohort Apr-26 | C34: $ | D34: =0 | E34: =0 | F34: =0 | G34: ='Rev-Capacity'!G29 | H34: =G34*(1+H$10)*(1-H$11)*IF(MOD((H$7-4),12)=0,IF((H$7-4)=12,H$12,H$13)*(1+H$14),1) | I34: =H34*(1+I$10)*(1-I$11)*IF(MOD((I$7-4),12)=0,IF((I$7-4)=12,I$12,I$13)*(1+I$14),1) | J34: =I34*(1+J$10)*(1-J$11)*IF(MOD((J$7-4),12)=0,IF((J$7-4)=12,J$12,J$13)*(1+J$14),1) | K34: =J34*(1+K$10)*(1-K$11)*IF(MOD((K$7-4),12)=0,IF((K$7-4)=12,K$12,K$13)*(1+K$14),1) | L34: =K34*(1+L$10)*(1-L$11)*IF(MOD((L$7-4),12)=0,IF((L$7-4)=12,L$12,L$13)*(1+L$14),1) | M34: =L34*(1+M$10)*(1-M$11)*IF(MOD((M$7-4),12)=0,IF((M$7-4)=12,M$12,M$13)*(1+M$14),1) | N34: =M34*(1+N$10)*(1-N$11)*IF(MOD((N$7-4),12)=0,IF((N$7-4)=12,N$12,N$13)*(1+N$14),1) | O34: =N34*(1+O$10)*(1-O$11)*IF(MOD((O$7-4),12)=0,IF((O$7-4)=12,O$12,O$13)*(1+O$14),1) | ... BK34: =BJ34*(1+BK$10)*(1-BK$11)*IF(MOD((BK$7-4),12)=0,IF((BK$7-4)=12,BK$12,BK$13)*(1+BK$14),1)
B35: Cohort May-26 | C35: $ | D35: =0 | E35: =0 | F35: =0 | G35: =0 | H35: ='Rev-Capacity'!H29 | I35: =H35*(1+I$10)*(1-I$11)*IF(MOD((I$7-5),12)=0,IF((I$7-5)=12,I$12,I$13)*(1+I$14),1) | J35: =I35*(1+J$10)*(1-J$11)*IF(MOD((J$7-5),12)=0,IF((J$7-5)=12,J$12,J$13)*(1+J$14),1) | K35: =J35*(1+K$10)*(1-K$11)*IF(MOD((K$7-5),12)=0,IF((K$7-5)=12,K$12,K$13)*(1+K$14),1) | L35: =K35*(1+L$10)*(1-L$11)*IF(MOD((L$7-5),12)=0,IF((L$7-5)=12,L$12,L$13)*(1+L$14),1) | M35: =L35*(1+M$10)*(1-M$11)*IF(MOD((M$7-5),12)=0,IF((M$7-5)=12,M$12,M$13)*(1+M$14),1) | N35: =M35*(1+N$10)*(1-N$11)*IF(MOD((N$7-5),12)=0,IF((N$7-5)=12,N$12,N$13)*(1+N$14),1) | O35: =N35*(1+O$10)*(1-O$11)*IF(MOD((O$7-5),12)=0,IF((O$7-5)=12,O$12,O$13)*(1+O$14),1) | P35: =O35*(1+P$10)*(1-P$11)*IF(MOD((P$7-5),12)=0,IF((P$7-5)=12,P$12,P$13)*(1+P$14),1) | ... BK35: =BJ35*(1+BK$10)*(1-BK$11)*IF(MOD((BK$7-5),12)=0,IF((BK$7-5)=12,BK$12,BK$13)*(1+BK$14),1)
B36: Cohort Jun-26 | C36: $ | D36: =0 | E36: =0 | F36: =0 | G36: =0 | H36: =0 | I36: ='Rev-Capacity'!I29 | J36: =I36*(1+J$10)*(1-J$11)*IF(MOD((J$7-6),12)=0,IF((J$7-6)=12,J$12,J$13)*(1+J$14),1) | K36: =J36*(1+K$10)*(1-K$11)*IF(MOD((K$7-6),12)=0,IF((K$7-6)=12,K$12,K$13)*(1+K$14),1) | L36: =K36*(1+L$10)*(1-L$11)*IF(MOD((L$7-6),12)=0,IF((L$7-6)=12,L$12,L$13)*(1+L$14),1) | M36: =L36*(1+M$10)*(1-M$11)*IF(MOD((M$7-6),12)=0,IF((M$7-6)=12,M$12,M$13)*(1+M$14),1) | N36: =M36*(1+N$10)*(1-N$11)*IF(MOD((N$7-6),12)=0,IF((N$7-6)=12,N$12,N$13)*(1+N$14),1) | O36: =N36*(1+O$10)*(1-O$11)*IF(MOD((O$7-6),12)=0,IF((O$7-6)=12,O$12,O$13)*(1+O$14),1) | P36: =O36*(1+P$10)*(1-P$11)*IF(MOD((P$7-6),12)=0,IF((P$7-6)=12,P$12,P$13)*(1+P$14),1) | Q36: =P36*(1+Q$10)*(1-Q$11)*IF(MOD((Q$7-6),12)=0,IF((Q$7-6)=12,Q$12,Q$13)*(1+Q$14),1) | ... BK36: =BJ36*(1+BK$10)*(1-BK$11)*IF(MOD((BK$7-6),12)=0,IF((BK$7-6)=12,BK$12,BK$13)*(1+BK$14),1)
B37: Cohort Jul-26 | C37: $ | D37: =0 | E37: =0 | F37: =0 | G37: =0 | H37: =0 | I37: =0 | J37: ='Rev-Capacity'!J29 | K37: =J37*(1+K$10)*(1-K$11)*IF(MOD((K$7-7),12)=0,IF((K$7-7)=12,K$12,K$13)*(1+K$14),1) | L37: =K37*(1+L$10)*(1-L$11)*IF(MOD((L$7-7),12)=0,IF((L$7-7)=12,L$12,L$13)*(1+L$14),1) | M37: =L37*(1+M$10)*(1-M$11)*IF(MOD((M$7-7),12)=0,IF((M$7-7)=12,M$12,M$13)*(1+M$14),1) | N37: =M37*(1+N$10)*(1-N$11)*IF(MOD((N$7-7),12)=0,IF((N$7-7)=12,N$12,N$13)*(1+N$14),1) | O37: =N37*(1+O$10)*(1-O$11)*IF(MOD((O$7-7),12)=0,IF((O$7-7)=12,O$12,O$13)*(1+O$14),1) | P37: =O37*(1+P$10)*(1-P$11)*IF(MOD((P$7-7),12)=0,IF((P$7-7)=12,P$12,P$13)*(1+P$14),1) | Q37: =P37*(1+Q$10)*(1-Q$11)*IF(MOD((Q$7-7),12)=0,IF((Q$7-7)=12,Q$12,Q$13)*(1+Q$14),1) | R37: =Q37*(1+R$10)*(1-R$11)*IF(MOD((R$7-7),12)=0,IF((R$7-7)=12,R$12,R$13)*(1+R$14),1) | ... BK37: =BJ37*(1+BK$10)*(1-BK$11)*IF(MOD((BK$7-7),12)=0,IF((BK$7-7)=12,BK$12,BK$13)*(1+BK$14),1)
B38: Cohort Aug-26 | C38: $ | D38: =0 | E38: =0 | F38: =0 | G38: =0 | H38: =0 | I38: =0 | J38: =0 | K38: ='Rev-Capacity'!K29 | L38: =K38*(1+L$10)*(1-L$11)*IF(MOD((L$7-8),12)=0,IF((L$7-8)=12,L$12,L$13)*(1+L$14),1) | M38: =L38*(1+M$10)*(1-M$11)*IF(MOD((M$7-8),12)=0,IF((M$7-8)=12,M$12,M$13)*(1+M$14),1) | N38: =M38*(1+N$10)*(1-N$11)*IF(MOD((N$7-8),12)=0,IF((N$7-8)=12,N$12,N$13)*(1+N$14),1) | O38: =N38*(1+O$10)*(1-O$11)*IF(MOD((O$7-8),12)=0,IF((O$7-8)=12,O$12,O$13)*(1+O$14),1) | P38: =O38*(1+P$10)*(1-P$11)*IF(MOD((P$7-8),12)=0,IF((P$7-8)=12,P$12,P$13)*(1+P$14),1) | Q38: =P38*(1+Q$10)*(1-Q$11)*IF(MOD((Q$7-8),12)=0,IF((Q$7-8)=12,Q$12,Q$13)*(1+Q$14),1) | R38: =Q38*(1+R$10)*(1-R$11)*IF(MOD((R$7-8),12)=0,IF((R$7-8)=12,R$12,R$13)*(1+R$14),1) | S38: =R38*(1+S$10)*(1-S$11)*IF(MOD((S$7-8),12)=0,IF((S$7-8)=12,S$12,S$13)*(1+S$14),1) | ... BK38: =BJ38*(1+BK$10)*(1-BK$11)*IF(MOD((BK$7-8),12)=0,IF((BK$7-8)=12,BK$12,BK$13)*(1+BK$14),1)
B39: Cohort Sep-26 | C39: $ | D39: =0 | E39: =0 | F39: =0 | G39: =0 | H39: =0 | I39: =0 | J39: =0 | K39: =0 | L39: ='Rev-Capacity'!L29 | M39: =L39*(1+M$10)*(1-M$11)*IF(MOD((M$7-9),12)=0,IF((M$7-9)=12,M$12,M$13)*(1+M$14),1) | N39: =M39*(1+N$10)*(1-N$11)*IF(MOD((N$7-9),12)=0,IF((N$7-9)=12,N$12,N$13)*(1+N$14),1) | O39: =N39*(1+O$10)*(1-O$11)*IF(MOD((O$7-9),12)=0,IF((O$7-9)=12,O$12,O$13)*(1+O$14),1) | P39: =O39*(1+P$10)*(1-P$11)*IF(MOD((P$7-9),12)=0,IF((P$7-9)=12,P$12,P$13)*(1+P$14),1) | Q39: =P39*(1+Q$10)*(1-Q$11)*IF(MOD((Q$7-9),12)=0,IF((Q$7-9)=12,Q$12,Q$13)*(1+Q$14),1) | R39: =Q39*(1+R$10)*(1-R$11)*IF(MOD((R$7-9),12)=0,IF((R$7-9)=12,R$12,R$13)*(1+R$14),1) | S39: =R39*(1+S$10)*(1-S$11)*IF(MOD((S$7-9),12)=0,IF((S$7-9)=12,S$12,S$13)*(1+S$14),1) | T39: =S39*(1+T$10)*(1-T$11)*IF(MOD((T$7-9),12)=0,IF((T$7-9)=12,T$12,T$13)*(1+T$14),1) | ... BK39: =BJ39*(1+BK$10)*(1-BK$11)*IF(MOD((BK$7-9),12)=0,IF((BK$7-9)=12,BK$12,BK$13)*(1+BK$14),1)
B40: Cohort Oct-26 | C40: $ | D40: =0 | E40: =0 | F40: =0 | G40: =0 | H40: =0 | I40: =0 | J40: =0 | K40: =0 | L40: =0 | M40: ='Rev-Capacity'!M29 | N40: =M40*(1+N$10)*(1-N$11)*IF(MOD((N$7-10),12)=0,IF((N$7-10)=12,N$12,N$13)*(1+N$14),1) | O40: =N40*(1+O$10)*(1-O$11)*IF(MOD((O$7-10),12)=0,IF((O$7-10)=12,O$12,O$13)*(1+O$14),1) | P40: =O40*(1+P$10)*(1-P$11)*IF(MOD((P$7-10),12)=0,IF((P$7-10)=12,P$12,P$13)*(1+P$14),1) | Q40: =P40*(1+Q$10)*(1-Q$11)*IF(MOD((Q$7-10),12)=0,IF((Q$7-10)=12,Q$12,Q$13)*(1+Q$14),1) | R40: =Q40*(1+R$10)*(1-R$11)*IF(MOD((R$7-10),12)=0,IF((R$7-10)=12,R$12,R$13)*(1+R$14),1) | S40: =R40*(1+S$10)*(1-S$11)*IF(MOD((S$7-10),12)=0,IF((S$7-10)=12,S$12,S$13)*(1+S$14),1) | T40: =S40*(1+T$10)*(1-T$11)*IF(MOD((T$7-10),12)=0,IF((T$7-10)=12,T$12,T$13)*(1+T$14),1) | U40: =T40*(1+U$10)*(1-U$11)*IF(MOD((U$7-10),12)=0,IF((U$7-10)=12,U$12,U$13)*(1+U$14),1) | ... BK40: =BJ40*(1+BK$10)*(1-BK$11)*IF(MOD((BK$7-10),12)=0,IF((BK$7-10)=12,BK$12,BK$13)*(1+BK$14),1)
B41: Cohort Nov-26 | C41: $ | D41: =0 | E41: =0 | F41: =0 | G41: =0 | H41: =0 | I41: =0 | J41: =0 | K41: =0 | ... M41: =0 | N41: ='Rev-Capacity'!N29 | O41: =N41*(1+O$10)*(1-O$11)*IF(MOD((O$7-11),12)=0,IF((O$7-11)=12,O$12,O$13)*(1+O$14),1) | P41: =O41*(1+P$10)*(1-P$11)*IF(MOD((P$7-11),12)=0,IF((P$7-11)=12,P$12,P$13)*(1+P$14),1) | Q41: =P41*(1+Q$10)*(1-Q$11)*IF(MOD((Q$7-11),12)=0,IF((Q$7-11)=12,Q$12,Q$13)*(1+Q$14),1) | R41: =Q41*(1+R$10)*(1-R$11)*IF(MOD((R$7-11),12)=0,IF((R$7-11)=12,R$12,R$13)*(1+R$14),1) | S41: =R41*(1+S$10)*(1-S$11)*IF(MOD((S$7-11),12)=0,IF((S$7-11)=12,S$12,S$13)*(1+S$14),1) | T41: =S41*(1+T$10)*(1-T$11)*IF(MOD((T$7-11),12)=0,IF((T$7-11)=12,T$12,T$13)*(1+T$14),1) | U41: =T41*(1+U$10)*(1-U$11)*IF(MOD((U$7-11),12)=0,IF((U$7-11)=12,U$12,U$13)*(1+U$14),1) | V41: =U41*(1+V$10)*(1-V$11)*IF(MOD((V$7-11),12)=0,IF((V$7-11)=12,V$12,V$13)*(1+V$14),1) | ... BK41: =BJ41*(1+BK$10)*(1-BK$11)*IF(MOD((BK$7-11),12)=0,IF((BK$7-11)=12,BK$12,BK$13)*(1+BK$14),1)
B42: Cohort Dec-26 | C42: $ | D42: =0 | E42: =0 | F42: =0 | G42: =0 | H42: =0 | I42: =0 | J42: =0 | K42: =0 | ... N42: =0 | O42: ='Rev-Capacity'!O29 | P42: =O42*(1+P$10)*(1-P$11)*IF(MOD((P$7-12),12)=0,IF((P$7-12)=12,P$12,P$13)*(1+P$14),1) | Q42: =P42*(1+Q$10)*(1-Q$11)*IF(MOD((Q$7-12),12)=0,IF((Q$7-12)=12,Q$12,Q$13)*(1+Q$14),1) | R42: =Q42*(1+R$10)*(1-R$11)*IF(MOD((R$7-12),12)=0,IF((R$7-12)=12,R$12,R$13)*(1+R$14),1) | S42: =R42*(1+S$10)*(1-S$11)*IF(MOD((S$7-12),12)=0,IF((S$7-12)=12,S$12,S$13)*(1+S$14),1) | T42: =S42*(1+T$10)*(1-T$11)*IF(MOD((T$7-12),12)=0,IF((T$7-12)=12,T$12,T$13)*(1+T$14),1) | U42: =T42*(1+U$10)*(1-U$11)*IF(MOD((U$7-12),12)=0,IF((U$7-12)=12,U$12,U$13)*(1+U$14),1) | V42: =U42*(1+V$10)*(1-V$11)*IF(MOD((V$7-12),12)=0,IF((V$7-12)=12,V$12,V$13)*(1+V$14),1) | W42: =V42*(1+W$10)*(1-W$11)*IF(MOD((W$7-12),12)=0,IF((W$7-12)=12,W$12,W$13)*(1+W$14),1) | ... BK42: =BJ42*(1+BK$10)*(1-BK$11)*IF(MOD((BK$7-12),12)=0,IF((BK$7-12)=12,BK$12,BK$13)*(1+BK$14),1)
B43: Cohort Jan-27 | C43: $ | D43: =0 | E43: =0 | F43: =0 | G43: =0 | H43: =0 | I43: =0 | J43: =0 | K43: =0 | ... O43: =0 | P43: ='Rev-Capacity'!P29 | Q43: =P43*(1+Q$10)*(1-Q$11)*IF(MOD((Q$7-13),12)=0,IF((Q$7-13)=12,Q$12,Q$13)*(1+Q$14),1) | R43: =Q43*(1+R$10)*(1-R$11)*IF(MOD((R$7-13),12)=0,IF((R$7-13)=12,R$12,R$13)*(1+R$14),1) | S43: =R43*(1+S$10)*(1-S$11)*IF(MOD((S$7-13),12)=0,IF((S$7-13)=12,S$12,S$13)*(1+S$14),1) | T43: =S43*(1+T$10)*(1-T$11)*IF(MOD((T$7-13),12)=0,IF((T$7-13)=12,T$12,T$13)*(1+T$14),1) | U43: =T43*(1+U$10)*(1-U$11)*IF(MOD((U$7-13),12)=0,IF((U$7-13)=12,U$12,U$13)*(1+U$14),1) | V43: =U43*(1+V$10)*(1-V$11)*IF(MOD((V$7-13),12)=0,IF((V$7-13)=12,V$12,V$13)*(1+V$14),1) | W43: =V43*(1+W$10)*(1-W$11)*IF(MOD((W$7-13),12)=0,IF((W$7-13)=12,W$12,W$13)*(1+W$14),1) | X43: =W43*(1+X$10)*(1-X$11)*IF(MOD((X$7-13),12)=0,IF((X$7-13)=12,X$12,X$13)*(1+X$14),1) | ... BK43: =BJ43*(1+BK$10)*(1-BK$11)*IF(MOD((BK$7-13),12)=0,IF((BK$7-13)=12,BK$12,BK$13)*(1+BK$14),1)
B44: Cohort Feb-27 | C44: $ | D44: =0 | E44: =0 | F44: =0 | G44: =0 | H44: =0 | I44: =0 | J44: =0 | K44: =0 | ... P44: =0 | Q44: ='Rev-Capacity'!Q29 | R44: =Q44*(1+R$10)*(1-R$11)*IF(MOD((R$7-14),12)=0,IF((R$7-14)=12,R$12,R$13)*(1+R$14),1) | S44: =R44*(1+S$10)*(1-S$11)*IF(MOD((S$7-14),12)=0,IF((S$7-14)=12,S$12,S$13)*(1+S$14),1) | T44: =S44*(1+T$10)*(1-T$11)*IF(MOD((T$7-14),12)=0,IF((T$7-14)=12,T$12,T$13)*(1+T$14),1) | U44: =T44*(1+U$10)*(1-U$11)*IF(MOD((U$7-14),12)=0,IF((U$7-14)=12,U$12,U$13)*(1+U$14),1) | V44: =U44*(1+V$10)*(1-V$11)*IF(MOD((V$7-14),12)=0,IF((V$7-14)=12,V$12,V$13)*(1+V$14),1) | W44: =V44*(1+W$10)*(1-W$11)*IF(MOD((W$7-14),12)=0,IF((W$7-14)=12,W$12,W$13)*(1+W$14),1) | X44: =W44*(1+X$10)*(1-X$11)*IF(MOD((X$7-14),12)=0,IF((X$7-14)=12,X$12,X$13)*(1+X$14),1) | Y44: =X44*(1+Y$10)*(1-Y$11)*IF(MOD((Y$7-14),12)=0,IF((Y$7-14)=12,Y$12,Y$13)*(1+Y$14),1) | ... BK44: =BJ44*(1+BK$10)*(1-BK$11)*IF(MOD((BK$7-14),12)=0,IF((BK$7-14)=12,BK$12,BK$13)*(1+BK$14),1)
B45: Cohort Mar-27 | C45: $ | D45: =0 | E45: =0 | F45: =0 | G45: =0 | H45: =0 | I45: =0 | J45: =0 | K45: =0 | ... Q45: =0 | R45: ='Rev-Capacity'!R29 | S45: =R45*(1+S$10)*(1-S$11)*IF(MOD((S$7-15),12)=0,IF((S$7-15)=12,S$12,S$13)*(1+S$14),1) | T45: =S45*(1+T$10)*(1-T$11)*IF(MOD((T$7-15),12)=0,IF((T$7-15)=12,T$12,T$13)*(1+T$14),1) | U45: =T45*(1+U$10)*(1-U$11)*IF(MOD((U$7-15),12)=0,IF((U$7-15)=12,U$12,U$13)*(1+U$14),1) | V45: =U45*(1+V$10)*(1-V$11)*IF(MOD((V$7-15),12)=0,IF((V$7-15)=12,V$12,V$13)*(1+V$14),1) | W45: =V45*(1+W$10)*(1-W$11)*IF(MOD((W$7-15),12)=0,IF((W$7-15)=12,W$12,W$13)*(1+W$14),1) | X45: =W45*(1+X$10)*(1-X$11)*IF(MOD((X$7-15),12)=0,IF((X$7-15)=12,X$12,X$13)*(1+X$14),1) | Y45: =X45*(1+Y$10)*(1-Y$11)*IF(MOD((Y$7-15),12)=0,IF((Y$7-15)=12,Y$12,Y$13)*(1+Y$14),1) | Z45: =Y45*(1+Z$10)*(1-Z$11)*IF(MOD((Z$7-15),12)=0,IF((Z$7-15)=12,Z$12,Z$13)*(1+Z$14),1) | ... BK45: =BJ45*(1+BK$10)*(1-BK$11)*IF(MOD((BK$7-15),12)=0,IF((BK$7-15)=12,BK$12,BK$13)*(1+BK$14),1)
B46: Cohort Apr-27 | C46: $ | D46: =0 | E46: =0 | F46: =0 | G46: =0 | H46: =0 | I46: =0 | J46: =0 | K46: =0 | ... R46: =0 | S46: ='Rev-Capacity'!S29 | T46: =S46*(1+T$10)*(1-T$11)*IF(MOD((T$7-16),12)=0,IF((T$7-16)=12,T$12,T$13)*(1+T$14),1) | U46: =T46*(1+U$10)*(1-U$11)*IF(MOD((U$7-16),12)=0,IF((U$7-16)=12,U$12,U$13)*(1+U$14),1) | V46: =U46*(1+V$10)*(1-V$11)*IF(MOD((V$7-16),12)=0,IF((V$7-16)=12,V$12,V$13)*(1+V$14),1) | W46: =V46*(1+W$10)*(1-W$11)*IF(MOD((W$7-16),12)=0,IF((W$7-16)=12,W$12,W$13)*(1+W$14),1) | X46: =W46*(1+X$10)*(1-X$11)*IF(MOD((X$7-16),12)=0,IF((X$7-16)=12,X$12,X$13)*(1+X$14),1) | Y46: =X46*(1+Y$10)*(1-Y$11)*IF(MOD((Y$7-16),12)=0,IF((Y$7-16)=12,Y$12,Y$13)*(1+Y$14),1) | Z46: =Y46*(1+Z$10)*(1-Z$11)*IF(MOD((Z$7-16),12)=0,IF((Z$7-16)=12,Z$12,Z$13)*(1+Z$14),1) | AA46: =Z46*(1+AA$10)*(1-AA$11)*IF(MOD((AA$7-16),12)=0,IF((AA$7-16)=12,AA$12,AA$13)*(1+AA$14),1) | ... BK46: =BJ46*(1+BK$10)*(1-BK$11)*IF(MOD((BK$7-16),12)=0,IF((BK$7-16)=12,BK$12,BK$13)*(1+BK$14),1)
B47: Cohort May-27 | C47: $ | D47: =0 | E47: =0 | F47: =0 | G47: =0 | H47: =0 | I47: =0 | J47: =0 | K47: =0 | ... S47: =0 | T47: ='Rev-Capacity'!T29 | U47: =T47*(1+U$10)*(1-U$11)*IF(MOD((U$7-17),12)=0,IF((U$7-17)=12,U$12,U$13)*(1+U$14),1) | V47: =U47*(1+V$10)*(1-V$11)*IF(MOD((V$7-17),12)=0,IF((V$7-17)=12,V$12,V$13)*(1+V$14),1) | W47: =V47*(1+W$10)*(1-W$11)*IF(MOD((W$7-17),12)=0,IF((W$7-17)=12,W$12,W$13)*(1+W$14),1) | X47: =W47*(1+X$10)*(1-X$11)*IF(MOD((X$7-17),12)=0,IF((X$7-17)=12,X$12,X$13)*(1+X$14),1) | Y47: =X47*(1+Y$10)*(1-Y$11)*IF(MOD((Y$7-17),12)=0,IF((Y$7-17)=12,Y$12,Y$13)*(1+Y$14),1) | Z47: =Y47*(1+Z$10)*(1-Z$11)*IF(MOD((Z$7-17),12)=0,IF((Z$7-17)=12,Z$12,Z$13)*(1+Z$14),1) | AA47: =Z47*(1+AA$10)*(1-AA$11)*IF(MOD((AA$7-17),12)=0,IF((AA$7-17)=12,AA$12,AA$13)*(1+AA$14),1) | AB47: =AA47*(1+AB$10)*(1-AB$11)*IF(MOD((AB$7-17),12)=0,IF((AB$7-17)=12,AB$12,AB$13)*(1+AB$14),1) | ... BK47: =BJ47*(1+BK$10)*(1-BK$11)*IF(MOD((BK$7-17),12)=0,IF((BK$7-17)=12,BK$12,BK$13)*(1+BK$14),1)
B48: Cohort Jun-27 | C48: $ | D48: =0 | E48: =0 | F48: =0 | G48: =0 | H48: =0 | I48: =0 | J48: =0 | K48: =0 | ... T48: =0 | U48: ='Rev-Capacity'!U29 | V48: =U48*(1+V$10)*(1-V$11)*IF(MOD((V$7-18),12)=0,IF((V$7-18)=12,V$12,V$13)*(1+V$14),1) | W48: =V48*(1+W$10)*(1-W$11)*IF(MOD((W$7-18),12)=0,IF((W$7-18)=12,W$12,W$13)*(1+W$14),1) | X48: =W48*(1+X$10)*(1-X$11)*IF(MOD((X$7-18),12)=0,IF((X$7-18)=12,X$12,X$13)*(1+X$14),1) | Y48: =X48*(1+Y$10)*(1-Y$11)*IF(MOD((Y$7-18),12)=0,IF((Y$7-18)=12,Y$12,Y$13)*(1+Y$14),1) | Z48: =Y48*(1+Z$10)*(1-Z$11)*IF(MOD((Z$7-18),12)=0,IF((Z$7-18)=12,Z$12,Z$13)*(1+Z$14),1) | AA48: =Z48*(1+AA$10)*(1-AA$11)*IF(MOD((AA$7-18),12)=0,IF((AA$7-18)=12,AA$12,AA$13)*(1+AA$14),1) | AB48: =AA48*(1+AB$10)*(1-AB$11)*IF(MOD((AB$7-18),12)=0,IF((AB$7-18)=12,AB$12,AB$13)*(1+AB$14),1) | AC48: =AB48*(1+AC$10)*(1-AC$11)*IF(MOD((AC$7-18),12)=0,IF((AC$7-18)=12,AC$12,AC$13)*(1+AC$14),1) | ... BK48: =BJ48*(1+BK$10)*(1-BK$11)*IF(MOD((BK$7-18),12)=0,IF((BK$7-18)=12,BK$12,BK$13)*(1+BK$14),1)
B49: Cohort Jul-27 | C49: $ | D49: =0 | E49: =0 | F49: =0 | G49: =0 | H49: =0 | I49: =0 | J49: =0 | K49: =0 | ... U49: =0 | V49: ='Rev-Capacity'!V29 | W49: =V49*(1+W$10)*(1-W$11)*IF(MOD((W$7-19),12)=0,IF((W$7-19)=12,W$12,W$13)*(1+W$14),1) | X49: =W49*(1+X$10)*(1-X$11)*IF(MOD((X$7-19),12)=0,IF((X$7-19)=12,X$12,X$13)*(1+X$14),1) | Y49: =X49*(1+Y$10)*(1-Y$11)*IF(MOD((Y$7-19),12)=0,IF((Y$7-19)=12,Y$12,Y$13)*(1+Y$14),1) | Z49: =Y49*(1+Z$10)*(1-Z$11)*IF(MOD((Z$7-19),12)=0,IF((Z$7-19)=12,Z$12,Z$13)*(1+Z$14),1) | AA49: =Z49*(1+AA$10)*(1-AA$11)*IF(MOD((AA$7-19),12)=0,IF((AA$7-19)=12,AA$12,AA$13)*(1+AA$14),1) | AB49: =AA49*(1+AB$10)*(1-AB$11)*IF(MOD((AB$7-19),12)=0,IF((AB$7-19)=12,AB$12,AB$13)*(1+AB$14),1) | AC49: =AB49*(1+AC$10)*(1-AC$11)*IF(MOD((AC$7-19),12)=0,IF((AC$7-19)=12,AC$12,AC$13)*(1+AC$14),1) | AD49: =AC49*(1+AD$10)*(1-AD$11)*IF(MOD((AD$7-19),12)=0,IF((AD$7-19)=12,AD$12,AD$13)*(1+AD$14),1) | ... BK49: =BJ49*(1+BK$10)*(1-BK$11)*IF(MOD((BK$7-19),12)=0,IF((BK$7-19)=12,BK$12,BK$13)*(1+BK$14),1)
B50: Cohort Aug-27 | C50: $ | D50: =0 | E50: =0 | F50: =0 | G50: =0 | H50: =0 | I50: =0 | J50: =0 | K50: =0 | ... V50: =0 | W50: ='Rev-Capacity'!W29 | X50: =W50*(1+X$10)*(1-X$11)*IF(MOD((X$7-20),12)=0,IF((X$7-20)=12,X$12,X$13)*(1+X$14),1) | Y50: =X50*(1+Y$10)*(1-Y$11)*IF(MOD((Y$7-20),12)=0,IF((Y$7-20)=12,Y$12,Y$13)*(1+Y$14),1) | Z50: =Y50*(1+Z$10)*(1-Z$11)*IF(MOD((Z$7-20),12)=0,IF((Z$7-20)=12,Z$12,Z$13)*(1+Z$14),1) | AA50: =Z50*(1+AA$10)*(1-AA$11)*IF(MOD((AA$7-20),12)=0,IF((AA$7-20)=12,AA$12,AA$13)*(1+AA$14),1) | AB50: =AA50*(1+AB$10)*(1-AB$11)*IF(MOD((AB$7-20),12)=0,IF((AB$7-20)=12,AB$12,AB$13)*(1+AB$14),1) | AC50: =AB50*(1+AC$10)*(1-AC$11)*IF(MOD((AC$7-20),12)=0,IF((AC$7-20)=12,AC$12,AC$13)*(1+AC$14),1) | AD50: =AC50*(1+AD$10)*(1-AD$11)*IF(MOD((AD$7-20),12)=0,IF((AD$7-20)=12,AD$12,AD$13)*(1+AD$14),1) | AE50: =AD50*(1+AE$10)*(1-AE$11)*IF(MOD((AE$7-20),12)=0,IF((AE$7-20)=12,AE$12,AE$13)*(1+AE$14),1) | ... BK50: =BJ50*(1+BK$10)*(1-BK$11)*IF(MOD((BK$7-20),12)=0,IF((BK$7-20)=12,BK$12,BK$13)*(1+BK$14),1)
B51: Cohort Sep-27 | C51: $ | D51: =0 | E51: =0 | F51: =0 | G51: =0 | H51: =0 | I51: =0 | J51: =0 | K51: =0 | ... W51: =0 | X51: ='Rev-Capacity'!X29 | Y51: =X51*(1+Y$10)*(1-Y$11)*IF(MOD((Y$7-21),12)=0,IF((Y$7-21)=12,Y$12,Y$13)*(1+Y$14),1) | Z51: =Y51*(1+Z$10)*(1-Z$11)*IF(MOD((Z$7-21),12)=0,IF((Z$7-21)=12,Z$12,Z$13)*(1+Z$14),1) | AA51: =Z51*(1+AA$10)*(1-AA$11)*IF(MOD((AA$7-21),12)=0,IF((AA$7-21)=12,AA$12,AA$13)*(1+AA$14),1) | AB51: =AA51*(1+AB$10)*(1-AB$11)*IF(MOD((AB$7-21),12)=0,IF((AB$7-21)=12,AB$12,AB$13)*(1+AB$14),1) | AC51: =AB51*(1+AC$10)*(1-AC$11)*IF(MOD((AC$7-21),12)=0,IF((AC$7-21)=12,AC$12,AC$13)*(1+AC$14),1) | AD51: =AC51*(1+AD$10)*(1-AD$11)*IF(MOD((AD$7-21),12)=0,IF((AD$7-21)=12,AD$12,AD$13)*(1+AD$14),1) | AE51: =AD51*(1+AE$10)*(1-AE$11)*IF(MOD((AE$7-21),12)=0,IF((AE$7-21)=12,AE$12,AE$13)*(1+AE$14),1) | AF51: =AE51*(1+AF$10)*(1-AF$11)*IF(MOD((AF$7-21),12)=0,IF((AF$7-21)=12,AF$12,AF$13)*(1+AF$14),1) | ... BK51: =BJ51*(1+BK$10)*(1-BK$11)*IF(MOD((BK$7-21),12)=0,IF((BK$7-21)=12,BK$12,BK$13)*(1+BK$14),1)
B52: Cohort Oct-27 | C52: $ | D52: =0 | E52: =0 | F52: =0 | G52: =0 | H52: =0 | I52: =0 | J52: =0 | K52: =0 | ... X52: =0 | Y52: ='Rev-Capacity'!Y29 | Z52: =Y52*(1+Z$10)*(1-Z$11)*IF(MOD((Z$7-22),12)=0,IF((Z$7-22)=12,Z$12,Z$13)*(1+Z$14),1) | AA52: =Z52*(1+AA$10)*(1-AA$11)*IF(MOD((AA$7-22),12)=0,IF((AA$7-22)=12,AA$12,AA$13)*(1+AA$14),1) | AB52: =AA52*(1+AB$10)*(1-AB$11)*IF(MOD((AB$7-22),12)=0,IF((AB$7-22)=12,AB$12,AB$13)*(1+AB$14),1) | AC52: =AB52*(1+AC$10)*(1-AC$11)*IF(MOD((AC$7-22),12)=0,IF((AC$7-22)=12,AC$12,AC$13)*(1+AC$14),1) | AD52: =AC52*(1+AD$10)*(1-AD$11)*IF(MOD((AD$7-22),12)=0,IF((AD$7-22)=12,AD$12,AD$13)*(1+AD$14),1) | AE52: =AD52*(1+AE$10)*(1-AE$11)*IF(MOD((AE$7-22),12)=0,IF((AE$7-22)=12,AE$12,AE$13)*(1+AE$14),1) | AF52: =AE52*(1+AF$10)*(1-AF$11)*IF(MOD((AF$7-22),12)=0,IF((AF$7-22)=12,AF$12,AF$13)*(1+AF$14),1) | AG52: =AF52*(1+AG$10)*(1-AG$11)*IF(MOD((AG$7-22),12)=0,IF((AG$7-22)=12,AG$12,AG$13)*(1+AG$14),1) | ... BK52: =BJ52*(1+BK$10)*(1-BK$11)*IF(MOD((BK$7-22),12)=0,IF((BK$7-22)=12,BK$12,BK$13)*(1+BK$14),1)
B53: Cohort Nov-27 | C53: $ | D53: =0 | E53: =0 | F53: =0 | G53: =0 | H53: =0 | I53: =0 | J53: =0 | K53: =0 | ... Y53: =0 | Z53: ='Rev-Capacity'!Z29 | AA53: =Z53*(1+AA$10)*(1-AA$11)*IF(MOD((AA$7-23),12)=0,IF((AA$7-23)=12,AA$12,AA$13)*(1+AA$14),1) | AB53: =AA53*(1+AB$10)*(1-AB$11)*IF(MOD((AB$7-23),12)=0,IF((AB$7-23)=12,AB$12,AB$13)*(1+AB$14),1) | AC53: =AB53*(1+AC$10)*(1-AC$11)*IF(MOD((AC$7-23),12)=0,IF((AC$7-23)=12,AC$12,AC$13)*(1+AC$14),1) | AD53: =AC53*(1+AD$10)*(1-AD$11)*IF(MOD((AD$7-23),12)=0,IF((AD$7-23)=12,AD$12,AD$13)*(1+AD$14),1) | AE53: =AD53*(1+AE$10)*(1-AE$11)*IF(MOD((AE$7-23),12)=0,IF((AE$7-23)=12,AE$12,AE$13)*(1+AE$14),1) | AF53: =AE53*(1+AF$10)*(1-AF$11)*IF(MOD((AF$7-23),12)=0,IF((AF$7-23)=12,AF$12,AF$13)*(1+AF$14),1) | AG53: =AF53*(1+AG$10)*(1-AG$11)*IF(MOD((AG$7-23),12)=0,IF((AG$7-23)=12,AG$12,AG$13)*(1+AG$14),1) | AH53: =AG53*(1+AH$10)*(1-AH$11)*IF(MOD((AH$7-23),12)=0,IF((AH$7-23)=12,AH$12,AH$13)*(1+AH$14),1) | ... BK53: =BJ53*(1+BK$10)*(1-BK$11)*IF(MOD((BK$7-23),12)=0,IF((BK$7-23)=12,BK$12,BK$13)*(1+BK$14),1)
B54: Cohort Dec-27 | C54: $ | D54: =0 | E54: =0 | F54: =0 | G54: =0 | H54: =0 | I54: =0 | J54: =0 | K54: =0 | ... Z54: =0 | AA54: ='Rev-Capacity'!AA29 | AB54: =AA54*(1+AB$10)*(1-AB$11)*IF(MOD((AB$7-24),12)=0,IF((AB$7-24)=12,AB$12,AB$13)*(1+AB$14),1) | AC54: =AB54*(1+AC$10)*(1-AC$11)*IF(MOD((AC$7-24),12)=0,IF((AC$7-24)=12,AC$12,AC$13)*(1+AC$14),1) | AD54: =AC54*(1+AD$10)*(1-AD$11)*IF(MOD((AD$7-24),12)=0,IF((AD$7-24)=12,AD$12,AD$13)*(1+AD$14),1) | AE54: =AD54*(1+AE$10)*(1-AE$11)*IF(MOD((AE$7-24),12)=0,IF((AE$7-24)=12,AE$12,AE$13)*(1+AE$14),1) | AF54: =AE54*(1+AF$10)*(1-AF$11)*IF(MOD((AF$7-24),12)=0,IF((AF$7-24)=12,AF$12,AF$13)*(1+AF$14),1) | AG54: =AF54*(1+AG$10)*(1-AG$11)*IF(MOD((AG$7-24),12)=0,IF((AG$7-24)=12,AG$12,AG$13)*(1+AG$14),1) | AH54: =AG54*(1+AH$10)*(1-AH$11)*IF(MOD((AH$7-24),12)=0,IF((AH$7-24)=12,AH$12,AH$13)*(1+AH$14),1) | AI54: =AH54*(1+AI$10)*(1-AI$11)*IF(MOD((AI$7-24),12)=0,IF((AI$7-24)=12,AI$12,AI$13)*(1+AI$14),1) | ... BK54: =BJ54*(1+BK$10)*(1-BK$11)*IF(MOD((BK$7-24),12)=0,IF((BK$7-24)=12,BK$12,BK$13)*(1+BK$14),1)
B55: Cohort Jan-28 | C55: $ | D55: =0 | E55: =0 | F55: =0 | G55: =0 | H55: =0 | I55: =0 | J55: =0 | K55: =0 | ... AA55: =0 | AB55: ='Rev-Capacity'!AB29 | AC55: =AB55*(1+AC$10)*(1-AC$11)*IF(MOD((AC$7-25),12)=0,IF((AC$7-25)=12,AC$12,AC$13)*(1+AC$14),1) | AD55: =AC55*(1+AD$10)*(1-AD$11)*IF(MOD((AD$7-25),12)=0,IF((AD$7-25)=12,AD$12,AD$13)*(1+AD$14),1) | AE55: =AD55*(1+AE$10)*(1-AE$11)*IF(MOD((AE$7-25),12)=0,IF((AE$7-25)=12,AE$12,AE$13)*(1+AE$14),1) | AF55: =AE55*(1+AF$10)*(1-AF$11)*IF(MOD((AF$7-25),12)=0,IF((AF$7-25)=12,AF$12,AF$13)*(1+AF$14),1) | AG55: =AF55*(1+AG$10)*(1-AG$11)*IF(MOD((AG$7-25),12)=0,IF((AG$7-25)=12,AG$12,AG$13)*(1+AG$14),1) | AH55: =AG55*(1+AH$10)*(1-AH$11)*IF(MOD((AH$7-25),12)=0,IF((AH$7-25)=12,AH$12,AH$13)*(1+AH$14),1) | AI55: =AH55*(1+AI$10)*(1-AI$11)*IF(MOD((AI$7-25),12)=0,IF((AI$7-25)=12,AI$12,AI$13)*(1+AI$14),1) | AJ55: =AI55*(1+AJ$10)*(1-AJ$11)*IF(MOD((AJ$7-25),12)=0,IF((AJ$7-25)=12,AJ$12,AJ$13)*(1+AJ$14),1) | ... BK55: =BJ55*(1+BK$10)*(1-BK$11)*IF(MOD((BK$7-25),12)=0,IF((BK$7-25)=12,BK$12,BK$13)*(1+BK$14),1)
B56: Cohort Feb-28 | C56: $ | D56: =0 | E56: =0 | F56: =0 | G56: =0 | H56: =0 | I56: =0 | J56: =0 | K56: =0 | ... AB56: =0 | AC56: ='Rev-Capacity'!AC29 | AD56: =AC56*(1+AD$10)*(1-AD$11)*IF(MOD((AD$7-26),12)=0,IF((AD$7-26)=12,AD$12,AD$13)*(1+AD$14),1) | AE56: =AD56*(1+AE$10)*(1-AE$11)*IF(MOD((AE$7-26),12)=0,IF((AE$7-26)=12,AE$12,AE$13)*(1+AE$14),1) | AF56: =AE56*(1+AF$10)*(1-AF$11)*IF(MOD((AF$7-26),12)=0,IF((AF$7-26)=12,AF$12,AF$13)*(1+AF$14),1) | AG56: =AF56*(1+AG$10)*(1-AG$11)*IF(MOD((AG$7-26),12)=0,IF((AG$7-26)=12,AG$12,AG$13)*(1+AG$14),1) | AH56: =AG56*(1+AH$10)*(1-AH$11)*IF(MOD((AH$7-26),12)=0,IF((AH$7-26)=12,AH$12,AH$13)*(1+AH$14),1) | AI56: =AH56*(1+AI$10)*(1-AI$11)*IF(MOD((AI$7-26),12)=0,IF((AI$7-26)=12,AI$12,AI$13)*(1+AI$14),1) | AJ56: =AI56*(1+AJ$10)*(1-AJ$11)*IF(MOD((AJ$7-26),12)=0,IF((AJ$7-26)=12,AJ$12,AJ$13)*(1+AJ$14),1) | AK56: =AJ56*(1+AK$10)*(1-AK$11)*IF(MOD((AK$7-26),12)=0,IF((AK$7-26)=12,AK$12,AK$13)*(1+AK$14),1) | ... BK56: =BJ56*(1+BK$10)*(1-BK$11)*IF(MOD((BK$7-26),12)=0,IF((BK$7-26)=12,BK$12,BK$13)*(1+BK$14),1)
B57: Cohort Mar-28 | C57: $ | D57: =0 | E57: =0 | F57: =0 | G57: =0 | H57: =0 | I57: =0 | J57: =0 | K57: =0 | ... AC57: =0 | AD57: ='Rev-Capacity'!AD29 | AE57: =AD57*(1+AE$10)*(1-AE$11)*IF(MOD((AE$7-27),12)=0,IF((AE$7-27)=12,AE$12,AE$13)*(1+AE$14),1) | AF57: =AE57*(1+AF$10)*(1-AF$11)*IF(MOD((AF$7-27),12)=0,IF((AF$7-27)=12,AF$12,AF$13)*(1+AF$14),1) | AG57: =AF57*(1+AG$10)*(1-AG$11)*IF(MOD((AG$7-27),12)=0,IF((AG$7-27)=12,AG$12,AG$13)*(1+AG$14),1) | AH57: =AG57*(1+AH$10)*(1-AH$11)*IF(MOD((AH$7-27),12)=0,IF((AH$7-27)=12,AH$12,AH$13)*(1+AH$14),1) | AI57: =AH57*(1+AI$10)*(1-AI$11)*IF(MOD((AI$7-27),12)=0,IF((AI$7-27)=12,AI$12,AI$13)*(1+AI$14),1) | AJ57: =AI57*(1+AJ$10)*(1-AJ$11)*IF(MOD((AJ$7-27),12)=0,IF((AJ$7-27)=12,AJ$12,AJ$13)*(1+AJ$14),1) | AK57: =AJ57*(1+AK$10)*(1-AK$11)*IF(MOD((AK$7-27),12)=0,IF((AK$7-27)=12,AK$12,AK$13)*(1+AK$14),1) | AL57: =AK57*(1+AL$10)*(1-AL$11)*IF(MOD((AL$7-27),12)=0,IF((AL$7-27)=12,AL$12,AL$13)*(1+AL$14),1) | ... BK57: =BJ57*(1+BK$10)*(1-BK$11)*IF(MOD((BK$7-27),12)=0,IF((BK$7-27)=12,BK$12,BK$13)*(1+BK$14),1)
B58: Cohort Apr-28 | C58: $ | D58: =0 | E58: =0 | F58: =0 | G58: =0 | H58: =0 | I58: =0 | J58: =0 | K58: =0 | ... AD58: =0 | AE58: ='Rev-Capacity'!AE29 | AF58: =AE58*(1+AF$10)*(1-AF$11)*IF(MOD((AF$7-28),12)=0,IF((AF$7-28)=12,AF$12,AF$13)*(1+AF$14),1) | AG58: =AF58*(1+AG$10)*(1-AG$11)*IF(MOD((AG$7-28),12)=0,IF((AG$7-28)=12,AG$12,AG$13)*(1+AG$14),1) | AH58: =AG58*(1+AH$10)*(1-AH$11)*IF(MOD((AH$7-28),12)=0,IF((AH$7-28)=12,AH$12,AH$13)*(1+AH$14),1) | AI58: =AH58*(1+AI$10)*(1-AI$11)*IF(MOD((AI$7-28),12)=0,IF((AI$7-28)=12,AI$12,AI$13)*(1+AI$14),1) | AJ58: =AI58*(1+AJ$10)*(1-AJ$11)*IF(MOD((AJ$7-28),12)=0,IF((AJ$7-28)=12,AJ$12,AJ$13)*(1+AJ$14),1) | AK58: =AJ58*(1+AK$10)*(1-AK$11)*IF(MOD((AK$7-28),12)=0,IF((AK$7-28)=12,AK$12,AK$13)*(1+AK$14),1) | AL58: =AK58*(1+AL$10)*(1-AL$11)*IF(MOD((AL$7-28),12)=0,IF((AL$7-28)=12,AL$12,AL$13)*(1+AL$14),1) | AM58: =AL58*(1+AM$10)*(1-AM$11)*IF(MOD((AM$7-28),12)=0,IF((AM$7-28)=12,AM$12,AM$13)*(1+AM$14),1) | ... BK58: =BJ58*(1+BK$10)*(1-BK$11)*IF(MOD((BK$7-28),12)=0,IF((BK$7-28)=12,BK$12,BK$13)*(1+BK$14),1)
B59: Cohort May-28 | C59: $ | D59: =0 | E59: =0 | F59: =0 | G59: =0 | H59: =0 | I59: =0 | J59: =0 | K59: =0 | ... AE59: =0 | AF59: ='Rev-Capacity'!AF29 | AG59: =AF59*(1+AG$10)*(1-AG$11)*IF(MOD((AG$7-29),12)=0,IF((AG$7-29)=12,AG$12,AG$13)*(1+AG$14),1) | AH59: =AG59*(1+AH$10)*(1-AH$11)*IF(MOD((AH$7-29),12)=0,IF((AH$7-29)=12,AH$12,AH$13)*(1+AH$14),1) | AI59: =AH59*(1+AI$10)*(1-AI$11)*IF(MOD((AI$7-29),12)=0,IF((AI$7-29)=12,AI$12,AI$13)*(1+AI$14),1) | AJ59: =AI59*(1+AJ$10)*(1-AJ$11)*IF(MOD((AJ$7-29),12)=0,IF((AJ$7-29)=12,AJ$12,AJ$13)*(1+AJ$14),1) | AK59: =AJ59*(1+AK$10)*(1-AK$11)*IF(MOD((AK$7-29),12)=0,IF((AK$7-29)=12,AK$12,AK$13)*(1+AK$14),1) | AL59: =AK59*(1+AL$10)*(1-AL$11)*IF(MOD((AL$7-29),12)=0,IF((AL$7-29)=12,AL$12,AL$13)*(1+AL$14),1) | AM59: =AL59*(1+AM$10)*(1-AM$11)*IF(MOD((AM$7-29),12)=0,IF((AM$7-29)=12,AM$12,AM$13)*(1+AM$14),1) | AN59: =AM59*(1+AN$10)*(1-AN$11)*IF(MOD((AN$7-29),12)=0,IF((AN$7-29)=12,AN$12,AN$13)*(1+AN$14),1) | ... BK59: =BJ59*(1+BK$10)*(1-BK$11)*IF(MOD((BK$7-29),12)=0,IF((BK$7-29)=12,BK$12,BK$13)*(1+BK$14),1)
B60: Cohort Jun-28 | C60: $ | D60: =0 | E60: =0 | F60: =0 | G60: =0 | H60: =0 | I60: =0 | J60: =0 | K60: =0 | ... AF60: =0 | AG60: ='Rev-Capacity'!AG29 | AH60: =AG60*(1+AH$10)*(1-AH$11)*IF(MOD((AH$7-30),12)=0,IF((AH$7-30)=12,AH$12,AH$13)*(1+AH$14),1) | AI60: =AH60*(1+AI$10)*(1-AI$11)*IF(MOD((AI$7-30),12)=0,IF((AI$7-30)=12,AI$12,AI$13)*(1+AI$14),1) | AJ60: =AI60*(1+AJ$10)*(1-AJ$11)*IF(MOD((AJ$7-30),12)=0,IF((AJ$7-30)=12,AJ$12,AJ$13)*(1+AJ$14),1) | AK60: =AJ60*(1+AK$10)*(1-AK$11)*IF(MOD((AK$7-30),12)=0,IF((AK$7-30)=12,AK$12,AK$13)*(1+AK$14),1) | AL60: =AK60*(1+AL$10)*(1-AL$11)*IF(MOD((AL$7-30),12)=0,IF((AL$7-30)=12,AL$12,AL$13)*(1+AL$14),1) | AM60: =AL60*(1+AM$10)*(1-AM$11)*IF(MOD((AM$7-30),12)=0,IF((AM$7-30)=12,AM$12,AM$13)*(1+AM$14),1) | AN60: =AM60*(1+AN$10)*(1-AN$11)*IF(MOD((AN$7-30),12)=0,IF((AN$7-30)=12,AN$12,AN$13)*(1+AN$14),1) | AO60: =AN60*(1+AO$10)*(1-AO$11)*IF(MOD((AO$7-30),12)=0,IF((AO$7-30)=12,AO$12,AO$13)*(1+AO$14),1) | ... BK60: =BJ60*(1+BK$10)*(1-BK$11)*IF(MOD((BK$7-30),12)=0,IF((BK$7-30)=12,BK$12,BK$13)*(1+BK$14),1)
B61: Cohort Jul-28 | C61: $ | D61: =0 | E61: =0 | F61: =0 | G61: =0 | H61: =0 | I61: =0 | J61: =0 | K61: =0 | ... AG61: =0 | AH61: ='Rev-Capacity'!AH29 | AI61: =AH61*(1+AI$10)*(1-AI$11)*IF(MOD((AI$7-31),12)=0,IF((AI$7-31)=12,AI$12,AI$13)*(1+AI$14),1) | AJ61: =AI61*(1+AJ$10)*(1-AJ$11)*IF(MOD((AJ$7-31),12)=0,IF((AJ$7-31)=12,AJ$12,AJ$13)*(1+AJ$14),1) | AK61: =AJ61*(1+AK$10)*(1-AK$11)*IF(MOD((AK$7-31),12)=0,IF((AK$7-31)=12,AK$12,AK$13)*(1+AK$14),1) | AL61: =AK61*(1+AL$10)*(1-AL$11)*IF(MOD((AL$7-31),12)=0,IF((AL$7-31)=12,AL$12,AL$13)*(1+AL$14),1) | AM61: =AL61*(1+AM$10)*(1-AM$11)*IF(MOD((AM$7-31),12)=0,IF((AM$7-31)=12,AM$12,AM$13)*(1+AM$14),1) | AN61: =AM61*(1+AN$10)*(1-AN$11)*IF(MOD((AN$7-31),12)=0,IF((AN$7-31)=12,AN$12,AN$13)*(1+AN$14),1) | AO61: =AN61*(1+AO$10)*(1-AO$11)*IF(MOD((AO$7-31),12)=0,IF((AO$7-31)=12,AO$12,AO$13)*(1+AO$14),1) | AP61: =AO61*(1+AP$10)*(1-AP$11)*IF(MOD((AP$7-31),12)=0,IF((AP$7-31)=12,AP$12,AP$13)*(1+AP$14),1) | ... BK61: =BJ61*(1+BK$10)*(1-BK$11)*IF(MOD((BK$7-31),12)=0,IF((BK$7-31)=12,BK$12,BK$13)*(1+BK$14),1)
B62: Cohort Aug-28 | C62: $ | D62: =0 | E62: =0 | F62: =0 | G62: =0 | H62: =0 | I62: =0 | J62: =0 | K62: =0 | ... AH62: =0 | AI62: ='Rev-Capacity'!AI29 | AJ62: =AI62*(1+AJ$10)*(1-AJ$11)*IF(MOD((AJ$7-32),12)=0,IF((AJ$7-32)=12,AJ$12,AJ$13)*(1+AJ$14),1) | AK62: =AJ62*(1+AK$10)*(1-AK$11)*IF(MOD((AK$7-32),12)=0,IF((AK$7-32)=12,AK$12,AK$13)*(1+AK$14),1) | AL62: =AK62*(1+AL$10)*(1-AL$11)*IF(MOD((AL$7-32),12)=0,IF((AL$7-32)=12,AL$12,AL$13)*(1+AL$14),1) | AM62: =AL62*(1+AM$10)*(1-AM$11)*IF(MOD((AM$7-32),12)=0,IF((AM$7-32)=12,AM$12,AM$13)*(1+AM$14),1) | AN62: =AM62*(1+AN$10)*(1-AN$11)*IF(MOD((AN$7-32),12)=0,IF((AN$7-32)=12,AN$12,AN$13)*(1+AN$14),1) | AO62: =AN62*(1+AO$10)*(1-AO$11)*IF(MOD((AO$7-32),12)=0,IF((AO$7-32)=12,AO$12,AO$13)*(1+AO$14),1) | AP62: =AO62*(1+AP$10)*(1-AP$11)*IF(MOD((AP$7-32),12)=0,IF((AP$7-32)=12,AP$12,AP$13)*(1+AP$14),1) | AQ62: =AP62*(1+AQ$10)*(1-AQ$11)*IF(MOD((AQ$7-32),12)=0,IF((AQ$7-32)=12,AQ$12,AQ$13)*(1+AQ$14),1) | ... BK62: =BJ62*(1+BK$10)*(1-BK$11)*IF(MOD((BK$7-32),12)=0,IF((BK$7-32)=12,BK$12,BK$13)*(1+BK$14),1)
B63: Cohort Sep-28 | C63: $ | D63: =0 | E63: =0 | F63: =0 | G63: =0 | H63: =0 | I63: =0 | J63: =0 | K63: =0 | ... AI63: =0 | AJ63: ='Rev-Capacity'!AJ29 | AK63: =AJ63*(1+AK$10)*(1-AK$11)*IF(MOD((AK$7-33),12)=0,IF((AK$7-33)=12,AK$12,AK$13)*(1+AK$14),1) | AL63: =AK63*(1+AL$10)*(1-AL$11)*IF(MOD((AL$7-33),12)=0,IF((AL$7-33)=12,AL$12,AL$13)*(1+AL$14),1) | AM63: =AL63*(1+AM$10)*(1-AM$11)*IF(MOD((AM$7-33),12)=0,IF((AM$7-33)=12,AM$12,AM$13)*(1+AM$14),1) | AN63: =AM63*(1+AN$10)*(1-AN$11)*IF(MOD((AN$7-33),12)=0,IF((AN$7-33)=12,AN$12,AN$13)*(1+AN$14),1) | AO63: =AN63*(1+AO$10)*(1-AO$11)*IF(MOD((AO$7-33),12)=0,IF((AO$7-33)=12,AO$12,AO$13)*(1+AO$14),1) | AP63: =AO63*(1+AP$10)*(1-AP$11)*IF(MOD((AP$7-33),12)=0,IF((AP$7-33)=12,AP$12,AP$13)*(1+AP$14),1) | AQ63: =AP63*(1+AQ$10)*(1-AQ$11)*IF(MOD((AQ$7-33),12)=0,IF((AQ$7-33)=12,AQ$12,AQ$13)*(1+AQ$14),1) | AR63: =AQ63*(1+AR$10)*(1-AR$11)*IF(MOD((AR$7-33),12)=0,IF((AR$7-33)=12,AR$12,AR$13)*(1+AR$14),1) | ... BK63: =BJ63*(1+BK$10)*(1-BK$11)*IF(MOD((BK$7-33),12)=0,IF((BK$7-33)=12,BK$12,BK$13)*(1+BK$14),1)
B64: Cohort Oct-28 | C64: $ | D64: =0 | E64: =0 | F64: =0 | G64: =0 | H64: =0 | I64: =0 | J64: =0 | K64: =0 | ... AJ64: =0 | AK64: ='Rev-Capacity'!AK29 | AL64: =AK64*(1+AL$10)*(1-AL$11)*IF(MOD((AL$7-34),12)=0,IF((AL$7-34)=12,AL$12,AL$13)*(1+AL$14),1) | AM64: =AL64*(1+AM$10)*(1-AM$11)*IF(MOD((AM$7-34),12)=0,IF((AM$7-34)=12,AM$12,AM$13)*(1+AM$14),1) | AN64: =AM64*(1+AN$10)*(1-AN$11)*IF(MOD((AN$7-34),12)=0,IF((AN$7-34)=12,AN$12,AN$13)*(1+AN$14),1) | AO64: =AN64*(1+AO$10)*(1-AO$11)*IF(MOD((AO$7-34),12)=0,IF((AO$7-34)=12,AO$12,AO$13)*(1+AO$14),1) | AP64: =AO64*(1+AP$10)*(1-AP$11)*IF(MOD((AP$7-34),12)=0,IF((AP$7-34)=12,AP$12,AP$13)*(1+AP$14),1) | AQ64: =AP64*(1+AQ$10)*(1-AQ$11)*IF(MOD((AQ$7-34),12)=0,IF((AQ$7-34)=12,AQ$12,AQ$13)*(1+AQ$14),1) | AR64: =AQ64*(1+AR$10)*(1-AR$11)*IF(MOD((AR$7-34),12)=0,IF((AR$7-34)=12,AR$12,AR$13)*(1+AR$14),1) | AS64: =AR64*(1+AS$10)*(1-AS$11)*IF(MOD((AS$7-34),12)=0,IF((AS$7-34)=12,AS$12,AS$13)*(1+AS$14),1) | ... BK64: =BJ64*(1+BK$10)*(1-BK$11)*IF(MOD((BK$7-34),12)=0,IF((BK$7-34)=12,BK$12,BK$13)*(1+BK$14),1)
B65: Cohort Nov-28 | C65: $ | D65: =0 | E65: =0 | F65: =0 | G65: =0 | H65: =0 | I65: =0 | J65: =0 | K65: =0 | ... AK65: =0 | AL65: ='Rev-Capacity'!AL29 | AM65: =AL65*(1+AM$10)*(1-AM$11)*IF(MOD((AM$7-35),12)=0,IF((AM$7-35)=12,AM$12,AM$13)*(1+AM$14),1) | AN65: =AM65*(1+AN$10)*(1-AN$11)*IF(MOD((AN$7-35),12)=0,IF((AN$7-35)=12,AN$12,AN$13)*(1+AN$14),1) | AO65: =AN65*(1+AO$10)*(1-AO$11)*IF(MOD((AO$7-35),12)=0,IF((AO$7-35)=12,AO$12,AO$13)*(1+AO$14),1) | AP65: =AO65*(1+AP$10)*(1-AP$11)*IF(MOD((AP$7-35),12)=0,IF((AP$7-35)=12,AP$12,AP$13)*(1+AP$14),1) | AQ65: =AP65*(1+AQ$10)*(1-AQ$11)*IF(MOD((AQ$7-35),12)=0,IF((AQ$7-35)=12,AQ$12,AQ$13)*(1+AQ$14),1) | AR65: =AQ65*(1+AR$10)*(1-AR$11)*IF(MOD((AR$7-35),12)=0,IF((AR$7-35)=12,AR$12,AR$13)*(1+AR$14),1) | AS65: =AR65*(1+AS$10)*(1-AS$11)*IF(MOD((AS$7-35),12)=0,IF((AS$7-35)=12,AS$12,AS$13)*(1+AS$14),1) | AT65: =AS65*(1+AT$10)*(1-AT$11)*IF(MOD((AT$7-35),12)=0,IF((AT$7-35)=12,AT$12,AT$13)*(1+AT$14),1) | ... BK65: =BJ65*(1+BK$10)*(1-BK$11)*IF(MOD((BK$7-35),12)=0,IF((BK$7-35)=12,BK$12,BK$13)*(1+BK$14),1)
B66: Cohort Dec-28 | C66: $ | D66: =0 | E66: =0 | F66: =0 | G66: =0 | H66: =0 | I66: =0 | J66: =0 | K66: =0 | ... AL66: =0 | AM66: ='Rev-Capacity'!AM29 | AN66: =AM66*(1+AN$10)*(1-AN$11)*IF(MOD((AN$7-36),12)=0,IF((AN$7-36)=12,AN$12,AN$13)*(1+AN$14),1) | AO66: =AN66*(1+AO$10)*(1-AO$11)*IF(MOD((AO$7-36),12)=0,IF((AO$7-36)=12,AO$12,AO$13)*(1+AO$14),1) | AP66: =AO66*(1+AP$10)*(1-AP$11)*IF(MOD((AP$7-36),12)=0,IF((AP$7-36)=12,AP$12,AP$13)*(1+AP$14),1) | AQ66: =AP66*(1+AQ$10)*(1-AQ$11)*IF(MOD((AQ$7-36),12)=0,IF((AQ$7-36)=12,AQ$12,AQ$13)*(1+AQ$14),1) | AR66: =AQ66*(1+AR$10)*(1-AR$11)*IF(MOD((AR$7-36),12)=0,IF((AR$7-36)=12,AR$12,AR$13)*(1+AR$14),1) | AS66: =AR66*(1+AS$10)*(1-AS$11)*IF(MOD((AS$7-36),12)=0,IF((AS$7-36)=12,AS$12,AS$13)*(1+AS$14),1) | AT66: =AS66*(1+AT$10)*(1-AT$11)*IF(MOD((AT$7-36),12)=0,IF((AT$7-36)=12,AT$12,AT$13)*(1+AT$14),1) | AU66: =AT66*(1+AU$10)*(1-AU$11)*IF(MOD((AU$7-36),12)=0,IF((AU$7-36)=12,AU$12,AU$13)*(1+AU$14),1) | ... BK66: =BJ66*(1+BK$10)*(1-BK$11)*IF(MOD((BK$7-36),12)=0,IF((BK$7-36)=12,BK$12,BK$13)*(1+BK$14),1)
B67: Cohort Jan-29 | C67: $ | D67: =0 | E67: =0 | F67: =0 | G67: =0 | H67: =0 | I67: =0 | J67: =0 | K67: =0 | ... AM67: =0 | AN67: ='Rev-Capacity'!AN29 | AO67: =AN67*(1+AO$10)*(1-AO$11)*IF(MOD((AO$7-37),12)=0,IF((AO$7-37)=12,AO$12,AO$13)*(1+AO$14),1) | AP67: =AO67*(1+AP$10)*(1-AP$11)*IF(MOD((AP$7-37),12)=0,IF((AP$7-37)=12,AP$12,AP$13)*(1+AP$14),1) | AQ67: =AP67*(1+AQ$10)*(1-AQ$11)*IF(MOD((AQ$7-37),12)=0,IF((AQ$7-37)=12,AQ$12,AQ$13)*(1+AQ$14),1) | AR67: =AQ67*(1+AR$10)*(1-AR$11)*IF(MOD((AR$7-37),12)=0,IF((AR$7-37)=12,AR$12,AR$13)*(1+AR$14),1) | AS67: =AR67*(1+AS$10)*(1-AS$11)*IF(MOD((AS$7-37),12)=0,IF((AS$7-37)=12,AS$12,AS$13)*(1+AS$14),1) | AT67: =AS67*(1+AT$10)*(1-AT$11)*IF(MOD((AT$7-37),12)=0,IF((AT$7-37)=12,AT$12,AT$13)*(1+AT$14),1) | AU67: =AT67*(1+AU$10)*(1-AU$11)*IF(MOD((AU$7-37),12)=0,IF((AU$7-37)=12,AU$12,AU$13)*(1+AU$14),1) | AV67: =AU67*(1+AV$10)*(1-AV$11)*IF(MOD((AV$7-37),12)=0,IF((AV$7-37)=12,AV$12,AV$13)*(1+AV$14),1) | ... BK67: =BJ67*(1+BK$10)*(1-BK$11)*IF(MOD((BK$7-37),12)=0,IF((BK$7-37)=12,BK$12,BK$13)*(1+BK$14),1)
B68: Cohort Feb-29 | C68: $ | D68: =0 | E68: =0 | F68: =0 | G68: =0 | H68: =0 | I68: =0 | J68: =0 | K68: =0 | ... AN68: =0 | AO68: ='Rev-Capacity'!AO29 | AP68: =AO68*(1+AP$10)*(1-AP$11)*IF(MOD((AP$7-38),12)=0,IF((AP$7-38)=12,AP$12,AP$13)*(1+AP$14),1) | AQ68: =AP68*(1+AQ$10)*(1-AQ$11)*IF(MOD((AQ$7-38),12)=0,IF((AQ$7-38)=12,AQ$12,AQ$13)*(1+AQ$14),1) | AR68: =AQ68*(1+AR$10)*(1-AR$11)*IF(MOD((AR$7-38),12)=0,IF((AR$7-38)=12,AR$12,AR$13)*(1+AR$14),1) | AS68: =AR68*(1+AS$10)*(1-AS$11)*IF(MOD((AS$7-38),12)=0,IF((AS$7-38)=12,AS$12,AS$13)*(1+AS$14),1) | AT68: =AS68*(1+AT$10)*(1-AT$11)*IF(MOD((AT$7-38),12)=0,IF((AT$7-38)=12,AT$12,AT$13)*(1+AT$14),1) | AU68: =AT68*(1+AU$10)*(1-AU$11)*IF(MOD((AU$7-38),12)=0,IF((AU$7-38)=12,AU$12,AU$13)*(1+AU$14),1) | AV68: =AU68*(1+AV$10)*(1-AV$11)*IF(MOD((AV$7-38),12)=0,IF((AV$7-38)=12,AV$12,AV$13)*(1+AV$14),1) | AW68: =AV68*(1+AW$10)*(1-AW$11)*IF(MOD((AW$7-38),12)=0,IF((AW$7-38)=12,AW$12,AW$13)*(1+AW$14),1) | ... BK68: =BJ68*(1+BK$10)*(1-BK$11)*IF(MOD((BK$7-38),12)=0,IF((BK$7-38)=12,BK$12,BK$13)*(1+BK$14),1)
B69: Cohort Mar-29 | C69: $ | D69: =0 | E69: =0 | F69: =0 | G69: =0 | H69: =0 | I69: =0 | J69: =0 | K69: =0 | ... AO69: =0 | AP69: ='Rev-Capacity'!AP29 | AQ69: =AP69*(1+AQ$10)*(1-AQ$11)*IF(MOD((AQ$7-39),12)=0,IF((AQ$7-39)=12,AQ$12,AQ$13)*(1+AQ$14),1) | AR69: =AQ69*(1+AR$10)*(1-AR$11)*IF(MOD((AR$7-39),12)=0,IF((AR$7-39)=12,AR$12,AR$13)*(1+AR$14),1) | AS69: =AR69*(1+AS$10)*(1-AS$11)*IF(MOD((AS$7-39),12)=0,IF((AS$7-39)=12,AS$12,AS$13)*(1+AS$14),1) | AT69: =AS69*(1+AT$10)*(1-AT$11)*IF(MOD((AT$7-39),12)=0,IF((AT$7-39)=12,AT$12,AT$13)*(1+AT$14),1) | AU69: =AT69*(1+AU$10)*(1-AU$11)*IF(MOD((AU$7-39),12)=0,IF((AU$7-39)=12,AU$12,AU$13)*(1+AU$14),1) | AV69: =AU69*(1+AV$10)*(1-AV$11)*IF(MOD((AV$7-39),12)=0,IF((AV$7-39)=12,AV$12,AV$13)*(1+AV$14),1) | AW69: =AV69*(1+AW$10)*(1-AW$11)*IF(MOD((AW$7-39),12)=0,IF((AW$7-39)=12,AW$12,AW$13)*(1+AW$14),1) | AX69: =AW69*(1+AX$10)*(1-AX$11)*IF(MOD((AX$7-39),12)=0,IF((AX$7-39)=12,AX$12,AX$13)*(1+AX$14),1) | ... BK69: =BJ69*(1+BK$10)*(1-BK$11)*IF(MOD((BK$7-39),12)=0,IF((BK$7-39)=12,BK$12,BK$13)*(1+BK$14),1)
B70: Cohort Apr-29 | C70: $ | D70: =0 | E70: =0 | F70: =0 | G70: =0 | H70: =0 | I70: =0 | J70: =0 | K70: =0 | ... AP70: =0 | AQ70: ='Rev-Capacity'!AQ29 | AR70: =AQ70*(1+AR$10)*(1-AR$11)*IF(MOD((AR$7-40),12)=0,IF((AR$7-40)=12,AR$12,AR$13)*(1+AR$14),1) | AS70: =AR70*(1+AS$10)*(1-AS$11)*IF(MOD((AS$7-40),12)=0,IF((AS$7-40)=12,AS$12,AS$13)*(1+AS$14),1) | AT70: =AS70*(1+AT$10)*(1-AT$11)*IF(MOD((AT$7-40),12)=0,IF((AT$7-40)=12,AT$12,AT$13)*(1+AT$14),1) | AU70: =AT70*(1+AU$10)*(1-AU$11)*IF(MOD((AU$7-40),12)=0,IF((AU$7-40)=12,AU$12,AU$13)*(1+AU$14),1) | AV70: =AU70*(1+AV$10)*(1-AV$11)*IF(MOD((AV$7-40),12)=0,IF((AV$7-40)=12,AV$12,AV$13)*(1+AV$14),1) | AW70: =AV70*(1+AW$10)*(1-AW$11)*IF(MOD((AW$7-40),12)=0,IF((AW$7-40)=12,AW$12,AW$13)*(1+AW$14),1) | AX70: =AW70*(1+AX$10)*(1-AX$11)*IF(MOD((AX$7-40),12)=0,IF((AX$7-40)=12,AX$12,AX$13)*(1+AX$14),1) | AY70: =AX70*(1+AY$10)*(1-AY$11)*IF(MOD((AY$7-40),12)=0,IF((AY$7-40)=12,AY$12,AY$13)*(1+AY$14),1) | ... BK70: =BJ70*(1+BK$10)*(1-BK$11)*IF(MOD((BK$7-40),12)=0,IF((BK$7-40)=12,BK$12,BK$13)*(1+BK$14),1)
B71: Cohort May-29 | C71: $ | D71: =0 | E71: =0 | F71: =0 | G71: =0 | H71: =0 | I71: =0 | J71: =0 | K71: =0 | ... AQ71: =0 | AR71: ='Rev-Capacity'!AR29 | AS71: =AR71*(1+AS$10)*(1-AS$11)*IF(MOD((AS$7-41),12)=0,IF((AS$7-41)=12,AS$12,AS$13)*(1+AS$14),1) | AT71: =AS71*(1+AT$10)*(1-AT$11)*IF(MOD((AT$7-41),12)=0,IF((AT$7-41)=12,AT$12,AT$13)*(1+AT$14),1) | AU71: =AT71*(1+AU$10)*(1-AU$11)*IF(MOD((AU$7-41),12)=0,IF((AU$7-41)=12,AU$12,AU$13)*(1+AU$14),1) | AV71: =AU71*(1+AV$10)*(1-AV$11)*IF(MOD((AV$7-41),12)=0,IF((AV$7-41)=12,AV$12,AV$13)*(1+AV$14),1) | AW71: =AV71*(1+AW$10)*(1-AW$11)*IF(MOD((AW$7-41),12)=0,IF((AW$7-41)=12,AW$12,AW$13)*(1+AW$14),1) | AX71: =AW71*(1+AX$10)*(1-AX$11)*IF(MOD((AX$7-41),12)=0,IF((AX$7-41)=12,AX$12,AX$13)*(1+AX$14),1) | AY71: =AX71*(1+AY$10)*(1-AY$11)*IF(MOD((AY$7-41),12)=0,IF((AY$7-41)=12,AY$12,AY$13)*(1+AY$14),1) | AZ71: =AY71*(1+AZ$10)*(1-AZ$11)*IF(MOD((AZ$7-41),12)=0,IF((AZ$7-41)=12,AZ$12,AZ$13)*(1+AZ$14),1) | ... BK71: =BJ71*(1+BK$10)*(1-BK$11)*IF(MOD((BK$7-41),12)=0,IF((BK$7-41)=12,BK$12,BK$13)*(1+BK$14),1)
B72: Cohort Jun-29 | C72: $ | D72: =0 | E72: =0 | F72: =0 | G72: =0 | H72: =0 | I72: =0 | J72: =0 | K72: =0 | ... AR72: =0 | AS72: ='Rev-Capacity'!AS29 | AT72: =AS72*(1+AT$10)*(1-AT$11)*IF(MOD((AT$7-42),12)=0,IF((AT$7-42)=12,AT$12,AT$13)*(1+AT$14),1) | AU72: =AT72*(1+AU$10)*(1-AU$11)*IF(MOD((AU$7-42),12)=0,IF((AU$7-42)=12,AU$12,AU$13)*(1+AU$14),1) | AV72: =AU72*(1+AV$10)*(1-AV$11)*IF(MOD((AV$7-42),12)=0,IF((AV$7-42)=12,AV$12,AV$13)*(1+AV$14),1) | AW72: =AV72*(1+AW$10)*(1-AW$11)*IF(MOD((AW$7-42),12)=0,IF((AW$7-42)=12,AW$12,AW$13)*(1+AW$14),1) | AX72: =AW72*(1+AX$10)*(1-AX$11)*IF(MOD((AX$7-42),12)=0,IF((AX$7-42)=12,AX$12,AX$13)*(1+AX$14),1) | AY72: =AX72*(1+AY$10)*(1-AY$11)*IF(MOD((AY$7-42),12)=0,IF((AY$7-42)=12,AY$12,AY$13)*(1+AY$14),1) | AZ72: =AY72*(1+AZ$10)*(1-AZ$11)*IF(MOD((AZ$7-42),12)=0,IF((AZ$7-42)=12,AZ$12,AZ$13)*(1+AZ$14),1) | BA72: =AZ72*(1+BA$10)*(1-BA$11)*IF(MOD((BA$7-42),12)=0,IF((BA$7-42)=12,BA$12,BA$13)*(1+BA$14),1) | ... BK72: =BJ72*(1+BK$10)*(1-BK$11)*IF(MOD((BK$7-42),12)=0,IF((BK$7-42)=12,BK$12,BK$13)*(1+BK$14),1)
B73: Cohort Jul-29 | C73: $ | D73: =0 | E73: =0 | F73: =0 | G73: =0 | H73: =0 | I73: =0 | J73: =0 | K73: =0 | ... AS73: =0 | AT73: ='Rev-Capacity'!AT29 | AU73: =AT73*(1+AU$10)*(1-AU$11)*IF(MOD((AU$7-43),12)=0,IF((AU$7-43)=12,AU$12,AU$13)*(1+AU$14),1) | AV73: =AU73*(1+AV$10)*(1-AV$11)*IF(MOD((AV$7-43),12)=0,IF((AV$7-43)=12,AV$12,AV$13)*(1+AV$14),1) | AW73: =AV73*(1+AW$10)*(1-AW$11)*IF(MOD((AW$7-43),12)=0,IF((AW$7-43)=12,AW$12,AW$13)*(1+AW$14),1) | AX73: =AW73*(1+AX$10)*(1-AX$11)*IF(MOD((AX$7-43),12)=0,IF((AX$7-43)=12,AX$12,AX$13)*(1+AX$14),1) | AY73: =AX73*(1+AY$10)*(1-AY$11)*IF(MOD((AY$7-43),12)=0,IF((AY$7-43)=12,AY$12,AY$13)*(1+AY$14),1) | AZ73: =AY73*(1+AZ$10)*(1-AZ$11)*IF(MOD((AZ$7-43),12)=0,IF((AZ$7-43)=12,AZ$12,AZ$13)*(1+AZ$14),1) | BA73: =AZ73*(1+BA$10)*(1-BA$11)*IF(MOD((BA$7-43),12)=0,IF((BA$7-43)=12,BA$12,BA$13)*(1+BA$14),1) | BB73: =BA73*(1+BB$10)*(1-BB$11)*IF(MOD((BB$7-43),12)=0,IF((BB$7-43)=12,BB$12,BB$13)*(1+BB$14),1) | ... BK73: =BJ73*(1+BK$10)*(1-BK$11)*IF(MOD((BK$7-43),12)=0,IF((BK$7-43)=12,BK$12,BK$13)*(1+BK$14),1)
B74: Cohort Aug-29 | C74: $ | D74: =0 | E74: =0 | F74: =0 | G74: =0 | H74: =0 | I74: =0 | J74: =0 | K74: =0 | ... AT74: =0 | AU74: ='Rev-Capacity'!AU29 | AV74: =AU74*(1+AV$10)*(1-AV$11)*IF(MOD((AV$7-44),12)=0,IF((AV$7-44)=12,AV$12,AV$13)*(1+AV$14),1) | AW74: =AV74*(1+AW$10)*(1-AW$11)*IF(MOD((AW$7-44),12)=0,IF((AW$7-44)=12,AW$12,AW$13)*(1+AW$14),1) | AX74: =AW74*(1+AX$10)*(1-AX$11)*IF(MOD((AX$7-44),12)=0,IF((AX$7-44)=12,AX$12,AX$13)*(1+AX$14),1) | AY74: =AX74*(1+AY$10)*(1-AY$11)*IF(MOD((AY$7-44),12)=0,IF((AY$7-44)=12,AY$12,AY$13)*(1+AY$14),1) | AZ74: =AY74*(1+AZ$10)*(1-AZ$11)*IF(MOD((AZ$7-44),12)=0,IF((AZ$7-44)=12,AZ$12,AZ$13)*(1+AZ$14),1) | BA74: =AZ74*(1+BA$10)*(1-BA$11)*IF(MOD((BA$7-44),12)=0,IF((BA$7-44)=12,BA$12,BA$13)*(1+BA$14),1) | BB74: =BA74*(1+BB$10)*(1-BB$11)*IF(MOD((BB$7-44),12)=0,IF((BB$7-44)=12,BB$12,BB$13)*(1+BB$14),1) | BC74: =BB74*(1+BC$10)*(1-BC$11)*IF(MOD((BC$7-44),12)=0,IF((BC$7-44)=12,BC$12,BC$13)*(1+BC$14),1) | ... BK74: =BJ74*(1+BK$10)*(1-BK$11)*IF(MOD((BK$7-44),12)=0,IF((BK$7-44)=12,BK$12,BK$13)*(1+BK$14),1)
B75: Cohort Sep-29 | C75: $ | D75: =0 | E75: =0 | F75: =0 | G75: =0 | H75: =0 | I75: =0 | J75: =0 | K75: =0 | ... AU75: =0 | AV75: ='Rev-Capacity'!AV29 | AW75: =AV75*(1+AW$10)*(1-AW$11)*IF(MOD((AW$7-45),12)=0,IF((AW$7-45)=12,AW$12,AW$13)*(1+AW$14),1) | AX75: =AW75*(1+AX$10)*(1-AX$11)*IF(MOD((AX$7-45),12)=0,IF((AX$7-45)=12,AX$12,AX$13)*(1+AX$14),1) | AY75: =AX75*(1+AY$10)*(1-AY$11)*IF(MOD((AY$7-45),12)=0,IF((AY$7-45)=12,AY$12,AY$13)*(1+AY$14),1) | AZ75: =AY75*(1+AZ$10)*(1-AZ$11)*IF(MOD((AZ$7-45),12)=0,IF((AZ$7-45)=12,AZ$12,AZ$13)*(1+AZ$14),1) | BA75: =AZ75*(1+BA$10)*(1-BA$11)*IF(MOD((BA$7-45),12)=0,IF((BA$7-45)=12,BA$12,BA$13)*(1+BA$14),1) | BB75: =BA75*(1+BB$10)*(1-BB$11)*IF(MOD((BB$7-45),12)=0,IF((BB$7-45)=12,BB$12,BB$13)*(1+BB$14),1) | BC75: =BB75*(1+BC$10)*(1-BC$11)*IF(MOD((BC$7-45),12)=0,IF((BC$7-45)=12,BC$12,BC$13)*(1+BC$14),1) | BD75: =BC75*(1+BD$10)*(1-BD$11)*IF(MOD((BD$7-45),12)=0,IF((BD$7-45)=12,BD$12,BD$13)*(1+BD$14),1) | ... BK75: =BJ75*(1+BK$10)*(1-BK$11)*IF(MOD((BK$7-45),12)=0,IF((BK$7-45)=12,BK$12,BK$13)*(1+BK$14),1)
B76: Cohort Oct-29 | C76: $ | D76: =0 | E76: =0 | F76: =0 | G76: =0 | H76: =0 | I76: =0 | J76: =0 | K76: =0 | ... AV76: =0 | AW76: ='Rev-Capacity'!AW29 | AX76: =AW76*(1+AX$10)*(1-AX$11)*IF(MOD((AX$7-46),12)=0,IF((AX$7-46)=12,AX$12,AX$13)*(1+AX$14),1) | AY76: =AX76*(1+AY$10)*(1-AY$11)*IF(MOD((AY$7-46),12)=0,IF((AY$7-46)=12,AY$12,AY$13)*(1+AY$14),1) | AZ76: =AY76*(1+AZ$10)*(1-AZ$11)*IF(MOD((AZ$7-46),12)=0,IF((AZ$7-46)=12,AZ$12,AZ$13)*(1+AZ$14),1) | BA76: =AZ76*(1+BA$10)*(1-BA$11)*IF(MOD((BA$7-46),12)=0,IF((BA$7-46)=12,BA$12,BA$13)*(1+BA$14),1) | BB76: =BA76*(1+BB$10)*(1-BB$11)*IF(MOD((BB$7-46),12)=0,IF((BB$7-46)=12,BB$12,BB$13)*(1+BB$14),1) | BC76: =BB76*(1+BC$10)*(1-BC$11)*IF(MOD((BC$7-46),12)=0,IF((BC$7-46)=12,BC$12,BC$13)*(1+BC$14),1) | BD76: =BC76*(1+BD$10)*(1-BD$11)*IF(MOD((BD$7-46),12)=0,IF((BD$7-46)=12,BD$12,BD$13)*(1+BD$14),1) | BE76: =BD76*(1+BE$10)*(1-BE$11)*IF(MOD((BE$7-46),12)=0,IF((BE$7-46)=12,BE$12,BE$13)*(1+BE$14),1) | ... BK76: =BJ76*(1+BK$10)*(1-BK$11)*IF(MOD((BK$7-46),12)=0,IF((BK$7-46)=12,BK$12,BK$13)*(1+BK$14),1)
B77: Cohort Nov-29 | C77: $ | D77: =0 | E77: =0 | F77: =0 | G77: =0 | H77: =0 | I77: =0 | J77: =0 | K77: =0 | ... AW77: =0 | AX77: ='Rev-Capacity'!AX29 | AY77: =AX77*(1+AY$10)*(1-AY$11)*IF(MOD((AY$7-47),12)=0,IF((AY$7-47)=12,AY$12,AY$13)*(1+AY$14),1) | AZ77: =AY77*(1+AZ$10)*(1-AZ$11)*IF(MOD((AZ$7-47),12)=0,IF((AZ$7-47)=12,AZ$12,AZ$13)*(1+AZ$14),1) | BA77: =AZ77*(1+BA$10)*(1-BA$11)*IF(MOD((BA$7-47),12)=0,IF((BA$7-47)=12,BA$12,BA$13)*(1+BA$14),1) | BB77: =BA77*(1+BB$10)*(1-BB$11)*IF(MOD((BB$7-47),12)=0,IF((BB$7-47)=12,BB$12,BB$13)*(1+BB$14),1) | BC77: =BB77*(1+BC$10)*(1-BC$11)*IF(MOD((BC$7-47),12)=0,IF((BC$7-47)=12,BC$12,BC$13)*(1+BC$14),1) | BD77: =BC77*(1+BD$10)*(1-BD$11)*IF(MOD((BD$7-47),12)=0,IF((BD$7-47)=12,BD$12,BD$13)*(1+BD$14),1) | BE77: =BD77*(1+BE$10)*(1-BE$11)*IF(MOD((BE$7-47),12)=0,IF((BE$7-47)=12,BE$12,BE$13)*(1+BE$14),1) | BF77: =BE77*(1+BF$10)*(1-BF$11)*IF(MOD((BF$7-47),12)=0,IF((BF$7-47)=12,BF$12,BF$13)*(1+BF$14),1) | ... BK77: =BJ77*(1+BK$10)*(1-BK$11)*IF(MOD((BK$7-47),12)=0,IF((BK$7-47)=12,BK$12,BK$13)*(1+BK$14),1)
B78: Cohort Dec-29 | C78: $ | D78: =0 | E78: =0 | F78: =0 | G78: =0 | H78: =0 | I78: =0 | J78: =0 | K78: =0 | ... AX78: =0 | AY78: ='Rev-Capacity'!AY29 | AZ78: =AY78*(1+AZ$10)*(1-AZ$11)*IF(MOD((AZ$7-48),12)=0,IF((AZ$7-48)=12,AZ$12,AZ$13)*(1+AZ$14),1) | BA78: =AZ78*(1+BA$10)*(1-BA$11)*IF(MOD((BA$7-48),12)=0,IF((BA$7-48)=12,BA$12,BA$13)*(1+BA$14),1) | BB78: =BA78*(1+BB$10)*(1-BB$11)*IF(MOD((BB$7-48),12)=0,IF((BB$7-48)=12,BB$12,BB$13)*(1+BB$14),1) | BC78: =BB78*(1+BC$10)*(1-BC$11)*IF(MOD((BC$7-48),12)=0,IF((BC$7-48)=12,BC$12,BC$13)*(1+BC$14),1) | BD78: =BC78*(1+BD$10)*(1-BD$11)*IF(MOD((BD$7-48),12)=0,IF((BD$7-48)=12,BD$12,BD$13)*(1+BD$14),1) | BE78: =BD78*(1+BE$10)*(1-BE$11)*IF(MOD((BE$7-48),12)=0,IF((BE$7-48)=12,BE$12,BE$13)*(1+BE$14),1) | BF78: =BE78*(1+BF$10)*(1-BF$11)*IF(MOD((BF$7-48),12)=0,IF((BF$7-48)=12,BF$12,BF$13)*(1+BF$14),1) | BG78: =BF78*(1+BG$10)*(1-BG$11)*IF(MOD((BG$7-48),12)=0,IF((BG$7-48)=12,BG$12,BG$13)*(1+BG$14),1) | ... BK78: =BJ78*(1+BK$10)*(1-BK$11)*IF(MOD((BK$7-48),12)=0,IF((BK$7-48)=12,BK$12,BK$13)*(1+BK$14),1)
B79: Cohort Jan-30 | C79: $ | D79: =0 | E79: =0 | F79: =0 | G79: =0 | H79: =0 | I79: =0 | J79: =0 | K79: =0 | ... AY79: =0 | AZ79: ='Rev-Capacity'!AZ29 | BA79: =AZ79*(1+BA$10)*(1-BA$11)*IF(MOD((BA$7-49),12)=0,IF((BA$7-49)=12,BA$12,BA$13)*(1+BA$14),1) | BB79: =BA79*(1+BB$10)*(1-BB$11)*IF(MOD((BB$7-49),12)=0,IF((BB$7-49)=12,BB$12,BB$13)*(1+BB$14),1) | BC79: =BB79*(1+BC$10)*(1-BC$11)*IF(MOD((BC$7-49),12)=0,IF((BC$7-49)=12,BC$12,BC$13)*(1+BC$14),1) | BD79: =BC79*(1+BD$10)*(1-BD$11)*IF(MOD((BD$7-49),12)=0,IF((BD$7-49)=12,BD$12,BD$13)*(1+BD$14),1) | BE79: =BD79*(1+BE$10)*(1-BE$11)*IF(MOD((BE$7-49),12)=0,IF((BE$7-49)=12,BE$12,BE$13)*(1+BE$14),1) | BF79: =BE79*(1+BF$10)*(1-BF$11)*IF(MOD((BF$7-49),12)=0,IF((BF$7-49)=12,BF$12,BF$13)*(1+BF$14),1) | BG79: =BF79*(1+BG$10)*(1-BG$11)*IF(MOD((BG$7-49),12)=0,IF((BG$7-49)=12,BG$12,BG$13)*(1+BG$14),1) | BH79: =BG79*(1+BH$10)*(1-BH$11)*IF(MOD((BH$7-49),12)=0,IF((BH$7-49)=12,BH$12,BH$13)*(1+BH$14),1) | ... BK79: =BJ79*(1+BK$10)*(1-BK$11)*IF(MOD((BK$7-49),12)=0,IF((BK$7-49)=12,BK$12,BK$13)*(1+BK$14),1)
B80: Cohort Feb-30 | C80: $ | D80: =0 | E80: =0 | F80: =0 | G80: =0 | H80: =0 | I80: =0 | J80: =0 | K80: =0 | ... AZ80: =0 | BA80: ='Rev-Capacity'!BA29 | BB80: =BA80*(1+BB$10)*(1-BB$11)*IF(MOD((BB$7-50),12)=0,IF((BB$7-50)=12,BB$12,BB$13)*(1+BB$14),1) | BC80: =BB80*(1+BC$10)*(1-BC$11)*IF(MOD((BC$7-50),12)=0,IF((BC$7-50)=12,BC$12,BC$13)*(1+BC$14),1) | BD80: =BC80*(1+BD$10)*(1-BD$11)*IF(MOD((BD$7-50),12)=0,IF((BD$7-50)=12,BD$12,BD$13)*(1+BD$14),1) | BE80: =BD80*(1+BE$10)*(1-BE$11)*IF(MOD((BE$7-50),12)=0,IF((BE$7-50)=12,BE$12,BE$13)*(1+BE$14),1) | BF80: =BE80*(1+BF$10)*(1-BF$11)*IF(MOD((BF$7-50),12)=0,IF((BF$7-50)=12,BF$12,BF$13)*(1+BF$14),1) | BG80: =BF80*(1+BG$10)*(1-BG$11)*IF(MOD((BG$7-50),12)=0,IF((BG$7-50)=12,BG$12,BG$13)*(1+BG$14),1) | BH80: =BG80*(1+BH$10)*(1-BH$11)*IF(MOD((BH$7-50),12)=0,IF((BH$7-50)=12,BH$12,BH$13)*(1+BH$14),1) | BI80: =BH80*(1+BI$10)*(1-BI$11)*IF(MOD((BI$7-50),12)=0,IF((BI$7-50)=12,BI$12,BI$13)*(1+BI$14),1) | ... BK80: =BJ80*(1+BK$10)*(1-BK$11)*IF(MOD((BK$7-50),12)=0,IF((BK$7-50)=12,BK$12,BK$13)*(1+BK$14),1)
B81: Cohort Mar-30 | C81: $ | D81: =0 | E81: =0 | F81: =0 | G81: =0 | H81: =0 | I81: =0 | J81: =0 | K81: =0 | ... BA81: =0 | BB81: ='Rev-Capacity'!BB29 | BC81: =BB81*(1+BC$10)*(1-BC$11)*IF(MOD((BC$7-51),12)=0,IF((BC$7-51)=12,BC$12,BC$13)*(1+BC$14),1) | BD81: =BC81*(1+BD$10)*(1-BD$11)*IF(MOD((BD$7-51),12)=0,IF((BD$7-51)=12,BD$12,BD$13)*(1+BD$14),1) | BE81: =BD81*(1+BE$10)*(1-BE$11)*IF(MOD((BE$7-51),12)=0,IF((BE$7-51)=12,BE$12,BE$13)*(1+BE$14),1) | BF81: =BE81*(1+BF$10)*(1-BF$11)*IF(MOD((BF$7-51),12)=0,IF((BF$7-51)=12,BF$12,BF$13)*(1+BF$14),1) | BG81: =BF81*(1+BG$10)*(1-BG$11)*IF(MOD((BG$7-51),12)=0,IF((BG$7-51)=12,BG$12,BG$13)*(1+BG$14),1) | BH81: =BG81*(1+BH$10)*(1-BH$11)*IF(MOD((BH$7-51),12)=0,IF((BH$7-51)=12,BH$12,BH$13)*(1+BH$14),1) | BI81: =BH81*(1+BI$10)*(1-BI$11)*IF(MOD((BI$7-51),12)=0,IF((BI$7-51)=12,BI$12,BI$13)*(1+BI$14),1) | BJ81: =BI81*(1+BJ$10)*(1-BJ$11)*IF(MOD((BJ$7-51),12)=0,IF((BJ$7-51)=12,BJ$12,BJ$13)*(1+BJ$14),1) | BK81: =BJ81*(1+BK$10)*(1-BK$11)*IF(MOD((BK$7-51),12)=0,IF((BK$7-51)=12,BK$12,BK$13)*(1+BK$14),1)
B82: Cohort Apr-30 | C82: $ | D82: =0 | E82: =0 | F82: =0 | G82: =0 | H82: =0 | I82: =0 | J82: =0 | K82: =0 | ... BB82: =0 | BC82: ='Rev-Capacity'!BC29 | BD82: =BC82*(1+BD$10)*(1-BD$11)*IF(MOD((BD$7-52),12)=0,IF((BD$7-52)=12,BD$12,BD$13)*(1+BD$14),1) | BE82: =BD82*(1+BE$10)*(1-BE$11)*IF(MOD((BE$7-52),12)=0,IF((BE$7-52)=12,BE$12,BE$13)*(1+BE$14),1) | BF82: =BE82*(1+BF$10)*(1-BF$11)*IF(MOD((BF$7-52),12)=0,IF((BF$7-52)=12,BF$12,BF$13)*(1+BF$14),1) | BG82: =BF82*(1+BG$10)*(1-BG$11)*IF(MOD((BG$7-52),12)=0,IF((BG$7-52)=12,BG$12,BG$13)*(1+BG$14),1) | BH82: =BG82*(1+BH$10)*(1-BH$11)*IF(MOD((BH$7-52),12)=0,IF((BH$7-52)=12,BH$12,BH$13)*(1+BH$14),1) | BI82: =BH82*(1+BI$10)*(1-BI$11)*IF(MOD((BI$7-52),12)=0,IF((BI$7-52)=12,BI$12,BI$13)*(1+BI$14),1) | BJ82: =BI82*(1+BJ$10)*(1-BJ$11)*IF(MOD((BJ$7-52),12)=0,IF((BJ$7-52)=12,BJ$12,BJ$13)*(1+BJ$14),1) | BK82: =BJ82*(1+BK$10)*(1-BK$11)*IF(MOD((BK$7-52),12)=0,IF((BK$7-52)=12,BK$12,BK$13)*(1+BK$14),1)
B83: Cohort May-30 | C83: $ | D83: =0 | E83: =0 | F83: =0 | G83: =0 | H83: =0 | I83: =0 | J83: =0 | K83: =0 | ... BC83: =0 | BD83: ='Rev-Capacity'!BD29 | BE83: =BD83*(1+BE$10)*(1-BE$11)*IF(MOD((BE$7-53),12)=0,IF((BE$7-53)=12,BE$12,BE$13)*(1+BE$14),1) | BF83: =BE83*(1+BF$10)*(1-BF$11)*IF(MOD((BF$7-53),12)=0,IF((BF$7-53)=12,BF$12,BF$13)*(1+BF$14),1) | BG83: =BF83*(1+BG$10)*(1-BG$11)*IF(MOD((BG$7-53),12)=0,IF((BG$7-53)=12,BG$12,BG$13)*(1+BG$14),1) | BH83: =BG83*(1+BH$10)*(1-BH$11)*IF(MOD((BH$7-53),12)=0,IF((BH$7-53)=12,BH$12,BH$13)*(1+BH$14),1) | BI83: =BH83*(1+BI$10)*(1-BI$11)*IF(MOD((BI$7-53),12)=0,IF((BI$7-53)=12,BI$12,BI$13)*(1+BI$14),1) | BJ83: =BI83*(1+BJ$10)*(1-BJ$11)*IF(MOD((BJ$7-53),12)=0,IF((BJ$7-53)=12,BJ$12,BJ$13)*(1+BJ$14),1) | BK83: =BJ83*(1+BK$10)*(1-BK$11)*IF(MOD((BK$7-53),12)=0,IF((BK$7-53)=12,BK$12,BK$13)*(1+BK$14),1)
B84: Cohort Jun-30 | C84: $ | D84: =0 | E84: =0 | F84: =0 | G84: =0 | H84: =0 | I84: =0 | J84: =0 | K84: =0 | ... BD84: =0 | BE84: ='Rev-Capacity'!BE29 | BF84: =BE84*(1+BF$10)*(1-BF$11)*IF(MOD((BF$7-54),12)=0,IF((BF$7-54)=12,BF$12,BF$13)*(1+BF$14),1) | BG84: =BF84*(1+BG$10)*(1-BG$11)*IF(MOD((BG$7-54),12)=0,IF((BG$7-54)=12,BG$12,BG$13)*(1+BG$14),1) | BH84: =BG84*(1+BH$10)*(1-BH$11)*IF(MOD((BH$7-54),12)=0,IF((BH$7-54)=12,BH$12,BH$13)*(1+BH$14),1) | BI84: =BH84*(1+BI$10)*(1-BI$11)*IF(MOD((BI$7-54),12)=0,IF((BI$7-54)=12,BI$12,BI$13)*(1+BI$14),1) | BJ84: =BI84*(1+BJ$10)*(1-BJ$11)*IF(MOD((BJ$7-54),12)=0,IF((BJ$7-54)=12,BJ$12,BJ$13)*(1+BJ$14),1) | BK84: =BJ84*(1+BK$10)*(1-BK$11)*IF(MOD((BK$7-54),12)=0,IF((BK$7-54)=12,BK$12,BK$13)*(1+BK$14),1)
B85: Cohort Jul-30 | C85: $ | D85: =0 | E85: =0 | F85: =0 | G85: =0 | H85: =0 | I85: =0 | J85: =0 | K85: =0 | ... BE85: =0 | BF85: ='Rev-Capacity'!BF29 | BG85: =BF85*(1+BG$10)*(1-BG$11)*IF(MOD((BG$7-55),12)=0,IF((BG$7-55)=12,BG$12,BG$13)*(1+BG$14),1) | BH85: =BG85*(1+BH$10)*(1-BH$11)*IF(MOD((BH$7-55),12)=0,IF((BH$7-55)=12,BH$12,BH$13)*(1+BH$14),1) | BI85: =BH85*(1+BI$10)*(1-BI$11)*IF(MOD((BI$7-55),12)=0,IF((BI$7-55)=12,BI$12,BI$13)*(1+BI$14),1) | BJ85: =BI85*(1+BJ$10)*(1-BJ$11)*IF(MOD((BJ$7-55),12)=0,IF((BJ$7-55)=12,BJ$12,BJ$13)*(1+BJ$14),1) | BK85: =BJ85*(1+BK$10)*(1-BK$11)*IF(MOD((BK$7-55),12)=0,IF((BK$7-55)=12,BK$12,BK$13)*(1+BK$14),1)
B86: Cohort Aug-30 | C86: $ | D86: =0 | E86: =0 | F86: =0 | G86: =0 | H86: =0 | I86: =0 | J86: =0 | K86: =0 | ... BF86: =0 | BG86: ='Rev-Capacity'!BG29 | BH86: =BG86*(1+BH$10)*(1-BH$11)*IF(MOD((BH$7-56),12)=0,IF((BH$7-56)=12,BH$12,BH$13)*(1+BH$14),1) | BI86: =BH86*(1+BI$10)*(1-BI$11)*IF(MOD((BI$7-56),12)=0,IF((BI$7-56)=12,BI$12,BI$13)*(1+BI$14),1) | BJ86: =BI86*(1+BJ$10)*(1-BJ$11)*IF(MOD((BJ$7-56),12)=0,IF((BJ$7-56)=12,BJ$12,BJ$13)*(1+BJ$14),1) | BK86: =BJ86*(1+BK$10)*(1-BK$11)*IF(MOD((BK$7-56),12)=0,IF((BK$7-56)=12,BK$12,BK$13)*(1+BK$14),1)
B87: Cohort Sep-30 | C87: $ | D87: =0 | E87: =0 | F87: =0 | G87: =0 | H87: =0 | I87: =0 | J87: =0 | K87: =0 | ... BG87: =0 | BH87: ='Rev-Capacity'!BH29 | BI87: =BH87*(1+BI$10)*(1-BI$11)*IF(MOD((BI$7-57),12)=0,IF((BI$7-57)=12,BI$12,BI$13)*(1+BI$14),1) | BJ87: =BI87*(1+BJ$10)*(1-BJ$11)*IF(MOD((BJ$7-57),12)=0,IF((BJ$7-57)=12,BJ$12,BJ$13)*(1+BJ$14),1) | BK87: =BJ87*(1+BK$10)*(1-BK$11)*IF(MOD((BK$7-57),12)=0,IF((BK$7-57)=12,BK$12,BK$13)*(1+BK$14),1)
B88: Cohort Oct-30 | C88: $ | D88: =0 | E88: =0 | F88: =0 | G88: =0 | H88: =0 | I88: =0 | J88: =0 | K88: =0 | ... BH88: =0 | BI88: ='Rev-Capacity'!BI29 | BJ88: =BI88*(1+BJ$10)*(1-BJ$11)*IF(MOD((BJ$7-58),12)=0,IF((BJ$7-58)=12,BJ$12,BJ$13)*(1+BJ$14),1) | BK88: =BJ88*(1+BK$10)*(1-BK$11)*IF(MOD((BK$7-58),12)=0,IF((BK$7-58)=12,BK$12,BK$13)*(1+BK$14),1)
B89: Cohort Nov-30 | C89: $ | D89: =0 | E89: =0 | F89: =0 | G89: =0 | H89: =0 | I89: =0 | J89: =0 | K89: =0 | ... BI89: =0 | BJ89: ='Rev-Capacity'!BJ29 | BK89: =BJ89*(1+BK$10)*(1-BK$11)*IF(MOD((BK$7-59),12)=0,IF((BK$7-59)=12,BK$12,BK$13)*(1+BK$14),1)
B90: Cohort Dec-30 | C90: $ | D90: =0 | E90: =0 | F90: =0 | G90: =0 | H90: =0 | I90: =0 | J90: =0 | K90: =0 | ... BJ90: =0 | BK90: ='Rev-Capacity'!BK29
B92: Total enterprise core ARR | C92: $ | D92: =SUM(D18:D29)+SUM(D31:D90) | E92: =SUM(E18:E29)+SUM(E31:E90) | F92: =SUM(F18:F29)+SUM(F31:F90) | G92: =SUM(G18:G29)+SUM(G31:G90) | H92: =SUM(H18:H29)+SUM(H31:H90) | I92: =SUM(I18:I29)+SUM(I31:I90) | J92: =SUM(J18:J29)+SUM(J31:J90) | K92: =SUM(K18:K29)+SUM(K31:K90) | ... BK92: =SUM(BK18:BK29)+SUM(BK31:BK90) | BM92: =O92 | BN92: =AA92 | BO92: =AM92 | BP92: =AY92 | BQ92: =BK92
B94: RENEWAL SCHEDULE
B95: ARR reaching its FIRST renewal this month | C95: $ | D95: =(Inputs!$D$15/12)*(1+D$10)*(1-D$11) | E95: =(D20)*(1+E$10)*(1-E$11) | F95: =(E21)*(1+F$10)*(1-F$11) | G95: =(F22)*(1+G$10)*(1-G$11) | H95: =(G23)*(1+H$10)*(1-H$11) | I95: =(H24)*(1+I$10)*(1-I$11) | J95: =(I25)*(1+J$10)*(1-J$11) | K95: =(J26)*(1+K$10)*(1-K$11) | L95: =(K27)*(1+L$10)*(1-L$11) | M95: =(L28)*(1+M$10)*(1-M$11) | N95: =(M29)*(1+N$10)*(1-N$11) | O95: =0 | P95: =(O31)*(1+P$10)*(1-P$11) | Q95: =(P32)*(1+Q$10)*(1-Q$11) | R95: =(Q33)*(1+R$10)*(1-R$11) | S95: =(R34)*(1+S$10)*(1-S$11) | T95: =(S35)*(1+T$10)*(1-T$11) | U95: =(T36)*(1+U$10)*(1-U$11) | V95: =(U37)*(1+V$10)*(1-V$11) | W95: =(V38)*(1+W$10)*(1-W$11) | X95: =(W39)*(1+X$10)*(1-X$11) | Y95: =(X40)*(1+Y$10)*(1-Y$11) | Z95: =(Y41)*(1+Z$10)*(1-Z$11) | AA95: =(Z42)*(1+AA$10)*(1-AA$11) | AB95: =(AA43)*(1+AB$10)*(1-AB$11) | AC95: =(AB44)*(1+AC$10)*(1-AC$11) | AD95: =(AC45)*(1+AD$10)*(1-AD$11) | AE95: =(AD46)*(1+AE$10)*(1-AE$11) | AF95: =(AE47)*(1+AF$10)*(1-AF$11) | AG95: =(AF48)*(1+AG$10)*(1-AG$11) | AH95: =(AG49)*(1+AH$10)*(1-AH$11) | AI95: =(AH50)*(1+AI$10)*(1-AI$11) | AJ95: =(AI51)*(1+AJ$10)*(1-AJ$11) | AK95: =(AJ52)*(1+AK$10)*(1-AK$11) | AL95: =(AK53)*(1+AL$10)*(1-AL$11) | AM95: =(AL54)*(1+AM$10)*(1-AM$11) | AN95: =(AM55)*(1+AN$10)*(1-AN$11) | AO95: =(AN56)*(1+AO$10)*(1-AO$11) | AP95: =(AO57)*(1+AP$10)*(1-AP$11) | AQ95: =(AP58)*(1+AQ$10)*(1-AQ$11) | AR95: =(AQ59)*(1+AR$10)*(1-AR$11) | AS95: =(AR60)*(1+AS$10)*(1-AS$11) | AT95: =(AS61)*(1+AT$10)*(1-AT$11) | AU95: =(AT62)*(1+AU$10)*(1-AU$11) | AV95: =(AU63)*(1+AV$10)*(1-AV$11) | AW95: =(AV64)*(1+AW$10)*(1-AW$11) | AX95: =(AW65)*(1+AX$10)*(1-AX$11) | AY95: =(AX66)*(1+AY$10)*(1-AY$11) | AZ95: =(AY67)*(1+AZ$10)*(1-AZ$11) | BA95: =(AZ68)*(1+BA$10)*(1-BA$11) | BB95: =(BA69)*(1+BB$10)*(1-BB$11) | BC95: =(BB70)*(1+BC$10)*(1-BC$11) | BD95: =(BC71)*(1+BD$10)*(1-BD$11) | BE95: =(BD72)*(1+BE$10)*(1-BE$11) | BF95: =(BE73)*(1+BF$10)*(1-BF$11) | BG95: =(BF74)*(1+BG$10)*(1-BG$11) | BH95: =(BG75)*(1+BH$10)*(1-BH$11) | BI95: =(BH76)*(1+BI$10)*(1-BI$11) | BJ95: =(BI77)*(1+BJ$10)*(1-BJ$11) | BK95: =(BJ78)*(1+BK$10)*(1-BK$11) | BM95: =SUM(D95:O95) | BN95: =SUM(P95:AA95) | BO95: =SUM(AB95:AM95) | BP95: =SUM(AN95:AY95) | BQ95: =SUM(AZ95:BK95)
B96: ARR reaching a LATER renewal this month | C96: $ | D96: =0 | E96: =0 | F96: =0 | G96: =0 | H96: =0 | I96: =0 | J96: =0 | K96: =0 | ... N96: =0 | O96: =(N18)*(1+O$10)*(1-O$11) | P96: =(O19)*(1+P$10)*(1-P$11) | Q96: =(P20)*(1+Q$10)*(1-Q$11) | R96: =(Q21)*(1+R$10)*(1-R$11) | S96: =(R22)*(1+S$10)*(1-S$11) | T96: =(S23)*(1+T$10)*(1-T$11) | U96: =(T24)*(1+U$10)*(1-U$11) | V96: =(U25)*(1+V$10)*(1-V$11) | W96: =(V26)*(1+W$10)*(1-W$11) | X96: =(W27)*(1+X$10)*(1-X$11) | Y96: =(X28)*(1+Y$10)*(1-Y$11) | Z96: =(Y29)*(1+Z$10)*(1-Z$11) | AA96: =(Z18)*(1+AA$10)*(1-AA$11) | AB96: =(AA19+AA31)*(1+AB$10)*(1-AB$11) | AC96: =(AB20+AB32)*(1+AC$10)*(1-AC$11) | AD96: =(AC21+AC33)*(1+AD$10)*(1-AD$11) | AE96: =(AD22+AD34)*(1+AE$10)*(1-AE$11) | AF96: =(AE23+AE35)*(1+AF$10)*(1-AF$11) | AG96: =(AF24+AF36)*(1+AG$10)*(1-AG$11) | AH96: =(AG25+AG37)*(1+AH$10)*(1-AH$11) | AI96: =(AH26+AH38)*(1+AI$10)*(1-AI$11) | AJ96: =(AI27+AI39)*(1+AJ$10)*(1-AJ$11) | AK96: =(AJ28+AJ40)*(1+AK$10)*(1-AK$11) | AL96: =(AK29+AK41)*(1+AL$10)*(1-AL$11) | AM96: =(AL18+AL42)*(1+AM$10)*(1-AM$11) | AN96: =(AM19+AM31+AM43)*(1+AN$10)*(1-AN$11) | AO96: =(AN20+AN32+AN44)*(1+AO$10)*(1-AO$11) | AP96: =(AO21+AO33+AO45)*(1+AP$10)*(1-AP$11) | AQ96: =(AP22+AP34+AP46)*(1+AQ$10)*(1-AQ$11) | AR96: =(AQ23+AQ35+AQ47)*(1+AR$10)*(1-AR$11) | AS96: =(AR24+AR36+AR48)*(1+AS$10)*(1-AS$11) | AT96: =(AS25+AS37+AS49)*(1+AT$10)*(1-AT$11) | AU96: =(AT26+AT38+AT50)*(1+AU$10)*(1-AU$11) | AV96: =(AU27+AU39+AU51)*(1+AV$10)*(1-AV$11) | AW96: =(AV28+AV40+AV52)*(1+AW$10)*(1-AW$11) | AX96: =(AW29+AW41+AW53)*(1+AX$10)*(1-AX$11) | AY96: =(AX18+AX42+AX54)*(1+AY$10)*(1-AY$11) | AZ96: =(AY19+AY31+AY43+AY55)*(1+AZ$10)*(1-AZ$11) | BA96: =(AZ20+AZ32+AZ44+AZ56)*(1+BA$10)*(1-BA$11) | BB96: =(BA21+BA33+BA45+BA57)*(1+BB$10)*(1-BB$11) | BC96: =(BB22+BB34+BB46+BB58)*(1+BC$10)*(1-BC$11) | BD96: =(BC23+BC35+BC47+BC59)*(1+BD$10)*(1-BD$11) | BE96: =(BD24+BD36+BD48+BD60)*(1+BE$10)*(1-BE$11) | BF96: =(BE25+BE37+BE49+BE61)*(1+BF$10)*(1-BF$11) | BG96: =(BF26+BF38+BF50+BF62)*(1+BG$10)*(1-BG$11) | BH96: =(BG27+BG39+BG51+BG63)*(1+BH$10)*(1-BH$11) | BI96: =(BH28+BH40+BH52+BH64)*(1+BI$10)*(1-BI$11) | BJ96: =(BI29+BI41+BI53+BI65)*(1+BJ$10)*(1-BJ$11) | BK96: =(BJ18+BJ42+BJ54+BJ66)*(1+BK$10)*(1-BK$11) | BM96: =SUM(D96:O96) | BN96: =SUM(P96:AA96) | BO96: =SUM(AB96:AM96) | BP96: =SUM(AN96:AY96) | BQ96: =SUM(AZ96:BK96)
B97: Total ARR renewing this month | C97: $ | D97: =D95+D96 | E97: =E95+E96 | F97: =F95+F96 | G97: =G95+G96 | H97: =H95+H96 | I97: =I95+I96 | J97: =J95+J96 | K97: =K95+K96 | ... BK97: =BK95+BK96 | BM97: =SUM(D97:O97) | BN97: =SUM(P97:AA97) | BO97: =SUM(AB97:AM97) | BP97: =SUM(AN97:AY97) | BQ97: =SUM(AZ97:BK97)
B98: Expand the triangle above to trace any single cohort through its renewals.

Sheet Rev-ARR Bridge
B2: Revenue: ARR Bridge
B5: Month ending | D5: 46053 | E5: 46081 | F5: 46112 | G5: 46142 | H5: 46173 | I5: 46203 | J5: 46234 | K5: 46265 | L5: 46295 | M5: 46326 | N5: 46356 | O5: 46387 | P5: 46418 | Q5: 46446 | R5: 46477 | S5: 46507 | T5: 46538 | U5: 46568 | V5: 46599 | W5: 46630 | X5: 46660 | Y5: 46691 | Z5: 46721 | AA5: 46752 | AB5: 46783 | AC5: 46812 | AD5: 46843 | AE5: 46873 | AF5: 46904 | AG5: 46934 | AH5: 46965 | AI5: 46996 | AJ5: 47026 | AK5: 47057 | AL5: 47087 | AM5: 47118 | AN5: 47149 | AO5: 47177 | AP5: 47208 | AQ5: 47238 | AR5: 47269 | AS5: 47299 | AT5: 47330 | AU5: 47361 | AV5: 47391 | AW5: 47422 | AX5: 47452 | AY5: 47483 | AZ5: 47514 | BA5: 47542 | BB5: 47573 | BC5: 47603 | BD5: 47634 | BE5: 47664 | BF5: 47695 | BG5: 47726 | BH5: 47756 | BI5: 47787 | BJ5: 47817 | BK5: 47848 | BM5: FY2026 | BN5: FY2027 | BO5: FY2028 | BP5: FY2029 | BQ5: FY2030
B6: Fiscal year | D6: 2026 | E6: 2026 | F6: 2026 | G6: 2026 | H6: 2026 | I6: 2026 | J6: 2026 | K6: 2026 | L6: 2026 | M6: 2026 | N6: 2026 | O6: 2026 | P6: 2027 | Q6: 2027 | R6: 2027 | S6: 2027 | T6: 2027 | U6: 2027 | V6: 2027 | W6: 2027 | X6: 2027 | Y6: 2027 | Z6: 2027 | AA6: 2027 | AB6: 2028 | AC6: 2028 | AD6: 2028 | AE6: 2028 | AF6: 2028 | AG6: 2028 | AH6: 2028 | AI6: 2028 | AJ6: 2028 | AK6: 2028 | AL6: 2028 | AM6: 2028 | AN6: 2029 | AO6: 2029 | AP6: 2029 | AQ6: 2029 | AR6: 2029 | AS6: 2029 | AT6: 2029 | AU6: 2029 | AV6: 2029 | AW6: 2029 | AX6: 2029 | AY6: 2029 | AZ6: 2030 | BA6: 2030 | BB6: 2030 | BC6: 2030 | BD6: 2030 | BE6: 2030 | BF6: 2030 | BG6: 2030 | BH6: 2030 | BI6: 2030 | BJ6: 2030 | BK6: 2030
B7: Period | D7: 1 | E7: 2 | F7: 3 | G7: 4 | H7: 5 | I7: 6 | J7: 7 | K7: 8 | L7: 9 | M7: 10 | N7: 11 | O7: 12 | P7: 13 | Q7: 14 | R7: 15 | S7: 16 | T7: 17 | U7: 18 | V7: 19 | W7: 20 | X7: 21 | Y7: 22 | Z7: 23 | AA7: 24 | AB7: 25 | AC7: 26 | AD7: 27 | AE7: 28 | AF7: 29 | AG7: 30 | AH7: 31 | AI7: 32 | AJ7: 33 | AK7: 34 | AL7: 35 | AM7: 36 | AN7: 37 | AO7: 38 | AP7: 39 | AQ7: 40 | AR7: 41 | AS7: 42 | AT7: 43 | AU7: 44 | AV7: 45 | AW7: 46 | AX7: 47 | AY7: 48 | AZ7: 49 | BA7: 50 | BB7: 51 | BC7: 52 | BD7: 53 | BE7: 54 | BF7: 55 | BG7: 56 | BH7: 57 | BI7: 58 | BJ7: 59 | BK7: 60
B9: ENTERPRISE CORE ARR BRIDGE
B10: Beginning ARR | C10: $ | D10: =Inputs!$D$15 | E10: =D14 | F10: =E14 | G10: =F14 | H10: =G14 | I10: =H14 | J10: =I14 | K10: =J14 | L10: =K14 | ... BK10: =BJ14
B11: New ARR | C11: $ | D11: ='Rev-Capacity'!D29 | E11: ='Rev-Capacity'!E29 | F11: ='Rev-Capacity'!F29 | G11: ='Rev-Capacity'!G29 | H11: ='Rev-Capacity'!H29 | I11: ='Rev-Capacity'!I29 | J11: ='Rev-Capacity'!J29 | K11: ='Rev-Capacity'!K29 | ... BK11: ='Rev-Capacity'!BK29 | BM11: =SUM(D11:O11) | BN11: =SUM(P11:AA11) | BO11: =SUM(AB11:AM11) | BP11: =SUM(AN11:AY11) | BQ11: =SUM(AZ11:BK11)
B12: Expansion | C12: $ | D12: =D10*'Rev-Cohorts'!D10+('Rev-Cohorts'!D95*'Rev-Cohorts'!D12+'Rev-Cohorts'!D96*'Rev-Cohorts'!D13)*'Rev-Cohorts'!D14 | E12: =E10*'Rev-Cohorts'!E10+('Rev-Cohorts'!E95*'Rev-Cohorts'!E12+'Rev-Cohorts'!E96*'Rev-Cohorts'!E13)*'Rev-Cohorts'!E14 | F12: =F10*'Rev-Cohorts'!F10+('Rev-Cohorts'!F95*'Rev-Cohorts'!F12+'Rev-Cohorts'!F96*'Rev-Cohorts'!F13)*'Rev-Cohorts'!F14 | G12: =G10*'Rev-Cohorts'!G10+('Rev-Cohorts'!G95*'Rev-Cohorts'!G12+'Rev-Cohorts'!G96*'Rev-Cohorts'!G13)*'Rev-Cohorts'!G14 | H12: =H10*'Rev-Cohorts'!H10+('Rev-Cohorts'!H95*'Rev-Cohorts'!H12+'Rev-Cohorts'!H96*'Rev-Cohorts'!H13)*'Rev-Cohorts'!H14 | I12: =I10*'Rev-Cohorts'!I10+('Rev-Cohorts'!I95*'Rev-Cohorts'!I12+'Rev-Cohorts'!I96*'Rev-Cohorts'!I13)*'Rev-Cohorts'!I14 | J12: =J10*'Rev-Cohorts'!J10+('Rev-Cohorts'!J95*'Rev-Cohorts'!J12+'Rev-Cohorts'!J96*'Rev-Cohorts'!J13)*'Rev-Cohorts'!J14 | K12: =K10*'Rev-Cohorts'!K10+('Rev-Cohorts'!K95*'Rev-Cohorts'!K12+'Rev-Cohorts'!K96*'Rev-Cohorts'!K13)*'Rev-Cohorts'!K14 | ... BK12: =BK10*'Rev-Cohorts'!BK10+('Rev-Cohorts'!BK95*'Rev-Cohorts'!BK12+'Rev-Cohorts'!BK96*'Rev-Cohorts'!BK13)*'Rev-Cohorts'!BK14 | BM12: =SUM(D12:O12) | BN12: =SUM(P12:AA12) | BO12: =SUM(AB12:AM12) | BP12: =SUM(AN12:AY12) | BQ12: =SUM(AZ12:BK12)
B13: Churn | C13: $ | D13: =-(D10*(1+'Rev-Cohorts'!D10)*'Rev-Cohorts'!D11+'Rev-Cohorts'!D95*(1-'Rev-Cohorts'!D12)+'Rev-Cohorts'!D96*(1-'Rev-Cohorts'!D13)) | E13: =-(E10*(1+'Rev-Cohorts'!E10)*'Rev-Cohorts'!E11+'Rev-Cohorts'!E95*(1-'Rev-Cohorts'!E12)+'Rev-Cohorts'!E96*(1-'Rev-Cohorts'!E13)) | F13: =-(F10*(1+'Rev-Cohorts'!F10)*'Rev-Cohorts'!F11+'Rev-Cohorts'!F95*(1-'Rev-Cohorts'!F12)+'Rev-Cohorts'!F96*(1-'Rev-Cohorts'!F13)) | G13: =-(G10*(1+'Rev-Cohorts'!G10)*'Rev-Cohorts'!G11+'Rev-Cohorts'!G95*(1-'Rev-Cohorts'!G12)+'Rev-Cohorts'!G96*(1-'Rev-Cohorts'!G13)) | H13: =-(H10*(1+'Rev-Cohorts'!H10)*'Rev-Cohorts'!H11+'Rev-Cohorts'!H95*(1-'Rev-Cohorts'!H12)+'Rev-Cohorts'!H96*(1-'Rev-Cohorts'!H13)) | I13: =-(I10*(1+'Rev-Cohorts'!I10)*'Rev-Cohorts'!I11+'Rev-Cohorts'!I95*(1-'Rev-Cohorts'!I12)+'Rev-Cohorts'!I96*(1-'Rev-Cohorts'!I13)) | J13: =-(J10*(1+'Rev-Cohorts'!J10)*'Rev-Cohorts'!J11+'Rev-Cohorts'!J95*(1-'Rev-Cohorts'!J12)+'Rev-Cohorts'!J96*(1-'Rev-Cohorts'!J13)) | K13: =-(K10*(1+'Rev-Cohorts'!K10)*'Rev-Cohorts'!K11+'Rev-Cohorts'!K95*(1-'Rev-Cohorts'!K12)+'Rev-Cohorts'!K96*(1-'Rev-Cohorts'!K13)) | ... BK13: =-(BK10*(1+'Rev-Cohorts'!BK10)*'Rev-Cohorts'!BK11+'Rev-Cohorts'!BK95*(1-'Rev-Cohorts'!BK12)+'Rev-Cohorts'!BK96*(1-'Rev-Cohorts'!BK13)) | BM13: =SUM(D13:O13) | BN13: =SUM(P13:AA13) | BO13: =SUM(AB13:AM13) | BP13: =SUM(AN13:AY13) | BQ13: =SUM(AZ13:BK13)
B14: Ending enterprise core ARR | C14: $ | D14: ='Rev-Cohorts'!D92 | E14: ='Rev-Cohorts'!E92 | F14: ='Rev-Cohorts'!F92 | G14: ='Rev-Cohorts'!G92 | H14: ='Rev-Cohorts'!H92 | I14: ='Rev-Cohorts'!I92 | J14: ='Rev-Cohorts'!J92 | K14: ='Rev-Cohorts'!K92 | ... BK14: ='Rev-Cohorts'!BK92 | BM14: =O14 | BN14: =AA14 | BO14: =AM14 | BP14: =AY14 | BQ14: =BK14
B16: AGENTS
B17: Enterprise customers | C17: # | D17: =Inputs!$D$16*(1-(Inputs!$D$62+Inputs!$D$73)/12)+'Rev-Capacity'!D30-Inputs!$D$16/12*(1-('Rev-Cohorts'!D12-Inputs!$D$73)) | E17: =D17+'Rev-Capacity'!E30-D17*(Inputs!$D$62+Inputs!$D$73)/12-IF(E$7<=12,Inputs!$D$16/12*(1-('Rev-Cohorts'!E12-Inputs!$D$73)),0) | F17: =E17+'Rev-Capacity'!F30-E17*(Inputs!$D$62+Inputs!$D$73)/12-IF(F$7<=12,Inputs!$D$16/12*(1-('Rev-Cohorts'!F12-Inputs!$D$73)),0) | G17: =F17+'Rev-Capacity'!G30-F17*(Inputs!$D$62+Inputs!$D$73)/12-IF(G$7<=12,Inputs!$D$16/12*(1-('Rev-Cohorts'!G12-Inputs!$D$73)),0) | H17: =G17+'Rev-Capacity'!H30-G17*(Inputs!$D$62+Inputs!$D$73)/12-IF(H$7<=12,Inputs!$D$16/12*(1-('Rev-Cohorts'!H12-Inputs!$D$73)),0) | I17: =H17+'Rev-Capacity'!I30-H17*(Inputs!$D$62+Inputs!$D$73)/12-IF(I$7<=12,Inputs!$D$16/12*(1-('Rev-Cohorts'!I12-Inputs!$D$73)),0) | J17: =I17+'Rev-Capacity'!J30-I17*(Inputs!$D$62+Inputs!$D$73)/12-IF(J$7<=12,Inputs!$D$16/12*(1-('Rev-Cohorts'!J12-Inputs!$D$73)),0) | K17: =J17+'Rev-Capacity'!K30-J17*(Inputs!$D$62+Inputs!$D$73)/12-IF(K$7<=12,Inputs!$D$16/12*(1-('Rev-Cohorts'!K12-Inputs!$D$73)),0) | L17: =K17+'Rev-Capacity'!L30-K17*(Inputs!$D$62+Inputs!$D$73)/12-IF(L$7<=12,Inputs!$D$16/12*(1-('Rev-Cohorts'!L12-Inputs!$D$73)),0) | ... BK17: =BJ17+'Rev-Capacity'!BK30-BJ17*(Inputs!$D$62+Inputs!$D$73)/12-IF(BK$7<=12,Inputs!$D$16/12*(1-('Rev-Cohorts'!BK12-Inputs!$D$73)),0) | BM17: =O17 | BN17: =AA17 | BO17: =AM17 | BP17: =AY17 | BQ17: =BK17
B18: Agents attach rate | C18: % | D18: =INDEX(Inputs!$D$94:$H$94,1,D$6-2025)*1/12 | E18: =INDEX(Inputs!$D$94:$H$94,1,E$6-2025)*2/12 | F18: =INDEX(Inputs!$D$94:$H$94,1,F$6-2025)*3/12 | G18: =INDEX(Inputs!$D$94:$H$94,1,G$6-2025)*4/12 | H18: =INDEX(Inputs!$D$94:$H$94,1,H$6-2025)*5/12 | I18: =INDEX(Inputs!$D$94:$H$94,1,I$6-2025)*6/12 | J18: =INDEX(Inputs!$D$94:$H$94,1,J$6-2025)*7/12 | K18: =INDEX(Inputs!$D$94:$H$94,1,K$6-2025)*8/12 | L18: =INDEX(Inputs!$D$94:$H$94,1,L$6-2025)*9/12 | M18: =INDEX(Inputs!$D$94:$H$94,1,M$6-2025)*10/12 | N18: =INDEX(Inputs!$D$94:$H$94,1,N$6-2025)*11/12 | O18: =INDEX(Inputs!$D$94:$H$94,1,O$6-2025)*12/12 | P18: =O18+(INDEX(Inputs!$D$94:$H$94,1,P$6-2025)-O18)*1/12 | Q18: =O18+(INDEX(Inputs!$D$94:$H$94,1,Q$6-2025)-O18)*2/12 | R18: =O18+(INDEX(Inputs!$D$94:$H$94,1,R$6-2025)-O18)*3/12 | S18: =O18+(INDEX(Inputs!$D$94:$H$94,1,S$6-2025)-O18)*4/12 | T18: =O18+(INDEX(Inputs!$D$94:$H$94,1,T$6-2025)-O18)*5/12 | U18: =O18+(INDEX(Inputs!$D$94:$H$94,1,U$6-2025)-O18)*6/12 | V18: =O18+(INDEX(Inputs!$D$94:$H$94,1,V$6-2025)-O18)*7/12 | W18: =O18+(INDEX(Inputs!$D$94:$H$94,1,W$6-2025)-O18)*8/12 | X18: =O18+(INDEX(Inputs!$D$94:$H$94,1,X$6-2025)-O18)*9/12 | Y18: =O18+(INDEX(Inputs!$D$94:$H$94,1,Y$6-2025)-O18)*10/12 | Z18: =O18+(INDEX(Inputs!$D$94:$H$94,1,Z$6-2025)-O18)*11/12 | AA18: =O18+(INDEX(Inputs!$D$94:$H$94,1,AA$6-2025)-O18)*12/12 | AB18: =AA18+(INDEX(Inputs!$D$94:$H$94,1,AB$6-2025)-AA18)*1/12 | AC18: =AA18+(INDEX(Inputs!$D$94:$H$94,1,AC$6-2025)-AA18)*2/12 | AD18: =AA18+(INDEX(Inputs!$D$94:$H$94,1,AD$6-2025)-AA18)*3/12 | AE18: =AA18+(INDEX(Inputs!$D$94:$H$94,1,AE$6-2025)-AA18)*4/12 | AF18: =AA18+(INDEX(Inputs!$D$94:$H$94,1,AF$6-2025)-AA18)*5/12 | AG18: =AA18+(INDEX(Inputs!$D$94:$H$94,1,AG$6-2025)-AA18)*6/12 | AH18: =AA18+(INDEX(Inputs!$D$94:$H$94,1,AH$6-2025)-AA18)*7/12 | AI18: =AA18+(INDEX(Inputs!$D$94:$H$94,1,AI$6-2025)-AA18)*8/12 | AJ18: =AA18+(INDEX(Inputs!$D$94:$H$94,1,AJ$6-2025)-AA18)*9/12 | AK18: =AA18+(INDEX(Inputs!$D$94:$H$94,1,AK$6-2025)-AA18)*10/12 | AL18: =AA18+(INDEX(Inputs!$D$94:$H$94,1,AL$6-2025)-AA18)*11/12 | AM18: =AA18+(INDEX(Inputs!$D$94:$H$94,1,AM$6-2025)-AA18)*12/12 | AN18: =AM18+(INDEX(Inputs!$D$94:$H$94,1,AN$6-2025)-AM18)*1/12 | AO18: =AM18+(INDEX(Inputs!$D$94:$H$94,1,AO$6-2025)-AM18)*2/12 | AP18: =AM18+(INDEX(Inputs!$D$94:$H$94,1,AP$6-2025)-AM18)*3/12 | AQ18: =AM18+(INDEX(Inputs!$D$94:$H$94,1,AQ$6-2025)-AM18)*4/12 | AR18: =AM18+(INDEX(Inputs!$D$94:$H$94,1,AR$6-2025)-AM18)*5/12 | AS18: =AM18+(INDEX(Inputs!$D$94:$H$94,1,AS$6-2025)-AM18)*6/12 | AT18: =AM18+(INDEX(Inputs!$D$94:$H$94,1,AT$6-2025)-AM18)*7/12 | AU18: =AM18+(INDEX(Inputs!$D$94:$H$94,1,AU$6-2025)-AM18)*8/12 | AV18: =AM18+(INDEX(Inputs!$D$94:$H$94,1,AV$6-2025)-AM18)*9/12 | AW18: =AM18+(INDEX(Inputs!$D$94:$H$94,1,AW$6-2025)-AM18)*10/12 | AX18: =AM18+(INDEX(Inputs!$D$94:$H$94,1,AX$6-2025)-AM18)*11/12 | AY18: =AM18+(INDEX(Inputs!$D$94:$H$94,1,AY$6-2025)-AM18)*12/12 | AZ18: =AY18+(INDEX(Inputs!$D$94:$H$94,1,AZ$6-2025)-AY18)*1/12 | BA18: =AY18+(INDEX(Inputs!$D$94:$H$94,1,BA$6-2025)-AY18)*2/12 | BB18: =AY18+(INDEX(Inputs!$D$94:$H$94,1,BB$6-2025)-AY18)*3/12 | BC18: =AY18+(INDEX(Inputs!$D$94:$H$94,1,BC$6-2025)-AY18)*4/12 | BD18: =AY18+(INDEX(Inputs!$D$94:$H$94,1,BD$6-2025)-AY18)*5/12 | BE18: =AY18+(INDEX(Inputs!$D$94:$H$94,1,BE$6-2025)-AY18)*6/12 | BF18: =AY18+(INDEX(Inputs!$D$94:$H$94,1,BF$6-2025)-AY18)*7/12 | BG18: =AY18+(INDEX(Inputs!$D$94:$H$94,1,BG$6-2025)-AY18)*8/12 | BH18: =AY18+(INDEX(Inputs!$D$94:$H$94,1,BH$6-2025)-AY18)*9/12 | BI18: =AY18+(INDEX(Inputs!$D$94:$H$94,1,BI$6-2025)-AY18)*10/12 | BJ18: =AY18+(INDEX(Inputs!$D$94:$H$94,1,BJ$6-2025)-AY18)*11/12 | BK18: =AY18+(INDEX(Inputs!$D$94:$H$94,1,BK$6-2025)-AY18)*12/12
B19: Agents customers | C19: # | D19: =D17*D18 | E19: =E17*E18 | F19: =F17*F18 | G19: =G17*G18 | H19: =H17*H18 | I19: =I17*I18 | J19: =J17*J18 | K19: =K17*K18 | ... BK19: =BK17*BK18
B20: Agents ACV | C20: $ | D20: =Inputs!$D$76*INDEX(Inputs!$D$102:$H$102,1,D$6-2025)*(1+((1+INDEX(Inputs!$D$110:$H$110,1,D$6-2025))^(1/12)-1))^0 | E20: =Inputs!$D$76*INDEX(Inputs!$D$102:$H$102,1,E$6-2025)*(1+((1+INDEX(Inputs!$D$110:$H$110,1,E$6-2025))^(1/12)-1))^1 | F20: =Inputs!$D$76*INDEX(Inputs!$D$102:$H$102,1,F$6-2025)*(1+((1+INDEX(Inputs!$D$110:$H$110,1,F$6-2025))^(1/12)-1))^2 | G20: =Inputs!$D$76*INDEX(Inputs!$D$102:$H$102,1,G$6-2025)*(1+((1+INDEX(Inputs!$D$110:$H$110,1,G$6-2025))^(1/12)-1))^3 | H20: =Inputs!$D$76*INDEX(Inputs!$D$102:$H$102,1,H$6-2025)*(1+((1+INDEX(Inputs!$D$110:$H$110,1,H$6-2025))^(1/12)-1))^4 | I20: =Inputs!$D$76*INDEX(Inputs!$D$102:$H$102,1,I$6-2025)*(1+((1+INDEX(Inputs!$D$110:$H$110,1,I$6-2025))^(1/12)-1))^5 | J20: =Inputs!$D$76*INDEX(Inputs!$D$102:$H$102,1,J$6-2025)*(1+((1+INDEX(Inputs!$D$110:$H$110,1,J$6-2025))^(1/12)-1))^6 | K20: =Inputs!$D$76*INDEX(Inputs!$D$102:$H$102,1,K$6-2025)*(1+((1+INDEX(Inputs!$D$110:$H$110,1,K$6-2025))^(1/12)-1))^7 | L20: =Inputs!$D$76*INDEX(Inputs!$D$102:$H$102,1,L$6-2025)*(1+((1+INDEX(Inputs!$D$110:$H$110,1,L$6-2025))^(1/12)-1))^8 | M20: =Inputs!$D$76*INDEX(Inputs!$D$102:$H$102,1,M$6-2025)*(1+((1+INDEX(Inputs!$D$110:$H$110,1,M$6-2025))^(1/12)-1))^9 | N20: =Inputs!$D$76*INDEX(Inputs!$D$102:$H$102,1,N$6-2025)*(1+((1+INDEX(Inputs!$D$110:$H$110,1,N$6-2025))^(1/12)-1))^10 | O20: =Inputs!$D$76*INDEX(Inputs!$D$102:$H$102,1,O$6-2025)*(1+((1+INDEX(Inputs!$D$110:$H$110,1,O$6-2025))^(1/12)-1))^11 | P20: =Inputs!$D$76*INDEX(Inputs!$D$102:$H$102,1,P$6-2025)*(1+((1+INDEX(Inputs!$D$110:$H$110,1,P$6-2025))^(1/12)-1))^12 | Q20: =Inputs!$D$76*INDEX(Inputs!$D$102:$H$102,1,Q$6-2025)*(1+((1+INDEX(Inputs!$D$110:$H$110,1,Q$6-2025))^(1/12)-1))^13 | R20: =Inputs!$D$76*INDEX(Inputs!$D$102:$H$102,1,R$6-2025)*(1+((1+INDEX(Inputs!$D$110:$H$110,1,R$6-2025))^(1/12)-1))^14 | S20: =Inputs!$D$76*INDEX(Inputs!$D$102:$H$102,1,S$6-2025)*(1+((1+INDEX(Inputs!$D$110:$H$110,1,S$6-2025))^(1/12)-1))^15 | T20: =Inputs!$D$76*INDEX(Inputs!$D$102:$H$102,1,T$6-2025)*(1+((1+INDEX(Inputs!$D$110:$H$110,1,T$6-2025))^(1/12)-1))^16 | U20: =Inputs!$D$76*INDEX(Inputs!$D$102:$H$102,1,U$6-2025)*(1+((1+INDEX(Inputs!$D$110:$H$110,1,U$6-2025))^(1/12)-1))^17 | V20: =Inputs!$D$76*INDEX(Inputs!$D$102:$H$102,1,V$6-2025)*(1+((1+INDEX(Inputs!$D$110:$H$110,1,V$6-2025))^(1/12)-1))^18 | W20: =Inputs!$D$76*INDEX(Inputs!$D$102:$H$102,1,W$6-2025)*(1+((1+INDEX(Inputs!$D$110:$H$110,1,W$6-2025))^(1/12)-1))^19 | X20: =Inputs!$D$76*INDEX(Inputs!$D$102:$H$102,1,X$6-2025)*(1+((1+INDEX(Inputs!$D$110:$H$110,1,X$6-2025))^(1/12)-1))^20 | Y20: =Inputs!$D$76*INDEX(Inputs!$D$102:$H$102,1,Y$6-2025)*(1+((1+INDEX(Inputs!$D$110:$H$110,1,Y$6-2025))^(1/12)-1))^21 | Z20: =Inputs!$D$76*INDEX(Inputs!$D$102:$H$102,1,Z$6-2025)*(1+((1+INDEX(Inputs!$D$110:$H$110,1,Z$6-2025))^(1/12)-1))^22 | AA20: =Inputs!$D$76*INDEX(Inputs!$D$102:$H$102,1,AA$6-2025)*(1+((1+INDEX(Inputs!$D$110:$H$110,1,AA$6-2025))^(1/12)-1))^23 | AB20: =Inputs!$D$76*INDEX(Inputs!$D$102:$H$102,1,AB$6-2025)*(1+((1+INDEX(Inputs!$D$110:$H$110,1,AB$6-2025))^(1/12)-1))^24 | AC20: =Inputs!$D$76*INDEX(Inputs!$D$102:$H$102,1,AC$6-2025)*(1+((1+INDEX(Inputs!$D$110:$H$110,1,AC$6-2025))^(1/12)-1))^25 | AD20: =Inputs!$D$76*INDEX(Inputs!$D$102:$H$102,1,AD$6-2025)*(1+((1+INDEX(Inputs!$D$110:$H$110,1,AD$6-2025))^(1/12)-1))^26 | AE20: =Inputs!$D$76*INDEX(Inputs!$D$102:$H$102,1,AE$6-2025)*(1+((1+INDEX(Inputs!$D$110:$H$110,1,AE$6-2025))^(1/12)-1))^27 | AF20: =Inputs!$D$76*INDEX(Inputs!$D$102:$H$102,1,AF$6-2025)*(1+((1+INDEX(Inputs!$D$110:$H$110,1,AF$6-2025))^(1/12)-1))^28 | AG20: =Inputs!$D$76*INDEX(Inputs!$D$102:$H$102,1,AG$6-2025)*(1+((1+INDEX(Inputs!$D$110:$H$110,1,AG$6-2025))^(1/12)-1))^29 | AH20: =Inputs!$D$76*INDEX(Inputs!$D$102:$H$102,1,AH$6-2025)*(1+((1+INDEX(Inputs!$D$110:$H$110,1,AH$6-2025))^(1/12)-1))^30 | AI20: =Inputs!$D$76*INDEX(Inputs!$D$102:$H$102,1,AI$6-2025)*(1+((1+INDEX(Inputs!$D$110:$H$110,1,AI$6-2025))^(1/12)-1))^31 | AJ20: =Inputs!$D$76*INDEX(Inputs!$D$102:$H$102,1,AJ$6-2025)*(1+((1+INDEX(Inputs!$D$110:$H$110,1,AJ$6-2025))^(1/12)-1))^32 | AK20: =Inputs!$D$76*INDEX(Inputs!$D$102:$H$102,1,AK$6-2025)*(1+((1+INDEX(Inputs!$D$110:$H$110,1,AK$6-2025))^(1/12)-1))^33 | AL20: =Inputs!$D$76*INDEX(Inputs!$D$102:$H$102,1,AL$6-2025)*(1+((1+INDEX(Inputs!$D$110:$H$110,1,AL$6-2025))^(1/12)-1))^34 | AM20: =Inputs!$D$76*INDEX(Inputs!$D$102:$H$102,1,AM$6-2025)*(1+((1+INDEX(Inputs!$D$110:$H$110,1,AM$6-2025))^(1/12)-1))^35 | AN20: =Inputs!$D$76*INDEX(Inputs!$D$102:$H$102,1,AN$6-2025)*(1+((1+INDEX(Inputs!$D$110:$H$110,1,AN$6-2025))^(1/12)-1))^36 | AO20: =Inputs!$D$76*INDEX(Inputs!$D$102:$H$102,1,AO$6-2025)*(1+((1+INDEX(Inputs!$D$110:$H$110,1,AO$6-2025))^(1/12)-1))^37 | AP20: =Inputs!$D$76*INDEX(Inputs!$D$102:$H$102,1,AP$6-2025)*(1+((1+INDEX(Inputs!$D$110:$H$110,1,AP$6-2025))^(1/12)-1))^38 | AQ20: =Inputs!$D$76*INDEX(Inputs!$D$102:$H$102,1,AQ$6-2025)*(1+((1+INDEX(Inputs!$D$110:$H$110,1,AQ$6-2025))^(1/12)-1))^39 | AR20: =Inputs!$D$76*INDEX(Inputs!$D$102:$H$102,1,AR$6-2025)*(1+((1+INDEX(Inputs!$D$110:$H$110,1,AR$6-2025))^(1/12)-1))^40 | AS20: =Inputs!$D$76*INDEX(Inputs!$D$102:$H$102,1,AS$6-2025)*(1+((1+INDEX(Inputs!$D$110:$H$110,1,AS$6-2025))^(1/12)-1))^41 | AT20: =Inputs!$D$76*INDEX(Inputs!$D$102:$H$102,1,AT$6-2025)*(1+((1+INDEX(Inputs!$D$110:$H$110,1,AT$6-2025))^(1/12)-1))^42 | AU20: =Inputs!$D$76*INDEX(Inputs!$D$102:$H$102,1,AU$6-2025)*(1+((1+INDEX(Inputs!$D$110:$H$110,1,AU$6-2025))^(1/12)-1))^43 | AV20: =Inputs!$D$76*INDEX(Inputs!$D$102:$H$102,1,AV$6-2025)*(1+((1+INDEX(Inputs!$D$110:$H$110,1,AV$6-2025))^(1/12)-1))^44 | AW20: =Inputs!$D$76*INDEX(Inputs!$D$102:$H$102,1,AW$6-2025)*(1+((1+INDEX(Inputs!$D$110:$H$110,1,AW$6-2025))^(1/12)-1))^45 | AX20: =Inputs!$D$76*INDEX(Inputs!$D$102:$H$102,1,AX$6-2025)*(1+((1+INDEX(Inputs!$D$110:$H$110,1,AX$6-2025))^(1/12)-1))^46 | AY20: =Inputs!$D$76*INDEX(Inputs!$D$102:$H$102,1,AY$6-2025)*(1+((1+INDEX(Inputs!$D$110:$H$110,1,AY$6-2025))^(1/12)-1))^47 | AZ20: =Inputs!$D$76*INDEX(Inputs!$D$102:$H$102,1,AZ$6-2025)*(1+((1+INDEX(Inputs!$D$110:$H$110,1,AZ$6-2025))^(1/12)-1))^48 | BA20: =Inputs!$D$76*INDEX(Inputs!$D$102:$H$102,1,BA$6-2025)*(1+((1+INDEX(Inputs!$D$110:$H$110,1,BA$6-2025))^(1/12)-1))^49 | BB20: =Inputs!$D$76*INDEX(Inputs!$D$102:$H$102,1,BB$6-2025)*(1+((1+INDEX(Inputs!$D$110:$H$110,1,BB$6-2025))^(1/12)-1))^50 | BC20: =Inputs!$D$76*INDEX(Inputs!$D$102:$H$102,1,BC$6-2025)*(1+((1+INDEX(Inputs!$D$110:$H$110,1,BC$6-2025))^(1/12)-1))^51 | BD20: =Inputs!$D$76*INDEX(Inputs!$D$102:$H$102,1,BD$6-2025)*(1+((1+INDEX(Inputs!$D$110:$H$110,1,BD$6-2025))^(1/12)-1))^52 | BE20: =Inputs!$D$76*INDEX(Inputs!$D$102:$H$102,1,BE$6-2025)*(1+((1+INDEX(Inputs!$D$110:$H$110,1,BE$6-2025))^(1/12)-1))^53 | BF20: =Inputs!$D$76*INDEX(Inputs!$D$102:$H$102,1,BF$6-2025)*(1+((1+INDEX(Inputs!$D$110:$H$110,1,BF$6-2025))^(1/12)-1))^54 | BG20: =Inputs!$D$76*INDEX(Inputs!$D$102:$H$102,1,BG$6-2025)*(1+((1+INDEX(Inputs!$D$110:$H$110,1,BG$6-2025))^(1/12)-1))^55 | BH20: =Inputs!$D$76*INDEX(Inputs!$D$102:$H$102,1,BH$6-2025)*(1+((1+INDEX(Inputs!$D$110:$H$110,1,BH$6-2025))^(1/12)-1))^56 | BI20: =Inputs!$D$76*INDEX(Inputs!$D$102:$H$102,1,BI$6-2025)*(1+((1+INDEX(Inputs!$D$110:$H$110,1,BI$6-2025))^(1/12)-1))^57 | BJ20: =Inputs!$D$76*INDEX(Inputs!$D$102:$H$102,1,BJ$6-2025)*(1+((1+INDEX(Inputs!$D$110:$H$110,1,BJ$6-2025))^(1/12)-1))^58 | BK20: =Inputs!$D$76*INDEX(Inputs!$D$102:$H$102,1,BK$6-2025)*(1+((1+INDEX(Inputs!$D$110:$H$110,1,BK$6-2025))^(1/12)-1))^59
B21: Agents ARR | C21: $ | D21: =D19*D20 | E21: =E19*E20 | F21: =F19*F20 | G21: =G19*G20 | H21: =H19*H20 | I21: =I19*I20 | J21: =J19*J20 | K21: =K19*K20 | ... BK21: =BK19*BK20 | BM21: =O21 | BN21: =AA21 | BO21: =AM21 | BP21: =AY21 | BQ21: =BK21
B23: TOTAL ARR
B24: Self serve ARR | C24: $ | D24: ='Rev-Capacity'!D21 | E24: ='Rev-Capacity'!E21 | F24: ='Rev-Capacity'!F21 | G24: ='Rev-Capacity'!G21 | H24: ='Rev-Capacity'!H21 | I24: ='Rev-Capacity'!I21 | J24: ='Rev-Capacity'!J21 | K24: ='Rev-Capacity'!K21 | ... BK24: ='Rev-Capacity'!BK21 | BM24: =O24 | BN24: =AA24 | BO24: =AM24 | BP24: =AY24 | BQ24: =BK24
B25: Core ARR, enterprise plus self serve | C25: $ | D25: =D14+D24 | E25: =E14+E24 | F25: =F14+F24 | G25: =G14+G24 | H25: =H14+H24 | I25: =I14+I24 | J25: =J14+J24 | K25: =K14+K24 | ... BK25: =BK14+BK24 | BM25: =O25 | BN25: =AA25 | BO25: =AM25 | BP25: =AY25 | BQ25: =BK25
B26: Total ARR | C26: $ | D26: =D25+D21 | E26: =E25+E21 | F26: =F25+F21 | G26: =G25+G21 | H26: =H25+H21 | I26: =I25+I21 | J26: =J25+J21 | K26: =K25+K21 | ... BK26: =BK25+BK21 | BM26: =O26 | BN26: =AA26 | BO26: =AM26 | BP26: =AY26 | BQ26: =BK26
B27: Year on year ARR growth | C27: % | D27: =D26/Inputs!$D$9-1 | E27: =E26/Inputs!$D$9-1 | F27: =F26/Inputs!$D$9-1 | G27: =G26/Inputs!$D$9-1 | H27: =H26/Inputs!$D$9-1 | I27: =I26/Inputs!$D$9-1 | J27: =J26/Inputs!$D$9-1 | K27: =K26/Inputs!$D$9-1 | ... O27: =O26/Inputs!$D$9-1 | P27: =P26/D26-1 | Q27: =Q26/E26-1 | R27: =R26/F26-1 | S27: =S26/G26-1 | T27: =T26/H26-1 | U27: =U26/I26-1 | V27: =V26/J26-1 | W27: =W26/K26-1 | ... BK27: =BK26/AY26-1 | BM27: =O27 | BN27: =AA27 | BO27: =AM27 | BP27: =AY27 | BQ27: =BK27

Sheet Headcount
B2: Headcount and Compensation
B5: Month ending | D5: 46053 | E5: 46081 | F5: 46112 | G5: 46142 | H5: 46173 | I5: 46203 | J5: 46234 | K5: 46265 | L5: 46295 | M5: 46326 | N5: 46356 | O5: 46387 | P5: 46418 | Q5: 46446 | R5: 46477 | S5: 46507 | T5: 46538 | U5: 46568 | V5: 46599 | W5: 46630 | X5: 46660 | Y5: 46691 | Z5: 46721 | AA5: 46752 | AB5: 46783 | AC5: 46812 | AD5: 46843 | AE5: 46873 | AF5: 46904 | AG5: 46934 | AH5: 46965 | AI5: 46996 | AJ5: 47026 | AK5: 47057 | AL5: 47087 | AM5: 47118 | AN5: 47149 | AO5: 47177 | AP5: 47208 | AQ5: 47238 | AR5: 47269 | AS5: 47299 | AT5: 47330 | AU5: 47361 | AV5: 47391 | AW5: 47422 | AX5: 47452 | AY5: 47483 | AZ5: 47514 | BA5: 47542 | BB5: 47573 | BC5: 47603 | BD5: 47634 | BE5: 47664 | BF5: 47695 | BG5: 47726 | BH5: 47756 | BI5: 47787 | BJ5: 47817 | BK5: 47848 | BM5: FY2026 | BN5: FY2027 | BO5: FY2028 | BP5: FY2029 | BQ5: FY2030
B6: Fiscal year | D6: 2026 | E6: 2026 | F6: 2026 | G6: 2026 | H6: 2026 | I6: 2026 | J6: 2026 | K6: 2026 | L6: 2026 | M6: 2026 | N6: 2026 | O6: 2026 | P6: 2027 | Q6: 2027 | R6: 2027 | S6: 2027 | T6: 2027 | U6: 2027 | V6: 2027 | W6: 2027 | X6: 2027 | Y6: 2027 | Z6: 2027 | AA6: 2027 | AB6: 2028 | AC6: 2028 | AD6: 2028 | AE6: 2028 | AF6: 2028 | AG6: 2028 | AH6: 2028 | AI6: 2028 | AJ6: 2028 | AK6: 2028 | AL6: 2028 | AM6: 2028 | AN6: 2029 | AO6: 2029 | AP6: 2029 | AQ6: 2029 | AR6: 2029 | AS6: 2029 | AT6: 2029 | AU6: 2029 | AV6: 2029 | AW6: 2029 | AX6: 2029 | AY6: 2029 | AZ6: 2030 | BA6: 2030 | BB6: 2030 | BC6: 2030 | BD6: 2030 | BE6: 2030 | BF6: 2030 | BG6: 2030 | BH6: 2030 | BI6: 2030 | BJ6: 2030 | BK6: 2030
B7: Period | D7: 1 | E7: 2 | F7: 3 | G7: 4 | H7: 5 | I7: 6 | J7: 7 | K7: 8 | L7: 9 | M7: 10 | N7: 11 | O7: 12 | P7: 13 | Q7: 14 | R7: 15 | S7: 16 | T7: 17 | U7: 18 | V7: 19 | W7: 20 | X7: 21 | Y7: 22 | Z7: 23 | AA7: 24 | AB7: 25 | AC7: 26 | AD7: 27 | AE7: 28 | AF7: 29 | AG7: 30 | AH7: 31 | AI7: 32 | AJ7: 33 | AK7: 34 | AL7: 35 | AM7: 36 | AN7: 37 | AO7: 38 | AP7: 39 | AQ7: 40 | AR7: 41 | AS7: 42 | AT7: 43 | AU7: 44 | AV7: 45 | AW7: 46 | AX7: 47 | AY7: 48 | AZ7: 49 | BA7: 50 | BB7: 51 | BC7: 52 | BD7: 53 | BE7: 54 | BF7: 55 | BG7: 56 | BH7: 57 | BI7: 58 | BJ7: 59 | BK7: 60
B9: ROSTER BY FUNCTION
B10: R&D hires per month | C10: # | D10: =INDEX(Inputs!$D$166:$H$166,1,D$6-2025) | E10: =INDEX(Inputs!$D$166:$H$166,1,E$6-2025) | F10: =INDEX(Inputs!$D$166:$H$166,1,F$6-2025) | G10: =INDEX(Inputs!$D$166:$H$166,1,G$6-2025) | H10: =INDEX(Inputs!$D$166:$H$166,1,H$6-2025) | I10: =INDEX(Inputs!$D$166:$H$166,1,I$6-2025) | J10: =INDEX(Inputs!$D$166:$H$166,1,J$6-2025) | K10: =INDEX(Inputs!$D$166:$H$166,1,K$6-2025) | ... BK10: =INDEX(Inputs!$D$166:$H$166,1,BK$6-2025)
B11: R&D headcount | C11: # | D11: =Inputs!$D$128+D10 | E11: =D11+E10 | F11: =E11+F10 | G11: =F11+G10 | H11: =G11+H10 | I11: =H11+I10 | J11: =I11+J10 | K11: =J11+K10 | L11: =K11+L10 | ... BK11: =BJ11+BK10 | BM11: =O11 | BN11: =AA11 | BO11: =AM11 | BP11: =AY11 | BQ11: =BK11
B12: G&A hires per month | C12: # | D12: =INDEX(Inputs!$D$158:$H$158,1,D$6-2025) | E12: =INDEX(Inputs!$D$158:$H$158,1,E$6-2025) | F12: =INDEX(Inputs!$D$158:$H$158,1,F$6-2025) | G12: =INDEX(Inputs!$D$158:$H$158,1,G$6-2025) | H12: =INDEX(Inputs!$D$158:$H$158,1,H$6-2025) | I12: =INDEX(Inputs!$D$158:$H$158,1,I$6-2025) | J12: =INDEX(Inputs!$D$158:$H$158,1,J$6-2025) | K12: =INDEX(Inputs!$D$158:$H$158,1,K$6-2025) | ... BK12: =INDEX(Inputs!$D$158:$H$158,1,BK$6-2025)
B13: G&A headcount | C13: # | D13: =Inputs!$D$131+D12 | E13: =D13+E12 | F13: =E13+F12 | G13: =F13+G12 | H13: =G13+H12 | I13: =H13+I12 | J13: =I13+J12 | K13: =J13+K12 | L13: =K13+L12 | ... BK13: =BJ13+BK12 | BM13: =O13 | BN13: =AA13 | BO13: =AM13 | BP13: =AY13 | BQ13: =BK13
B14: Customer success headcount | C14: # | D14: =MAX('Rev-ARR Bridge'!D17/INDEX(Inputs!$D$150:$H$150,1,D$6-2025),Inputs!$D$130*0.5) | E14: =MAX('Rev-ARR Bridge'!E17/INDEX(Inputs!$D$150:$H$150,1,E$6-2025),Inputs!$D$130*0.5) | F14: =MAX('Rev-ARR Bridge'!F17/INDEX(Inputs!$D$150:$H$150,1,F$6-2025),Inputs!$D$130*0.5) | G14: =MAX('Rev-ARR Bridge'!G17/INDEX(Inputs!$D$150:$H$150,1,G$6-2025),Inputs!$D$130*0.5) | H14: =MAX('Rev-ARR Bridge'!H17/INDEX(Inputs!$D$150:$H$150,1,H$6-2025),Inputs!$D$130*0.5) | I14: =MAX('Rev-ARR Bridge'!I17/INDEX(Inputs!$D$150:$H$150,1,I$6-2025),Inputs!$D$130*0.5) | J14: =MAX('Rev-ARR Bridge'!J17/INDEX(Inputs!$D$150:$H$150,1,J$6-2025),Inputs!$D$130*0.5) | K14: =MAX('Rev-ARR Bridge'!K17/INDEX(Inputs!$D$150:$H$150,1,K$6-2025),Inputs!$D$130*0.5) | ... BK14: =MAX('Rev-ARR Bridge'!BK17/INDEX(Inputs!$D$150:$H$150,1,BK$6-2025),Inputs!$D$130*0.5) | BM14: =O14 | BN14: =AA14 | BO14: =AM14 | BP14: =AY14 | BQ14: =BK14
B15: SDR headcount | C15: # | D15: ='Rev-Capacity'!D12*Inputs!$D$31 | E15: ='Rev-Capacity'!E12*Inputs!$D$31 | F15: ='Rev-Capacity'!F12*Inputs!$D$31 | G15: ='Rev-Capacity'!G12*Inputs!$D$31 | H15: ='Rev-Capacity'!H12*Inputs!$D$31 | I15: ='Rev-Capacity'!I12*Inputs!$D$31 | J15: ='Rev-Capacity'!J12*Inputs!$D$31 | K15: ='Rev-Capacity'!K12*Inputs!$D$31 | ... BK15: ='Rev-Capacity'!BK12*Inputs!$D$31
B16: MKTG headcount | C16: # | D16: ='Rev-Capacity'!D12*Inputs!$D$32 | E16: ='Rev-Capacity'!E12*Inputs!$D$32 | F16: ='Rev-Capacity'!F12*Inputs!$D$32 | G16: ='Rev-Capacity'!G12*Inputs!$D$32 | H16: ='Rev-Capacity'!H12*Inputs!$D$32 | I16: ='Rev-Capacity'!I12*Inputs!$D$32 | J16: ='Rev-Capacity'!J12*Inputs!$D$32 | K16: ='Rev-Capacity'!K12*Inputs!$D$32 | ... BK16: ='Rev-Capacity'!BK12*Inputs!$D$32
B17: SOPS headcount | C17: # | D17: ='Rev-Capacity'!D12*Inputs!$D$33 | E17: ='Rev-Capacity'!E12*Inputs!$D$33 | F17: ='Rev-Capacity'!F12*Inputs!$D$33 | G17: ='Rev-Capacity'!G12*Inputs!$D$33 | H17: ='Rev-Capacity'!H12*Inputs!$D$33 | I17: ='Rev-Capacity'!I12*Inputs!$D$33 | J17: ='Rev-Capacity'!J12*Inputs!$D$33 | K17: ='Rev-Capacity'!K12*Inputs!$D$33 | ... BK17: ='Rev-Capacity'!BK12*Inputs!$D$33
B18: ENABLE headcount | C18: # | D18: ='Rev-Capacity'!D12*Inputs!$D$34 | E18: ='Rev-Capacity'!E12*Inputs!$D$34 | F18: ='Rev-Capacity'!F12*Inputs!$D$34 | G18: ='Rev-Capacity'!G12*Inputs!$D$34 | H18: ='Rev-Capacity'!H12*Inputs!$D$34 | I18: ='Rev-Capacity'!I12*Inputs!$D$34 | J18: ='Rev-Capacity'!J12*Inputs!$D$34 | K18: ='Rev-Capacity'!K12*Inputs!$D$34 | ... BK18: ='Rev-Capacity'!BK12*Inputs!$D$34
B19: Sales and marketing headcount | C19: # | D19: ='Rev-Capacity'!D12+D15+D16+D17+D18 | E19: ='Rev-Capacity'!E12+E15+E16+E17+E18 | F19: ='Rev-Capacity'!F12+F15+F16+F17+F18 | G19: ='Rev-Capacity'!G12+G15+G16+G17+G18 | H19: ='Rev-Capacity'!H12+H15+H16+H17+H18 | I19: ='Rev-Capacity'!I12+I15+I16+I17+I18 | J19: ='Rev-Capacity'!J12+J15+J16+J17+J18 | K19: ='Rev-Capacity'!K12+K15+K16+K17+K18 | ... BK19: ='Rev-Capacity'!BK12+BK15+BK16+BK17+BK18 | BM19: =O19 | BN19: =AA19 | BO19: =AM19 | BP19: =AY19 | BQ19: =BK19
B20: Total headcount | C20: # | D20: =D11+D13+D14+D19 | E20: =E11+E13+E14+E19 | F20: =F11+F13+F14+F19 | G20: =G11+G13+G14+G19 | H20: =H11+H13+H14+H19 | I20: =I11+I13+I14+I19 | J20: =J11+J13+J14+J19 | K20: =K11+K13+K14+K19 | ... BK20: =BK11+BK13+BK14+BK19 | BM20: =O20 | BN20: =AA20 | BO20: =AM20 | BP20: =AY20 | BQ20: =BK20
B21: Gross hires including backfill | C21: # | D21: =D10+D12+'Rev-Capacity'!D10+(Inputs!$D$128+Inputs!$D$131)*Inputs!$D$141/12+'Rev-Capacity'!D11 | E21: =E10+E12+'Rev-Capacity'!E10+(D11+D13)*Inputs!$D$141/12+'Rev-Capacity'!E11 | F21: =F10+F12+'Rev-Capacity'!F10+(E11+E13)*Inputs!$D$141/12+'Rev-Capacity'!F11 | G21: =G10+G12+'Rev-Capacity'!G10+(F11+F13)*Inputs!$D$141/12+'Rev-Capacity'!G11 | H21: =H10+H12+'Rev-Capacity'!H10+(G11+G13)*Inputs!$D$141/12+'Rev-Capacity'!H11 | I21: =I10+I12+'Rev-Capacity'!I10+(H11+H13)*Inputs!$D$141/12+'Rev-Capacity'!I11 | J21: =J10+J12+'Rev-Capacity'!J10+(I11+I13)*Inputs!$D$141/12+'Rev-Capacity'!J11 | K21: =K10+K12+'Rev-Capacity'!K10+(J11+J13)*Inputs!$D$141/12+'Rev-Capacity'!K11 | L21: =L10+L12+'Rev-Capacity'!L10+(K11+K13)*Inputs!$D$141/12+'Rev-Capacity'!L11 | ... BK21: =BK10+BK12+'Rev-Capacity'!BK10+(BJ11+BJ13)*Inputs!$D$141/12+'Rev-Capacity'!BK11 | BM21: =SUM(D21:O21) | BN21: =SUM(P21:AA21) | BO21: =SUM(AB21:AM21) | BP21: =SUM(AN21:AY21) | BQ21: =SUM(AZ21:BK21)
B23: PAYROLL
B24: Compensation escalator | C24: x | D24: =(1+((1+Inputs!$D$139)^(1/12)-1))^0 | E24: =(1+((1+Inputs!$D$139)^(1/12)-1))^1 | F24: =(1+((1+Inputs!$D$139)^(1/12)-1))^2 | G24: =(1+((1+Inputs!$D$139)^(1/12)-1))^3 | H24: =(1+((1+Inputs!$D$139)^(1/12)-1))^4 | I24: =(1+((1+Inputs!$D$139)^(1/12)-1))^5 | J24: =(1+((1+Inputs!$D$139)^(1/12)-1))^6 | K24: =(1+((1+Inputs!$D$139)^(1/12)-1))^7 | L24: =(1+((1+Inputs!$D$139)^(1/12)-1))^8 | M24: =(1+((1+Inputs!$D$139)^(1/12)-1))^9 | N24: =(1+((1+Inputs!$D$139)^(1/12)-1))^10 | O24: =(1+((1+Inputs!$D$139)^(1/12)-1))^11 | P24: =(1+((1+Inputs!$D$139)^(1/12)-1))^12 | Q24: =(1+((1+Inputs!$D$139)^(1/12)-1))^13 | R24: =(1+((1+Inputs!$D$139)^(1/12)-1))^14 | S24: =(1+((1+Inputs!$D$139)^(1/12)-1))^15 | T24: =(1+((1+Inputs!$D$139)^(1/12)-1))^16 | U24: =(1+((1+Inputs!$D$139)^(1/12)-1))^17 | V24: =(1+((1+Inputs!$D$139)^(1/12)-1))^18 | W24: =(1+((1+Inputs!$D$139)^(1/12)-1))^19 | X24: =(1+((1+Inputs!$D$139)^(1/12)-1))^20 | Y24: =(1+((1+Inputs!$D$139)^(1/12)-1))^21 | Z24: =(1+((1+Inputs!$D$139)^(1/12)-1))^22 | AA24: =(1+((1+Inputs!$D$139)^(1/12)-1))^23 | AB24: =(1+((1+Inputs!$D$139)^(1/12)-1))^24 | AC24: =(1+((1+Inputs!$D$139)^(1/12)-1))^25 | AD24: =(1+((1+Inputs!$D$139)^(1/12)-1))^26 | AE24: =(1+((1+Inputs!$D$139)^(1/12)-1))^27 | AF24: =(1+((1+Inputs!$D$139)^(1/12)-1))^28 | AG24: =(1+((1+Inputs!$D$139)^(1/12)-1))^29 | AH24: =(1+((1+Inputs!$D$139)^(1/12)-1))^30 | AI24: =(1+((1+Inputs!$D$139)^(1/12)-1))^31 | AJ24: =(1+((1+Inputs!$D$139)^(1/12)-1))^32 | AK24: =(1+((1+Inputs!$D$139)^(1/12)-1))^33 | AL24: =(1+((1+Inputs!$D$139)^(1/12)-1))^34 | AM24: =(1+((1+Inputs!$D$139)^(1/12)-1))^35 | AN24: =(1+((1+Inputs!$D$139)^(1/12)-1))^36 | AO24: =(1+((1+Inputs!$D$139)^(1/12)-1))^37 | AP24: =(1+((1+Inputs!$D$139)^(1/12)-1))^38 | AQ24: =(1+((1+Inputs!$D$139)^(1/12)-1))^39 | AR24: =(1+((1+Inputs!$D$139)^(1/12)-1))^40 | AS24: =(1+((1+Inputs!$D$139)^(1/12)-1))^41 | AT24: =(1+((1+Inputs!$D$139)^(1/12)-1))^42 | AU24: =(1+((1+Inputs!$D$139)^(1/12)-1))^43 | AV24: =(1+((1+Inputs!$D$139)^(1/12)-1))^44 | AW24: =(1+((1+Inputs!$D$139)^(1/12)-1))^45 | AX24: =(1+((1+Inputs!$D$139)^(1/12)-1))^46 | AY24: =(1+((1+Inputs!$D$139)^(1/12)-1))^47 | AZ24: =(1+((1+Inputs!$D$139)^(1/12)-1))^48 | BA24: =(1+((1+Inputs!$D$139)^(1/12)-1))^49 | BB24: =(1+((1+Inputs!$D$139)^(1/12)-1))^50 | BC24: =(1+((1+Inputs!$D$139)^(1/12)-1))^51 | BD24: =(1+((1+Inputs!$D$139)^(1/12)-1))^52 | BE24: =(1+((1+Inputs!$D$139)^(1/12)-1))^53 | BF24: =(1+((1+Inputs!$D$139)^(1/12)-1))^54 | BG24: =(1+((1+Inputs!$D$139)^(1/12)-1))^55 | BH24: =(1+((1+Inputs!$D$139)^(1/12)-1))^56 | BI24: =(1+((1+Inputs!$D$139)^(1/12)-1))^57 | BJ24: =(1+((1+Inputs!$D$139)^(1/12)-1))^58 | BK24: =(1+((1+Inputs!$D$139)^(1/12)-1))^59
B25: RND payroll | C25: $ | D25: =D11*Inputs!$D$132/12*D24 | E25: =E11*Inputs!$D$132/12*E24 | F25: =F11*Inputs!$D$132/12*F24 | G25: =G11*Inputs!$D$132/12*G24 | H25: =H11*Inputs!$D$132/12*H24 | I25: =I11*Inputs!$D$132/12*I24 | J25: =J11*Inputs!$D$132/12*J24 | K25: =K11*Inputs!$D$132/12*K24 | ... BK25: =BK11*Inputs!$D$132/12*BK24 | BM25: =SUM(D25:O25) | BN25: =SUM(P25:AA25) | BO25: =SUM(AB25:AM25) | BP25: =SUM(AN25:AY25) | BQ25: =SUM(AZ25:BK25)
B26: CS payroll | C26: $ | D26: =D14*Inputs!$D$137/12*D24 | E26: =E14*Inputs!$D$137/12*E24 | F26: =F14*Inputs!$D$137/12*F24 | G26: =G14*Inputs!$D$137/12*G24 | H26: =H14*Inputs!$D$137/12*H24 | I26: =I14*Inputs!$D$137/12*I24 | J26: =J14*Inputs!$D$137/12*J24 | K26: =K14*Inputs!$D$137/12*K24 | ... BK26: =BK14*Inputs!$D$137/12*BK24 | BM26: =SUM(D26:O26) | BN26: =SUM(P26:AA26) | BO26: =SUM(AB26:AM26) | BP26: =SUM(AN26:AY26) | BQ26: =SUM(AZ26:BK26)
B27: GA payroll | C27: $ | D27: =D13*Inputs!$D$138/12*D24 | E27: =E13*Inputs!$D$138/12*E24 | F27: =F13*Inputs!$D$138/12*F24 | G27: =G13*Inputs!$D$138/12*G24 | H27: =H13*Inputs!$D$138/12*H24 | I27: =I13*Inputs!$D$138/12*I24 | J27: =J13*Inputs!$D$138/12*J24 | K27: =K13*Inputs!$D$138/12*K24 | ... BK27: =BK13*Inputs!$D$138/12*BK24 | BM27: =SUM(D27:O27) | BN27: =SUM(P27:AA27) | BO27: =SUM(AB27:AM27) | BP27: =SUM(AN27:AY27) | BQ27: =SUM(AZ27:BK27)
B28: S&M payroll | C28: $ | D28: =('Rev-Capacity'!D12*Inputs!$D$133+D15*Inputs!$D$134+D16*Inputs!$D$135+(D17+D18)*Inputs!$D$136)/12*D24 | E28: =('Rev-Capacity'!E12*Inputs!$D$133+E15*Inputs!$D$134+E16*Inputs!$D$135+(E17+E18)*Inputs!$D$136)/12*E24 | F28: =('Rev-Capacity'!F12*Inputs!$D$133+F15*Inputs!$D$134+F16*Inputs!$D$135+(F17+F18)*Inputs!$D$136)/12*F24 | G28: =('Rev-Capacity'!G12*Inputs!$D$133+G15*Inputs!$D$134+G16*Inputs!$D$135+(G17+G18)*Inputs!$D$136)/12*G24 | H28: =('Rev-Capacity'!H12*Inputs!$D$133+H15*Inputs!$D$134+H16*Inputs!$D$135+(H17+H18)*Inputs!$D$136)/12*H24 | I28: =('Rev-Capacity'!I12*Inputs!$D$133+I15*Inputs!$D$134+I16*Inputs!$D$135+(I17+I18)*Inputs!$D$136)/12*I24 | J28: =('Rev-Capacity'!J12*Inputs!$D$133+J15*Inputs!$D$134+J16*Inputs!$D$135+(J17+J18)*Inputs!$D$136)/12*J24 | K28: =('Rev-Capacity'!K12*Inputs!$D$133+K15*Inputs!$D$134+K16*Inputs!$D$135+(K17+K18)*Inputs!$D$136)/12*K24 | ... BK28: =('Rev-Capacity'!BK12*Inputs!$D$133+BK15*Inputs!$D$134+BK16*Inputs!$D$135+(BK17+BK18)*Inputs!$D$136)/12*BK24 | BM28: =SUM(D28:O28) | BN28: =SUM(P28:AA28) | BO28: =SUM(AB28:AM28) | BP28: =SUM(AN28:AY28) | BQ28: =SUM(AZ28:BK28)
B29: Total payroll | C29: $ | D29: =D25+D26+D27+D28 | E29: =E25+E26+E27+E28 | F29: =F25+F26+F27+F28 | G29: =G25+G26+G27+G28 | H29: =H25+H26+H27+H28 | I29: =I25+I26+I27+I28 | J29: =J25+J26+J27+J28 | K29: =K25+K26+K27+K28 | ... BK29: =BK25+BK26+BK27+BK28 | BM29: =SUM(D29:O29) | BN29: =SUM(P29:AA29) | BO29: =SUM(AB29:AM29) | BP29: =SUM(AN29:AY29) | BQ29: =SUM(AZ29:BK29)
B30: Stock compensation, non cash | C30: $ | D30: =D29*Inputs!$D$143 | E30: =E29*Inputs!$D$143 | F30: =F29*Inputs!$D$143 | G30: =G29*Inputs!$D$143 | H30: =H29*Inputs!$D$143 | I30: =I29*Inputs!$D$143 | J30: =J29*Inputs!$D$143 | K30: =K29*Inputs!$D$143 | ... BK30: =BK29*Inputs!$D$143 | BM30: =SUM(D30:O30) | BN30: =SUM(P30:AA30) | BO30: =SUM(AB30:AM30) | BP30: =SUM(AN30:AY30) | BQ30: =SUM(AZ30:BK30)
B31: Recruiting cost | C31: $ | D31: =D21*Inputs!$D$142 | E31: =E21*Inputs!$D$142 | F31: =F21*Inputs!$D$142 | G31: =G21*Inputs!$D$142 | H31: =H21*Inputs!$D$142 | I31: =I21*Inputs!$D$142 | J31: =J21*Inputs!$D$142 | K31: =K21*Inputs!$D$142 | ... BK31: =BK21*Inputs!$D$142 | BM31: =SUM(D31:O31) | BN31: =SUM(P31:AA31) | BO31: =SUM(AB31:AM31) | BP31: =SUM(AN31:AY31) | BQ31: =SUM(AZ31:BK31)

Sheet P&L
B2: Profit and Loss
B5: Month ending | D5: 46053 | E5: 46081 | F5: 46112 | G5: 46142 | H5: 46173 | I5: 46203 | J5: 46234 | K5: 46265 | L5: 46295 | M5: 46326 | N5: 46356 | O5: 46387 | P5: 46418 | Q5: 46446 | R5: 46477 | S5: 46507 | T5: 46538 | U5: 46568 | V5: 46599 | W5: 46630 | X5: 46660 | Y5: 46691 | Z5: 46721 | AA5: 46752 | AB5: 46783 | AC5: 46812 | AD5: 46843 | AE5: 46873 | AF5: 46904 | AG5: 46934 | AH5: 46965 | AI5: 46996 | AJ5: 47026 | AK5: 47057 | AL5: 47087 | AM5: 47118 | AN5: 47149 | AO5: 47177 | AP5: 47208 | AQ5: 47238 | AR5: 47269 | AS5: 47299 | AT5: 47330 | AU5: 47361 | AV5: 47391 | AW5: 47422 | AX5: 47452 | AY5: 47483 | AZ5: 47514 | BA5: 47542 | BB5: 47573 | BC5: 47603 | BD5: 47634 | BE5: 47664 | BF5: 47695 | BG5: 47726 | BH5: 47756 | BI5: 47787 | BJ5: 47817 | BK5: 47848 | BM5: FY2026 | BN5: FY2027 | BO5: FY2028 | BP5: FY2029 | BQ5: FY2030
B6: Fiscal year | D6: 2026 | E6: 2026 | F6: 2026 | G6: 2026 | H6: 2026 | I6: 2026 | J6: 2026 | K6: 2026 | L6: 2026 | M6: 2026 | N6: 2026 | O6: 2026 | P6: 2027 | Q6: 2027 | R6: 2027 | S6: 2027 | T6: 2027 | U6: 2027 | V6: 2027 | W6: 2027 | X6: 2027 | Y6: 2027 | Z6: 2027 | AA6: 2027 | AB6: 2028 | AC6: 2028 | AD6: 2028 | AE6: 2028 | AF6: 2028 | AG6: 2028 | AH6: 2028 | AI6: 2028 | AJ6: 2028 | AK6: 2028 | AL6: 2028 | AM6: 2028 | AN6: 2029 | AO6: 2029 | AP6: 2029 | AQ6: 2029 | AR6: 2029 | AS6: 2029 | AT6: 2029 | AU6: 2029 | AV6: 2029 | AW6: 2029 | AX6: 2029 | AY6: 2029 | AZ6: 2030 | BA6: 2030 | BB6: 2030 | BC6: 2030 | BD6: 2030 | BE6: 2030 | BF6: 2030 | BG6: 2030 | BH6: 2030 | BI6: 2030 | BJ6: 2030 | BK6: 2030
B7: Period | D7: 1 | E7: 2 | F7: 3 | G7: 4 | H7: 5 | I7: 6 | J7: 7 | K7: 8 | L7: 9 | M7: 10 | N7: 11 | O7: 12 | P7: 13 | Q7: 14 | R7: 15 | S7: 16 | T7: 17 | U7: 18 | V7: 19 | W7: 20 | X7: 21 | Y7: 22 | Z7: 23 | AA7: 24 | AB7: 25 | AC7: 26 | AD7: 27 | AE7: 28 | AF7: 29 | AG7: 30 | AH7: 31 | AI7: 32 | AJ7: 33 | AK7: 34 | AL7: 35 | AM7: 36 | AN7: 37 | AO7: 38 | AP7: 39 | AQ7: 40 | AR7: 41 | AS7: 42 | AT7: 43 | AU7: 44 | AV7: 45 | AW7: 46 | AX7: 47 | AY7: 48 | AZ7: 49 | BA7: 50 | BB7: 51 | BC7: 52 | BD7: 53 | BE7: 54 | BF7: 55 | BG7: 56 | BH7: 57 | BI7: 58 | BJ7: 59 | BK7: 60
B9: REVENUE
B10: Core revenue | C10: $ | D10: =Inputs!$D$9/12 | E10: ='Rev-ARR Bridge'!D25/12 | F10: ='Rev-ARR Bridge'!E25/12 | G10: ='Rev-ARR Bridge'!F25/12 | H10: ='Rev-ARR Bridge'!G25/12 | I10: ='Rev-ARR Bridge'!H25/12 | J10: ='Rev-ARR Bridge'!I25/12 | K10: ='Rev-ARR Bridge'!J25/12 | L10: ='Rev-ARR Bridge'!K25/12 | ... BK10: ='Rev-ARR Bridge'!BJ25/12 | BM10: =SUM(D10:O10) | BN10: =SUM(P10:AA10) | BO10: =SUM(AB10:AM10) | BP10: =SUM(AN10:AY10) | BQ10: =SUM(AZ10:BK10)
B11: Self serve revenue, memo | C11: $ | D11: =Inputs!$D$17/12 | E11: ='Rev-ARR Bridge'!D24/12 | F11: ='Rev-ARR Bridge'!E24/12 | G11: ='Rev-ARR Bridge'!F24/12 | H11: ='Rev-ARR Bridge'!G24/12 | I11: ='Rev-ARR Bridge'!H24/12 | J11: ='Rev-ARR Bridge'!I24/12 | K11: ='Rev-ARR Bridge'!J24/12 | L11: ='Rev-ARR Bridge'!K24/12 | ... BK11: ='Rev-ARR Bridge'!BJ24/12
B12: Agents revenue | C12: $ | D12: =0 | E12: ='Rev-ARR Bridge'!D21/12 | F12: ='Rev-ARR Bridge'!E21/12 | G12: ='Rev-ARR Bridge'!F21/12 | H12: ='Rev-ARR Bridge'!G21/12 | I12: ='Rev-ARR Bridge'!H21/12 | J12: ='Rev-ARR Bridge'!I21/12 | K12: ='Rev-ARR Bridge'!J21/12 | L12: ='Rev-ARR Bridge'!K21/12 | ... BK12: ='Rev-ARR Bridge'!BJ21/12 | BM12: =SUM(D12:O12) | BN12: =SUM(P12:AA12) | BO12: =SUM(AB12:AM12) | BP12: =SUM(AN12:AY12) | BQ12: =SUM(AZ12:BK12)
B13: Total revenue | C13: $ | D13: =D10+D12 | E13: =E10+E12 | F13: =F10+F12 | G13: =G10+G12 | H13: =H10+H12 | I13: =I10+I12 | J13: =J10+J12 | K13: =K10+K12 | ... BK13: =BK10+BK12 | BM13: =SUM(D13:O13) | BN13: =SUM(P13:AA13) | BO13: =SUM(AB13:AM13) | BP13: =SUM(AN13:AY13) | BQ13: =SUM(AZ13:BK13)
B15: COST OF REVENUE
B16: Queries per customer per month | C16: # | D16: =Inputs!$D$114*Inputs!$D$115*Inputs!$D$116*(1+((1+Inputs!$D$118)^(1/12)-1))^0 | E16: =Inputs!$D$114*Inputs!$D$115*Inputs!$D$116*(1+((1+Inputs!$D$118)^(1/12)-1))^1 | F16: =Inputs!$D$114*Inputs!$D$115*Inputs!$D$116*(1+((1+Inputs!$D$118)^(1/12)-1))^2 | G16: =Inputs!$D$114*Inputs!$D$115*Inputs!$D$116*(1+((1+Inputs!$D$118)^(1/12)-1))^3 | H16: =Inputs!$D$114*Inputs!$D$115*Inputs!$D$116*(1+((1+Inputs!$D$118)^(1/12)-1))^4 | I16: =Inputs!$D$114*Inputs!$D$115*Inputs!$D$116*(1+((1+Inputs!$D$118)^(1/12)-1))^5 | J16: =Inputs!$D$114*Inputs!$D$115*Inputs!$D$116*(1+((1+Inputs!$D$118)^(1/12)-1))^6 | K16: =Inputs!$D$114*Inputs!$D$115*Inputs!$D$116*(1+((1+Inputs!$D$118)^(1/12)-1))^7 | L16: =Inputs!$D$114*Inputs!$D$115*Inputs!$D$116*(1+((1+Inputs!$D$118)^(1/12)-1))^8 | M16: =Inputs!$D$114*Inputs!$D$115*Inputs!$D$116*(1+((1+Inputs!$D$118)^(1/12)-1))^9 | N16: =Inputs!$D$114*Inputs!$D$115*Inputs!$D$116*(1+((1+Inputs!$D$118)^(1/12)-1))^10 | O16: =Inputs!$D$114*Inputs!$D$115*Inputs!$D$116*(1+((1+Inputs!$D$118)^(1/12)-1))^11 | P16: =Inputs!$D$114*Inputs!$D$115*Inputs!$D$116*(1+((1+Inputs!$D$118)^(1/12)-1))^12 | Q16: =Inputs!$D$114*Inputs!$D$115*Inputs!$D$116*(1+((1+Inputs!$D$118)^(1/12)-1))^13 | R16: =Inputs!$D$114*Inputs!$D$115*Inputs!$D$116*(1+((1+Inputs!$D$118)^(1/12)-1))^14 | S16: =Inputs!$D$114*Inputs!$D$115*Inputs!$D$116*(1+((1+Inputs!$D$118)^(1/12)-1))^15 | T16: =Inputs!$D$114*Inputs!$D$115*Inputs!$D$116*(1+((1+Inputs!$D$118)^(1/12)-1))^16 | U16: =Inputs!$D$114*Inputs!$D$115*Inputs!$D$116*(1+((1+Inputs!$D$118)^(1/12)-1))^17 | V16: =Inputs!$D$114*Inputs!$D$115*Inputs!$D$116*(1+((1+Inputs!$D$118)^(1/12)-1))^18 | W16: =Inputs!$D$114*Inputs!$D$115*Inputs!$D$116*(1+((1+Inputs!$D$118)^(1/12)-1))^19 | X16: =Inputs!$D$114*Inputs!$D$115*Inputs!$D$116*(1+((1+Inputs!$D$118)^(1/12)-1))^20 | Y16: =Inputs!$D$114*Inputs!$D$115*Inputs!$D$116*(1+((1+Inputs!$D$118)^(1/12)-1))^21 | Z16: =Inputs!$D$114*Inputs!$D$115*Inputs!$D$116*(1+((1+Inputs!$D$118)^(1/12)-1))^22 | AA16: =Inputs!$D$114*Inputs!$D$115*Inputs!$D$116*(1+((1+Inputs!$D$118)^(1/12)-1))^23 | AB16: =Inputs!$D$114*Inputs!$D$115*Inputs!$D$116*(1+((1+Inputs!$D$118)^(1/12)-1))^24 | AC16: =Inputs!$D$114*Inputs!$D$115*Inputs!$D$116*(1+((1+Inputs!$D$118)^(1/12)-1))^25 | AD16: =Inputs!$D$114*Inputs!$D$115*Inputs!$D$116*(1+((1+Inputs!$D$118)^(1/12)-1))^26 | AE16: =Inputs!$D$114*Inputs!$D$115*Inputs!$D$116*(1+((1+Inputs!$D$118)^(1/12)-1))^27 | AF16: =Inputs!$D$114*Inputs!$D$115*Inputs!$D$116*(1+((1+Inputs!$D$118)^(1/12)-1))^28 | AG16: =Inputs!$D$114*Inputs!$D$115*Inputs!$D$116*(1+((1+Inputs!$D$118)^(1/12)-1))^29 | AH16: =Inputs!$D$114*Inputs!$D$115*Inputs!$D$116*(1+((1+Inputs!$D$118)^(1/12)-1))^30 | AI16: =Inputs!$D$114*Inputs!$D$115*Inputs!$D$116*(1+((1+Inputs!$D$118)^(1/12)-1))^31 | AJ16: =Inputs!$D$114*Inputs!$D$115*Inputs!$D$116*(1+((1+Inputs!$D$118)^(1/12)-1))^32 | AK16: =Inputs!$D$114*Inputs!$D$115*Inputs!$D$116*(1+((1+Inputs!$D$118)^(1/12)-1))^33 | AL16: =Inputs!$D$114*Inputs!$D$115*Inputs!$D$116*(1+((1+Inputs!$D$118)^(1/12)-1))^34 | AM16: =Inputs!$D$114*Inputs!$D$115*Inputs!$D$116*(1+((1+Inputs!$D$118)^(1/12)-1))^35 | AN16: =Inputs!$D$114*Inputs!$D$115*Inputs!$D$116*(1+((1+Inputs!$D$118)^(1/12)-1))^36 | AO16: =Inputs!$D$114*Inputs!$D$115*Inputs!$D$116*(1+((1+Inputs!$D$118)^(1/12)-1))^37 | AP16: =Inputs!$D$114*Inputs!$D$115*Inputs!$D$116*(1+((1+Inputs!$D$118)^(1/12)-1))^38 | AQ16: =Inputs!$D$114*Inputs!$D$115*Inputs!$D$116*(1+((1+Inputs!$D$118)^(1/12)-1))^39 | AR16: =Inputs!$D$114*Inputs!$D$115*Inputs!$D$116*(1+((1+Inputs!$D$118)^(1/12)-1))^40 | AS16: =Inputs!$D$114*Inputs!$D$115*Inputs!$D$116*(1+((1+Inputs!$D$118)^(1/12)-1))^41 | AT16: =Inputs!$D$114*Inputs!$D$115*Inputs!$D$116*(1+((1+Inputs!$D$118)^(1/12)-1))^42 | AU16: =Inputs!$D$114*Inputs!$D$115*Inputs!$D$116*(1+((1+Inputs!$D$118)^(1/12)-1))^43 | AV16: =Inputs!$D$114*Inputs!$D$115*Inputs!$D$116*(1+((1+Inputs!$D$118)^(1/12)-1))^44 | AW16: =Inputs!$D$114*Inputs!$D$115*Inputs!$D$116*(1+((1+Inputs!$D$118)^(1/12)-1))^45 | AX16: =Inputs!$D$114*Inputs!$D$115*Inputs!$D$116*(1+((1+Inputs!$D$118)^(1/12)-1))^46 | AY16: =Inputs!$D$114*Inputs!$D$115*Inputs!$D$116*(1+((1+Inputs!$D$118)^(1/12)-1))^47 | AZ16: =Inputs!$D$114*Inputs!$D$115*Inputs!$D$116*(1+((1+Inputs!$D$118)^(1/12)-1))^48 | BA16: =Inputs!$D$114*Inputs!$D$115*Inputs!$D$116*(1+((1+Inputs!$D$118)^(1/12)-1))^49 | BB16: =Inputs!$D$114*Inputs!$D$115*Inputs!$D$116*(1+((1+Inputs!$D$118)^(1/12)-1))^50 | BC16: =Inputs!$D$114*Inputs!$D$115*Inputs!$D$116*(1+((1+Inputs!$D$118)^(1/12)-1))^51 | BD16: =Inputs!$D$114*Inputs!$D$115*Inputs!$D$116*(1+((1+Inputs!$D$118)^(1/12)-1))^52 | BE16: =Inputs!$D$114*Inputs!$D$115*Inputs!$D$116*(1+((1+Inputs!$D$118)^(1/12)-1))^53 | BF16: =Inputs!$D$114*Inputs!$D$115*Inputs!$D$116*(1+((1+Inputs!$D$118)^(1/12)-1))^54 | BG16: =Inputs!$D$114*Inputs!$D$115*Inputs!$D$116*(1+((1+Inputs!$D$118)^(1/12)-1))^55 | BH16: =Inputs!$D$114*Inputs!$D$115*Inputs!$D$116*(1+((1+Inputs!$D$118)^(1/12)-1))^56 | BI16: =Inputs!$D$114*Inputs!$D$115*Inputs!$D$116*(1+((1+Inputs!$D$118)^(1/12)-1))^57 | BJ16: =Inputs!$D$114*Inputs!$D$115*Inputs!$D$116*(1+((1+Inputs!$D$118)^(1/12)-1))^58 | BK16: =Inputs!$D$114*Inputs!$D$115*Inputs!$D$116*(1+((1+Inputs!$D$118)^(1/12)-1))^59
B17: Cost per query | C17: $ | D17: =Inputs!$D$119*(1-Inputs!$D$120)^(0/12) | E17: =Inputs!$D$119*(1-Inputs!$D$120)^(1/12) | F17: =Inputs!$D$119*(1-Inputs!$D$120)^(2/12) | G17: =Inputs!$D$119*(1-Inputs!$D$120)^(3/12) | H17: =Inputs!$D$119*(1-Inputs!$D$120)^(4/12) | I17: =Inputs!$D$119*(1-Inputs!$D$120)^(5/12) | J17: =Inputs!$D$119*(1-Inputs!$D$120)^(6/12) | K17: =Inputs!$D$119*(1-Inputs!$D$120)^(7/12) | L17: =Inputs!$D$119*(1-Inputs!$D$120)^(8/12) | M17: =Inputs!$D$119*(1-Inputs!$D$120)^(9/12) | N17: =Inputs!$D$119*(1-Inputs!$D$120)^(10/12) | O17: =Inputs!$D$119*(1-Inputs!$D$120)^(11/12) | P17: =Inputs!$D$119*(1-Inputs!$D$120)^(12/12) | Q17: =Inputs!$D$119*(1-Inputs!$D$120)^(13/12) | R17: =Inputs!$D$119*(1-Inputs!$D$120)^(14/12) | S17: =Inputs!$D$119*(1-Inputs!$D$120)^(15/12) | T17: =Inputs!$D$119*(1-Inputs!$D$120)^(16/12) | U17: =Inputs!$D$119*(1-Inputs!$D$120)^(17/12) | V17: =Inputs!$D$119*(1-Inputs!$D$120)^(18/12) | W17: =Inputs!$D$119*(1-Inputs!$D$120)^(19/12) | X17: =Inputs!$D$119*(1-Inputs!$D$120)^(20/12) | Y17: =Inputs!$D$119*(1-Inputs!$D$120)^(21/12) | Z17: =Inputs!$D$119*(1-Inputs!$D$120)^(22/12) | AA17: =Inputs!$D$119*(1-Inputs!$D$120)^(23/12) | AB17: =Inputs!$D$119*(1-Inputs!$D$120)^(24/12) | AC17: =Inputs!$D$119*(1-Inputs!$D$120)^(25/12) | AD17: =Inputs!$D$119*(1-Inputs!$D$120)^(26/12) | AE17: =Inputs!$D$119*(1-Inputs!$D$120)^(27/12) | AF17: =Inputs!$D$119*(1-Inputs!$D$120)^(28/12) | AG17: =Inputs!$D$119*(1-Inputs!$D$120)^(29/12) | AH17: =Inputs!$D$119*(1-Inputs!$D$120)^(30/12) | AI17: =Inputs!$D$119*(1-Inputs!$D$120)^(31/12) | AJ17: =Inputs!$D$119*(1-Inputs!$D$120)^(32/12) | AK17: =Inputs!$D$119*(1-Inputs!$D$120)^(33/12) | AL17: =Inputs!$D$119*(1-Inputs!$D$120)^(34/12) | AM17: =Inputs!$D$119*(1-Inputs!$D$120)^(35/12) | AN17: =Inputs!$D$119*(1-Inputs!$D$120)^(36/12) | AO17: =Inputs!$D$119*(1-Inputs!$D$120)^(37/12) | AP17: =Inputs!$D$119*(1-Inputs!$D$120)^(38/12) | AQ17: =Inputs!$D$119*(1-Inputs!$D$120)^(39/12) | AR17: =Inputs!$D$119*(1-Inputs!$D$120)^(40/12) | AS17: =Inputs!$D$119*(1-Inputs!$D$120)^(41/12) | AT17: =Inputs!$D$119*(1-Inputs!$D$120)^(42/12) | AU17: =Inputs!$D$119*(1-Inputs!$D$120)^(43/12) | AV17: =Inputs!$D$119*(1-Inputs!$D$120)^(44/12) | AW17: =Inputs!$D$119*(1-Inputs!$D$120)^(45/12) | AX17: =Inputs!$D$119*(1-Inputs!$D$120)^(46/12) | AY17: =Inputs!$D$119*(1-Inputs!$D$120)^(47/12) | AZ17: =Inputs!$D$119*(1-Inputs!$D$120)^(48/12) | BA17: =Inputs!$D$119*(1-Inputs!$D$120)^(49/12) | BB17: =Inputs!$D$119*(1-Inputs!$D$120)^(50/12) | BC17: =Inputs!$D$119*(1-Inputs!$D$120)^(51/12) | BD17: =Inputs!$D$119*(1-Inputs!$D$120)^(52/12) | BE17: =Inputs!$D$119*(1-Inputs!$D$120)^(53/12) | BF17: =Inputs!$D$119*(1-Inputs!$D$120)^(54/12) | BG17: =Inputs!$D$119*(1-Inputs!$D$120)^(55/12) | BH17: =Inputs!$D$119*(1-Inputs!$D$120)^(56/12) | BI17: =Inputs!$D$119*(1-Inputs!$D$120)^(57/12) | BJ17: =Inputs!$D$119*(1-Inputs!$D$120)^(58/12) | BK17: =Inputs!$D$119*(1-Inputs!$D$120)^(59/12)
B18: Inference cost | C18: $ | D18: ='Rev-ARR Bridge'!D17*D16*D17 | E18: ='Rev-ARR Bridge'!E17*E16*E17 | F18: ='Rev-ARR Bridge'!F17*F16*F17 | G18: ='Rev-ARR Bridge'!G17*G16*G17 | H18: ='Rev-ARR Bridge'!H17*H16*H17 | I18: ='Rev-ARR Bridge'!I17*I16*I17 | J18: ='Rev-ARR Bridge'!J17*J16*J17 | K18: ='Rev-ARR Bridge'!K17*K16*K17 | ... BK18: ='Rev-ARR Bridge'!BK17*BK16*BK17 | BM18: =SUM(D18:O18) | BN18: =SUM(P18:AA18) | BO18: =SUM(AB18:AM18) | BP18: =SUM(AN18:AY18) | BQ18: =SUM(AZ18:BK18)
B19: Agents cost | C19: $ | D19: =D12*INDEX(Inputs!$D$121:$H$121,1,D$6-2025) | E19: =E12*INDEX(Inputs!$D$121:$H$121,1,E$6-2025) | F19: =F12*INDEX(Inputs!$D$121:$H$121,1,F$6-2025) | G19: =G12*INDEX(Inputs!$D$121:$H$121,1,G$6-2025) | H19: =H12*INDEX(Inputs!$D$121:$H$121,1,H$6-2025) | I19: =I12*INDEX(Inputs!$D$121:$H$121,1,I$6-2025) | J19: =J12*INDEX(Inputs!$D$121:$H$121,1,J$6-2025) | K19: =K12*INDEX(Inputs!$D$121:$H$121,1,K$6-2025) | ... BK19: =BK12*INDEX(Inputs!$D$121:$H$121,1,BK$6-2025)
B20: Self serve cost | C20: $ | D20: =D11*Inputs!$D$122 | E20: =E11*Inputs!$D$122 | F20: =F11*Inputs!$D$122 | G20: =G11*Inputs!$D$122 | H20: =H11*Inputs!$D$122 | I20: =I11*Inputs!$D$122 | J20: =J11*Inputs!$D$122 | K20: =K11*Inputs!$D$122 | ... BK20: =BK11*Inputs!$D$122
B21: Hosting and infrastructure | C21: $ | D21: =D13*INDEX(Inputs!$D$123:$H$123,1,D$6-2025) | E21: =E13*INDEX(Inputs!$D$123:$H$123,1,E$6-2025) | F21: =F13*INDEX(Inputs!$D$123:$H$123,1,F$6-2025) | G21: =G13*INDEX(Inputs!$D$123:$H$123,1,G$6-2025) | H21: =H13*INDEX(Inputs!$D$123:$H$123,1,H$6-2025) | I21: =I13*INDEX(Inputs!$D$123:$H$123,1,I$6-2025) | J21: =J13*INDEX(Inputs!$D$123:$H$123,1,J$6-2025) | K21: =K13*INDEX(Inputs!$D$123:$H$123,1,K$6-2025) | ... BK21: =BK13*INDEX(Inputs!$D$123:$H$123,1,BK$6-2025)
B22: Third party data | C22: $ | D22: =D13*Inputs!$D$124 | E22: =E13*Inputs!$D$124 | F22: =F13*Inputs!$D$124 | G22: =G13*Inputs!$D$124 | H22: =H13*Inputs!$D$124 | I22: =I13*Inputs!$D$124 | J22: =J13*Inputs!$D$124 | K22: =K13*Inputs!$D$124 | ... BK22: =BK13*Inputs!$D$124
B23: Total cost of revenue | C23: $ | D23: =D18+D19+D20+D21+D22 | E23: =E18+E19+E20+E21+E22 | F23: =F18+F19+F20+F21+F22 | G23: =G18+G19+G20+G21+G22 | H23: =H18+H19+H20+H21+H22 | I23: =I18+I19+I20+I21+I22 | J23: =J18+J19+J20+J21+J22 | K23: =K18+K19+K20+K21+K22 | ... BK23: =BK18+BK19+BK20+BK21+BK22 | BM23: =SUM(D23:O23) | BN23: =SUM(P23:AA23) | BO23: =SUM(AB23:AM23) | BP23: =SUM(AN23:AY23) | BQ23: =SUM(AZ23:BK23)
B24: Gross profit | C24: $ | D24: =D13-D23 | E24: =E13-E23 | F24: =F13-F23 | G24: =G13-G23 | H24: =H13-H23 | I24: =I13-I23 | J24: =J13-J23 | K24: =K13-K23 | ... BK24: =BK13-BK23 | BM24: =SUM(D24:O24) | BN24: =SUM(P24:AA24) | BO24: =SUM(AB24:AM24) | BP24: =SUM(AN24:AY24) | BQ24: =SUM(AZ24:BK24)
B25: Gross margin | C25: % | D25: =IF(D13=0,0,D24/D13) | E25: =IF(E13=0,0,E24/E13) | F25: =IF(F13=0,0,F24/F13) | G25: =IF(G13=0,0,G24/G13) | H25: =IF(H13=0,0,H24/H13) | I25: =IF(I13=0,0,I24/I13) | J25: =IF(J13=0,0,J24/J13) | K25: =IF(K13=0,0,K24/K13) | ... BK25: =IF(BK13=0,0,BK24/BK13) | BM25: =IF(BM13=0,0,BM24/BM13) | BN25: =IF(BN13=0,0,BN24/BN13) | BO25: =IF(BO13=0,0,BO24/BO13) | BP25: =IF(BP13=0,0,BP24/BP13) | BQ25: =IF(BQ13=0,0,BQ24/BQ13)
B27: OPERATING EXPENSE
B28: Software | C28: $ | D28: =Headcount!D20*Inputs!$D$169/12 | E28: =Headcount!E20*Inputs!$D$169/12 | F28: =Headcount!F20*Inputs!$D$169/12 | G28: =Headcount!G20*Inputs!$D$169/12 | H28: =Headcount!H20*Inputs!$D$169/12 | I28: =Headcount!I20*Inputs!$D$169/12 | J28: =Headcount!J20*Inputs!$D$169/12 | K28: =Headcount!K20*Inputs!$D$169/12 | ... BK28: =Headcount!BK20*Inputs!$D$169/12
B29: Travel and entertainment | C29: $ | D29: =Headcount!D20*Inputs!$D$170/12 | E29: =Headcount!E20*Inputs!$D$170/12 | F29: =Headcount!F20*Inputs!$D$170/12 | G29: =Headcount!G20*Inputs!$D$170/12 | H29: =Headcount!H20*Inputs!$D$170/12 | I29: =Headcount!I20*Inputs!$D$170/12 | J29: =Headcount!J20*Inputs!$D$170/12 | K29: =Headcount!K20*Inputs!$D$170/12 | ... BK29: =Headcount!BK20*Inputs!$D$170/12
B30: Facilities including office step | C30: $ | D30: =Headcount!D20*Inputs!$D$172/12+IF(Headcount!D20>=Inputs!$D$173,Inputs!$D$174/12,0) | E30: =Headcount!E20*Inputs!$D$172/12+IF(Headcount!E20>=Inputs!$D$173,Inputs!$D$174/12,0) | F30: =Headcount!F20*Inputs!$D$172/12+IF(Headcount!F20>=Inputs!$D$173,Inputs!$D$174/12,0) | G30: =Headcount!G20*Inputs!$D$172/12+IF(Headcount!G20>=Inputs!$D$173,Inputs!$D$174/12,0) | H30: =Headcount!H20*Inputs!$D$172/12+IF(Headcount!H20>=Inputs!$D$173,Inputs!$D$174/12,0) | I30: =Headcount!I20*Inputs!$D$172/12+IF(Headcount!I20>=Inputs!$D$173,Inputs!$D$174/12,0) | J30: =Headcount!J20*Inputs!$D$172/12+IF(Headcount!J20>=Inputs!$D$173,Inputs!$D$174/12,0) | K30: =Headcount!K20*Inputs!$D$172/12+IF(Headcount!K20>=Inputs!$D$173,Inputs!$D$174/12,0) | ... BK30: =Headcount!BK20*Inputs!$D$172/12+IF(Headcount!BK20>=Inputs!$D$173,Inputs!$D$174/12,0)
B31: Other G&A | C31: $ | D31: =Headcount!D20*Inputs!$D$171/12 | E31: =Headcount!E20*Inputs!$D$171/12 | F31: =Headcount!F20*Inputs!$D$171/12 | G31: =Headcount!G20*Inputs!$D$171/12 | H31: =Headcount!H20*Inputs!$D$171/12 | I31: =Headcount!I20*Inputs!$D$171/12 | J31: =Headcount!J20*Inputs!$D$171/12 | K31: =Headcount!K20*Inputs!$D$171/12 | ... BK31: =Headcount!BK20*Inputs!$D$171/12
B32: R&D compute | C32: $ | D32: =D13*INDEX(Inputs!$D$175:$H$175,1,D$6-2025) | E32: =E13*INDEX(Inputs!$D$175:$H$175,1,E$6-2025) | F32: =F13*INDEX(Inputs!$D$175:$H$175,1,F$6-2025) | G32: =G13*INDEX(Inputs!$D$175:$H$175,1,G$6-2025) | H32: =H13*INDEX(Inputs!$D$175:$H$175,1,H$6-2025) | I32: =I13*INDEX(Inputs!$D$175:$H$175,1,I$6-2025) | J32: =J13*INDEX(Inputs!$D$175:$H$175,1,J$6-2025) | K32: =K13*INDEX(Inputs!$D$175:$H$175,1,K$6-2025) | ... BK32: =BK13*INDEX(Inputs!$D$175:$H$175,1,BK$6-2025)
B33: Marketing programmes | C33: $ | D33: =D13*Inputs!$D$176 | E33: =E13*Inputs!$D$176 | F33: =F13*Inputs!$D$176 | G33: =G13*Inputs!$D$176 | H33: =H13*Inputs!$D$176 | I33: =I13*Inputs!$D$176 | J33: =J13*Inputs!$D$176 | K33: =K13*Inputs!$D$176 | ... BK33: =BK13*Inputs!$D$176
B34: Professional fees | C34: $ | D34: =Inputs!$D$177*(1+Inputs!$D$178)^(D$6-2026)/12 | E34: =Inputs!$D$177*(1+Inputs!$D$178)^(E$6-2026)/12 | F34: =Inputs!$D$177*(1+Inputs!$D$178)^(F$6-2026)/12 | G34: =Inputs!$D$177*(1+Inputs!$D$178)^(G$6-2026)/12 | H34: =Inputs!$D$177*(1+Inputs!$D$178)^(H$6-2026)/12 | I34: =Inputs!$D$177*(1+Inputs!$D$178)^(I$6-2026)/12 | J34: =Inputs!$D$177*(1+Inputs!$D$178)^(J$6-2026)/12 | K34: =Inputs!$D$177*(1+Inputs!$D$178)^(K$6-2026)/12 | ... BK34: =Inputs!$D$177*(1+Inputs!$D$178)^(BK$6-2026)/12
B35: Insurance | C35: $ | D35: =Inputs!$D$179*(1+Inputs!$D$180)^(D$6-2026)/12 | E35: =Inputs!$D$179*(1+Inputs!$D$180)^(E$6-2026)/12 | F35: =Inputs!$D$179*(1+Inputs!$D$180)^(F$6-2026)/12 | G35: =Inputs!$D$179*(1+Inputs!$D$180)^(G$6-2026)/12 | H35: =Inputs!$D$179*(1+Inputs!$D$180)^(H$6-2026)/12 | I35: =Inputs!$D$179*(1+Inputs!$D$180)^(I$6-2026)/12 | J35: =Inputs!$D$179*(1+Inputs!$D$180)^(J$6-2026)/12 | K35: =Inputs!$D$179*(1+Inputs!$D$180)^(K$6-2026)/12 | ... BK35: =Inputs!$D$179*(1+Inputs!$D$180)^(BK$6-2026)/12
B36: Customer success payroll | C36: $ | D36: =Headcount!D26 | E36: =Headcount!E26 | F36: =Headcount!F26 | G36: =Headcount!G26 | H36: =Headcount!H26 | I36: =Headcount!I26 | J36: =Headcount!J26 | K36: =Headcount!K26 | ... BK36: =Headcount!BK26
B37: Sales, marketing and customer success | C37: $ | D37: =Headcount!D28+D36+D33+D29*0.5 | E37: =Headcount!E28+E36+E33+E29*0.5 | F37: =Headcount!F28+F36+F33+F29*0.5 | G37: =Headcount!G28+G36+G33+G29*0.5 | H37: =Headcount!H28+H36+H33+H29*0.5 | I37: =Headcount!I28+I36+I33+I29*0.5 | J37: =Headcount!J28+J36+J33+J29*0.5 | K37: =Headcount!K28+K36+K33+K29*0.5 | ... BK37: =Headcount!BK28+BK36+BK33+BK29*0.5 | BM37: =SUM(D37:O37) | BN37: =SUM(P37:AA37) | BO37: =SUM(AB37:AM37) | BP37: =SUM(AN37:AY37) | BQ37: =SUM(AZ37:BK37)
B38: Research and development | C38: $ | D38: =Headcount!D25+D28*0.5+D32 | E38: =Headcount!E25+E28*0.5+E32 | F38: =Headcount!F25+F28*0.5+F32 | G38: =Headcount!G25+G28*0.5+G32 | H38: =Headcount!H25+H28*0.5+H32 | I38: =Headcount!I25+I28*0.5+I32 | J38: =Headcount!J25+J28*0.5+J32 | K38: =Headcount!K25+K28*0.5+K32 | ... BK38: =Headcount!BK25+BK28*0.5+BK32 | BM38: =SUM(D38:O38) | BN38: =SUM(P38:AA38) | BO38: =SUM(AB38:AM38) | BP38: =SUM(AN38:AY38) | BQ38: =SUM(AZ38:BK38)
B39: General and administrative | C39: $ | D39: =Headcount!D27+Headcount!D31+D34+D35+D30+D31+D28*0.5+D29*0.5 | E39: =Headcount!E27+Headcount!E31+E34+E35+E30+E31+E28*0.5+E29*0.5 | F39: =Headcount!F27+Headcount!F31+F34+F35+F30+F31+F28*0.5+F29*0.5 | G39: =Headcount!G27+Headcount!G31+G34+G35+G30+G31+G28*0.5+G29*0.5 | H39: =Headcount!H27+Headcount!H31+H34+H35+H30+H31+H28*0.5+H29*0.5 | I39: =Headcount!I27+Headcount!I31+I34+I35+I30+I31+I28*0.5+I29*0.5 | J39: =Headcount!J27+Headcount!J31+J34+J35+J30+J31+J28*0.5+J29*0.5 | K39: =Headcount!K27+Headcount!K31+K34+K35+K30+K31+K28*0.5+K29*0.5 | ... BK39: =Headcount!BK27+Headcount!BK31+BK34+BK35+BK30+BK31+BK28*0.5+BK29*0.5 | BM39: =SUM(D39:O39) | BN39: =SUM(P39:AA39) | BO39: =SUM(AB39:AM39) | BP39: =SUM(AN39:AY39) | BQ39: =SUM(AZ39:BK39)
B40: Total operating expense | C40: $ | D40: =D37+D38+D39 | E40: =E37+E38+E39 | F40: =F37+F38+F39 | G40: =G37+G38+G39 | H40: =H37+H38+H39 | I40: =I37+I38+I39 | J40: =J37+J38+J39 | K40: =K37+K38+K39 | ... BK40: =BK37+BK38+BK39 | BM40: =SUM(D40:O40) | BN40: =SUM(P40:AA40) | BO40: =SUM(AB40:AM40) | BP40: =SUM(AN40:AY40) | BQ40: =SUM(AZ40:BK40)
B42: EARNINGS
B43: EBITDA, excluding stock compensation | C43: $ | D43: =D24-D40 | E43: =E24-E40 | F43: =F24-F40 | G43: =G24-G40 | H43: =H24-H40 | I43: =I24-I40 | J43: =J24-J40 | K43: =K24-K40 | ... BK43: =BK24-BK40 | BM43: =SUM(D43:O43) | BN43: =SUM(P43:AA43) | BO43: =SUM(AB43:AM43) | BP43: =SUM(AN43:AY43) | BQ43: =SUM(AZ43:BK43)
B44: Stock compensation, non cash | C44: $ | D44: =D13*Inputs!$D$143 | E44: =E13*Inputs!$D$143 | F44: =F13*Inputs!$D$143 | G44: =G13*Inputs!$D$143 | H44: =H13*Inputs!$D$143 | I44: =I13*Inputs!$D$143 | J44: =J13*Inputs!$D$143 | K44: =K13*Inputs!$D$143 | ... BK44: =BK13*Inputs!$D$143 | BM44: =SUM(D44:O44) | BN44: =SUM(P44:AA44) | BO44: =SUM(AB44:AM44) | BP44: =SUM(AN44:AY44) | BQ44: =SUM(AZ44:BK44)
B45: Operating result after stock compensation | C45: $ | D45: =D43-D44 | E45: =E43-E44 | F45: =F43-F44 | G45: =G43-G44 | H45: =H43-H44 | I45: =I43-I44 | J45: =J43-J44 | K45: =K43-K44 | ... BK45: =BK43-BK44 | BM45: =SUM(D45:O45) | BN45: =SUM(P45:AA45) | BO45: =SUM(AB45:AM45) | BP45: =SUM(AN45:AY45) | BQ45: =SUM(AZ45:BK45)
B46: EBITDA margin | C46: % | D46: =IF(D13=0,0,D43/D13) | E46: =IF(E13=0,0,E43/E13) | F46: =IF(F13=0,0,F43/F13) | G46: =IF(G13=0,0,G43/G13) | H46: =IF(H13=0,0,H43/H13) | I46: =IF(I13=0,0,I43/I13) | J46: =IF(J13=0,0,J43/J13) | K46: =IF(K13=0,0,K43/K13) | ... BK46: =IF(BK13=0,0,BK43/BK13) | BM46: =IF(BM13=0,0,BM43/BM13) | BN46: =IF(BN13=0,0,BN43/BN13) | BO46: =IF(BO13=0,0,BO43/BO13) | BP46: =IF(BP13=0,0,BP43/BP13) | BQ46: =IF(BQ13=0,0,BQ43/BQ13)

Sheet Cash Flow
B2: Cash Flow
B5: Month ending | D5: 46053 | E5: 46081 | F5: 46112 | G5: 46142 | H5: 46173 | I5: 46203 | J5: 46234 | K5: 46265 | L5: 46295 | M5: 46326 | N5: 46356 | O5: 46387 | P5: 46418 | Q5: 46446 | R5: 46477 | S5: 46507 | T5: 46538 | U5: 46568 | V5: 46599 | W5: 46630 | X5: 46660 | Y5: 46691 | Z5: 46721 | AA5: 46752 | AB5: 46783 | AC5: 46812 | AD5: 46843 | AE5: 46873 | AF5: 46904 | AG5: 46934 | AH5: 46965 | AI5: 46996 | AJ5: 47026 | AK5: 47057 | AL5: 47087 | AM5: 47118 | AN5: 47149 | AO5: 47177 | AP5: 47208 | AQ5: 47238 | AR5: 47269 | AS5: 47299 | AT5: 47330 | AU5: 47361 | AV5: 47391 | AW5: 47422 | AX5: 47452 | AY5: 47483 | AZ5: 47514 | BA5: 47542 | BB5: 47573 | BC5: 47603 | BD5: 47634 | BE5: 47664 | BF5: 47695 | BG5: 47726 | BH5: 47756 | BI5: 47787 | BJ5: 47817 | BK5: 47848 | BM5: FY2026 | BN5: FY2027 | BO5: FY2028 | BP5: FY2029 | BQ5: FY2030
B6: Fiscal year | D6: 2026 | E6: 2026 | F6: 2026 | G6: 2026 | H6: 2026 | I6: 2026 | J6: 2026 | K6: 2026 | L6: 2026 | M6: 2026 | N6: 2026 | O6: 2026 | P6: 2027 | Q6: 2027 | R6: 2027 | S6: 2027 | T6: 2027 | U6: 2027 | V6: 2027 | W6: 2027 | X6: 2027 | Y6: 2027 | Z6: 2027 | AA6: 2027 | AB6: 2028 | AC6: 2028 | AD6: 2028 | AE6: 2028 | AF6: 2028 | AG6: 2028 | AH6: 2028 | AI6: 2028 | AJ6: 2028 | AK6: 2028 | AL6: 2028 | AM6: 2028 | AN6: 2029 | AO6: 2029 | AP6: 2029 | AQ6: 2029 | AR6: 2029 | AS6: 2029 | AT6: 2029 | AU6: 2029 | AV6: 2029 | AW6: 2029 | AX6: 2029 | AY6: 2029 | AZ6: 2030 | BA6: 2030 | BB6: 2030 | BC6: 2030 | BD6: 2030 | BE6: 2030 | BF6: 2030 | BG6: 2030 | BH6: 2030 | BI6: 2030 | BJ6: 2030 | BK6: 2030
B7: Period | D7: 1 | E7: 2 | F7: 3 | G7: 4 | H7: 5 | I7: 6 | J7: 7 | K7: 8 | L7: 9 | M7: 10 | N7: 11 | O7: 12 | P7: 13 | Q7: 14 | R7: 15 | S7: 16 | T7: 17 | U7: 18 | V7: 19 | W7: 20 | X7: 21 | Y7: 22 | Z7: 23 | AA7: 24 | AB7: 25 | AC7: 26 | AD7: 27 | AE7: 28 | AF7: 29 | AG7: 30 | AH7: 31 | AI7: 32 | AJ7: 33 | AK7: 34 | AL7: 35 | AM7: 36 | AN7: 37 | AO7: 38 | AP7: 39 | AQ7: 40 | AR7: 41 | AS7: 42 | AT7: 43 | AU7: 44 | AV7: 45 | AW7: 46 | AX7: 47 | AY7: 48 | AZ7: 49 | BA7: 50 | BB7: 51 | BC7: 52 | BD7: 53 | BE7: 54 | BF7: 55 | BG7: 56 | BH7: 57 | BI7: 58 | BJ7: 59 | BK7: 60
B9: BILLINGS AND DEFERRED REVENUE
B10: Deferred revenue factor | C10: x | D10: =Inputs!$D$183*0.5+Inputs!$D$184*1.5/12 | E10: =Inputs!$D$183*0.5+Inputs!$D$184*1.5/12 | F10: =Inputs!$D$183*0.5+Inputs!$D$184*1.5/12 | G10: =Inputs!$D$183*0.5+Inputs!$D$184*1.5/12 | H10: =Inputs!$D$183*0.5+Inputs!$D$184*1.5/12 | I10: =Inputs!$D$183*0.5+Inputs!$D$184*1.5/12 | J10: =Inputs!$D$183*0.5+Inputs!$D$184*1.5/12 | K10: =Inputs!$D$183*0.5+Inputs!$D$184*1.5/12 | ... BK10: =Inputs!$D$183*0.5+Inputs!$D$184*1.5/12
B11: Deferred revenue balance | C11: $ | D11: ='Rev-ARR Bridge'!D25*D10 | E11: ='Rev-ARR Bridge'!E25*E10 | F11: ='Rev-ARR Bridge'!F25*F10 | G11: ='Rev-ARR Bridge'!G25*G10 | H11: ='Rev-ARR Bridge'!H25*H10 | I11: ='Rev-ARR Bridge'!I25*I10 | J11: ='Rev-ARR Bridge'!J25*J10 | K11: ='Rev-ARR Bridge'!K25*K10 | ... BK11: ='Rev-ARR Bridge'!BK25*BK10 | BM11: =O11 | BN11: =AA11 | BO11: =AM11 | BP11: =AY11 | BQ11: =BK11
B12: Change in deferred revenue | C12: $ | D12: =D11-Inputs!$D$9*D10 | E12: =E11-D11 | F12: =F11-E11 | G12: =G11-F11 | H12: =H11-G11 | I12: =I11-H11 | J12: =J11-I11 | K12: =K11-J11 | L12: =L11-K11 | ... BK12: =BK11-BJ11 | BM12: =SUM(D12:O12) | BN12: =SUM(P12:AA12) | BO12: =SUM(AB12:AM12) | BP12: =SUM(AN12:AY12) | BQ12: =SUM(AZ12:BK12)
B13: Core billings | C13: $ | D13: ='P&L'!D10+D12 | E13: ='P&L'!E10+E12 | F13: ='P&L'!F10+F12 | G13: ='P&L'!G10+G12 | H13: ='P&L'!H10+H12 | I13: ='P&L'!I10+I12 | J13: ='P&L'!J10+J12 | K13: ='P&L'!K10+K12 | ... BK13: ='P&L'!BK10+BK12
B14: Agents billings, in arrears | C14: $ | D14: =0 | E14: ='P&L'!D12 | F14: ='P&L'!E12 | G14: ='P&L'!F12 | H14: ='P&L'!G12 | I14: ='P&L'!H12 | J14: ='P&L'!I12 | K14: ='P&L'!J12 | L14: ='P&L'!K12 | ... BK14: ='P&L'!BJ12
B15: Total billings | C15: $ | D15: =D13+D14 | E15: =E13+E14 | F15: =F13+F14 | G15: =G13+G14 | H15: =H13+H14 | I15: =I13+I14 | J15: =J13+J14 | K15: =K13+K14 | ... BK15: =BK13+BK14 | BM15: =SUM(D15:O15) | BN15: =SUM(P15:AA15) | BO15: =SUM(AB15:AM15) | BP15: =SUM(AN15:AY15) | BQ15: =SUM(AZ15:BK15)
B17: WORKING CAPITAL
B18: Accounts receivable | C18: $ | D18: =D15*Inputs!$D$185/30 | E18: =E15*Inputs!$D$185/30 | F18: =F15*Inputs!$D$185/30 | G18: =G15*Inputs!$D$185/30 | H18: =H15*Inputs!$D$185/30 | I18: =I15*Inputs!$D$185/30 | J18: =J15*Inputs!$D$185/30 | K18: =K15*Inputs!$D$185/30 | ... BK18: =BK15*Inputs!$D$185/30 | BM18: =O18 | BN18: =AA18 | BO18: =AM18 | BP18: =AY18 | BQ18: =BK18
B19: Change in receivables | C19: $ | D19: =0 | E19: =E18-D18 | F19: =F18-E18 | G19: =G18-F18 | H19: =H18-G18 | I19: =I18-H18 | J19: =J18-I18 | K19: =K18-J18 | L19: =L18-K18 | ... BK19: =BK18-BJ18
B20: Accounts payable | C20: $ | D20: =('P&L'!D23+'P&L'!D40)*Inputs!$D$186/30 | E20: =('P&L'!E23+'P&L'!E40)*Inputs!$D$186/30 | F20: =('P&L'!F23+'P&L'!F40)*Inputs!$D$186/30 | G20: =('P&L'!G23+'P&L'!G40)*Inputs!$D$186/30 | H20: =('P&L'!H23+'P&L'!H40)*Inputs!$D$186/30 | I20: =('P&L'!I23+'P&L'!I40)*Inputs!$D$186/30 | J20: =('P&L'!J23+'P&L'!J40)*Inputs!$D$186/30 | K20: =('P&L'!K23+'P&L'!K40)*Inputs!$D$186/30 | ... BK20: =('P&L'!BK23+'P&L'!BK40)*Inputs!$D$186/30
B21: Change in payables | C21: $ | D21: =0 | E21: =E20-D20 | F21: =F20-E20 | G21: =G20-F20 | H21: =H20-G20 | I21: =I20-H20 | J21: =J20-I20 | K21: =K20-J20 | L21: =L20-K20 | ... BK21: =BK20-BJ20
B22: Bad debt | C22: $ | D22: =D15*Inputs!$D$187 | E22: =E15*Inputs!$D$187 | F22: =F15*Inputs!$D$187 | G22: =G15*Inputs!$D$187 | H22: =H15*Inputs!$D$187 | I22: =I15*Inputs!$D$187 | J22: =J15*Inputs!$D$187 | K22: =K15*Inputs!$D$187 | ... BK22: =BK15*Inputs!$D$187
B24: CAPITAL AND NON CASH
B25: Capital expenditure | C25: $ | D25: =Headcount!D21*Inputs!$D$188+IF(AND(Headcount!D20>=Inputs!$D$173,Headcount!D20<Inputs!$D$173),Inputs!$D$189,0) | E25: =Headcount!E21*Inputs!$D$188+IF(AND(Headcount!E20>=Inputs!$D$173,Headcount!D20<Inputs!$D$173),Inputs!$D$189,0) | F25: =Headcount!F21*Inputs!$D$188+IF(AND(Headcount!F20>=Inputs!$D$173,Headcount!E20<Inputs!$D$173),Inputs!$D$189,0) | G25: =Headcount!G21*Inputs!$D$188+IF(AND(Headcount!G20>=Inputs!$D$173,Headcount!F20<Inputs!$D$173),Inputs!$D$189,0) | H25: =Headcount!H21*Inputs!$D$188+IF(AND(Headcount!H20>=Inputs!$D$173,Headcount!G20<Inputs!$D$173),Inputs!$D$189,0) | I25: =Headcount!I21*Inputs!$D$188+IF(AND(Headcount!I20>=Inputs!$D$173,Headcount!H20<Inputs!$D$173),Inputs!$D$189,0) | J25: =Headcount!J21*Inputs!$D$188+IF(AND(Headcount!J20>=Inputs!$D$173,Headcount!I20<Inputs!$D$173),Inputs!$D$189,0) | K25: =Headcount!K21*Inputs!$D$188+IF(AND(Headcount!K20>=Inputs!$D$173,Headcount!J20<Inputs!$D$173),Inputs!$D$189,0) | L25: =Headcount!L21*Inputs!$D$188+IF(AND(Headcount!L20>=Inputs!$D$173,Headcount!K20<Inputs!$D$173),Inputs!$D$189,0) | ... BK25: =Headcount!BK21*Inputs!$D$188+IF(AND(Headcount!BK20>=Inputs!$D$173,Headcount!BJ20<Inputs!$D$173),Inputs!$D$189,0) | BM25: =SUM(D25:O25) | BN25: =SUM(P25:AA25) | BO25: =SUM(AB25:AM25) | BP25: =SUM(AN25:AY25) | BQ25: =SUM(AZ25:BK25)
B26: Depreciation and amortisation | C26: $ | D26: =SUM(D25:D25)/36 | E26: =SUM(D25:E25)/36 | F26: =SUM(D25:F25)/36 | G26: =SUM(D25:G25)/36 | H26: =SUM(D25:H25)/36 | I26: =SUM(D25:I25)/36 | J26: =SUM(D25:J25)/36 | K26: =SUM(D25:K25)/36 | L26: =SUM(D25:L25)/36 | M26: =SUM(D25:M25)/36 | N26: =SUM(D25:N25)/36 | O26: =SUM(D25:O25)/36 | P26: =SUM(D25:P25)/36 | Q26: =SUM(D25:Q25)/36 | R26: =SUM(D25:R25)/36 | S26: =SUM(D25:S25)/36 | T26: =SUM(D25:T25)/36 | U26: =SUM(D25:U25)/36 | V26: =SUM(D25:V25)/36 | W26: =SUM(D25:W25)/36 | X26: =SUM(D25:X25)/36 | Y26: =SUM(D25:Y25)/36 | Z26: =SUM(D25:Z25)/36 | AA26: =SUM(D25:AA25)/36 | AB26: =SUM(D25:AB25)/36 | AC26: =SUM(D25:AC25)/36 | AD26: =SUM(D25:AD25)/36 | AE26: =SUM(D25:AE25)/36 | AF26: =SUM(D25:AF25)/36 | AG26: =SUM(D25:AG25)/36 | AH26: =SUM(D25:AH25)/36 | AI26: =SUM(D25:AI25)/36 | AJ26: =SUM(D25:AJ25)/36 | AK26: =SUM(D25:AK25)/36 | AL26: =SUM(D25:AL25)/36 | AM26: =SUM(D25:AM25)/36 | AN26: =SUM(E25:AN25)/36 | AO26: =SUM(F25:AO25)/36 | AP26: =SUM(G25:AP25)/36 | AQ26: =SUM(H25:AQ25)/36 | AR26: =SUM(I25:AR25)/36 | AS26: =SUM(J25:AS25)/36 | AT26: =SUM(K25:AT25)/36 | ... BK26: =SUM(AB25:BK25)/36 | BM26: =SUM(D26:O26) | BN26: =SUM(P26:AA26) | BO26: =SUM(AB26:AM26) | BP26: =SUM(AN26:AY26) | BQ26: =SUM(AZ26:BK26)
B27: Stock compensation add back | C27: $ | D27: ='P&L'!D44 | E27: ='P&L'!E44 | F27: ='P&L'!F44 | G27: ='P&L'!G44 | H27: ='P&L'!H44 | I27: ='P&L'!I44 | J27: ='P&L'!J44 | K27: ='P&L'!K44 | ... BK27: ='P&L'!BK44 | BM27: =SUM(D27:O27) | BN27: =SUM(P27:AA27) | BO27: =SUM(AB27:AM27) | BP27: =SUM(AN27:AY27) | BQ27: =SUM(AZ27:BK27)
B29: CASH ROLL
B30: Opening cash | C30: $ | D30: =Inputs!$D$10 | E30: =D34 | F30: =E34 | G30: =F34 | H30: =G34 | I30: =H34 | J30: =I34 | K30: =J34 | L30: =K34 | ... BK30: =BJ34
B31: Interest income | C31: $ | D31: =D30*Inputs!$D$190/12 | E31: =E30*Inputs!$D$190/12 | F31: =F30*Inputs!$D$190/12 | G31: =G30*Inputs!$D$190/12 | H31: =H30*Inputs!$D$190/12 | I31: =I30*Inputs!$D$190/12 | J31: =J30*Inputs!$D$190/12 | K31: =K30*Inputs!$D$190/12 | ... BK31: =BK30*Inputs!$D$190/12 | BM31: =SUM(D31:O31) | BN31: =SUM(P31:AA31) | BO31: =SUM(AB31:AM31) | BP31: =SUM(AN31:AY31) | BQ31: =SUM(AZ31:BK31)
B32: Net income | C32: $ | D32: ='P&L'!D43-'P&L'!D44-D26+D31 | E32: ='P&L'!E43-'P&L'!E44-E26+E31 | F32: ='P&L'!F43-'P&L'!F44-F26+F31 | G32: ='P&L'!G43-'P&L'!G44-G26+G31 | H32: ='P&L'!H43-'P&L'!H44-H26+H31 | I32: ='P&L'!I43-'P&L'!I44-I26+I31 | J32: ='P&L'!J43-'P&L'!J44-J26+J31 | K32: ='P&L'!K43-'P&L'!K44-K26+K31 | ... BK32: ='P&L'!BK43-'P&L'!BK44-BK26+BK31 | BM32: =SUM(D32:O32) | BN32: =SUM(P32:AA32) | BO32: =SUM(AB32:AM32) | BP32: =SUM(AN32:AY32) | BQ32: =SUM(AZ32:BK32)
B33: Free cash flow | C33: $ | D33: =D32+D27+D26-D19+D12+D21-D22-D25 | E33: =E32+E27+E26-E19+E12+E21-E22-E25 | F33: =F32+F27+F26-F19+F12+F21-F22-F25 | G33: =G32+G27+G26-G19+G12+G21-G22-G25 | H33: =H32+H27+H26-H19+H12+H21-H22-H25 | I33: =I32+I27+I26-I19+I12+I21-I22-I25 | J33: =J32+J27+J26-J19+J12+J21-J22-J25 | K33: =K32+K27+K26-K19+K12+K21-K22-K25 | ... BK33: =BK32+BK27+BK26-BK19+BK12+BK21-BK22-BK25 | BM33: =SUM(D33:O33) | BN33: =SUM(P33:AA33) | BO33: =SUM(AB33:AM33) | BP33: =SUM(AN33:AY33) | BQ33: =SUM(AZ33:BK33)
B34: Closing cash | C34: $ | D34: =D30+D33 | E34: =E30+E33 | F34: =F30+F33 | G34: =G30+G33 | H34: =H30+H33 | I34: =I30+I33 | J34: =J30+J33 | K34: =K30+K33 | ... BK34: =BK30+BK33 | BM34: =O34 | BN34: =AA34 | BO34: =AM34 | BP34: =AY34 | BQ34: =BK34
B35: Headroom over minimum balance | C35: $ | D35: =D34-Inputs!$D$12 | E35: =E34-Inputs!$D$12 | F35: =F34-Inputs!$D$12 | G35: =G34-Inputs!$D$12 | H35: =H34-Inputs!$D$12 | I35: =I34-Inputs!$D$12 | J35: =J34-Inputs!$D$12 | K35: =K34-Inputs!$D$12 | ... BK35: =BK34-Inputs!$D$12 | BM35: =O35 | BN35: =AA35 | BO35: =AM35 | BP35: =AY35 | BQ35: =BK35

Sheet KPIs
B2: Key Performance Indicators and Runway
B5: Month ending | D5: 46053 | E5: 46081 | F5: 46112 | G5: 46142 | H5: 46173 | I5: 46203 | J5: 46234 | K5: 46265 | L5: 46295 | M5: 46326 | N5: 46356 | O5: 46387 | P5: 46418 | Q5: 46446 | R5: 46477 | S5: 46507 | T5: 46538 | U5: 46568 | V5: 46599 | W5: 46630 | X5: 46660 | Y5: 46691 | Z5: 46721 | AA5: 46752 | AB5: 46783 | AC5: 46812 | AD5: 46843 | AE5: 46873 | AF5: 46904 | AG5: 46934 | AH5: 46965 | AI5: 46996 | AJ5: 47026 | AK5: 47057 | AL5: 47087 | AM5: 47118 | AN5: 47149 | AO5: 47177 | AP5: 47208 | AQ5: 47238 | AR5: 47269 | AS5: 47299 | AT5: 47330 | AU5: 47361 | AV5: 47391 | AW5: 47422 | AX5: 47452 | AY5: 47483 | AZ5: 47514 | BA5: 47542 | BB5: 47573 | BC5: 47603 | BD5: 47634 | BE5: 47664 | BF5: 47695 | BG5: 47726 | BH5: 47756 | BI5: 47787 | BJ5: 47817 | BK5: 47848 | BM5: FY2026 | BN5: FY2027 | BO5: FY2028 | BP5: FY2029 | BQ5: FY2030
B6: Fiscal year | D6: 2026 | E6: 2026 | F6: 2026 | G6: 2026 | H6: 2026 | I6: 2026 | J6: 2026 | K6: 2026 | L6: 2026 | M6: 2026 | N6: 2026 | O6: 2026 | P6: 2027 | Q6: 2027 | R6: 2027 | S6: 2027 | T6: 2027 | U6: 2027 | V6: 2027 | W6: 2027 | X6: 2027 | Y6: 2027 | Z6: 2027 | AA6: 2027 | AB6: 2028 | AC6: 2028 | AD6: 2028 | AE6: 2028 | AF6: 2028 | AG6: 2028 | AH6: 2028 | AI6: 2028 | AJ6: 2028 | AK6: 2028 | AL6: 2028 | AM6: 2028 | AN6: 2029 | AO6: 2029 | AP6: 2029 | AQ6: 2029 | AR6: 2029 | AS6: 2029 | AT6: 2029 | AU6: 2029 | AV6: 2029 | AW6: 2029 | AX6: 2029 | AY6: 2029 | AZ6: 2030 | BA6: 2030 | BB6: 2030 | BC6: 2030 | BD6: 2030 | BE6: 2030 | BF6: 2030 | BG6: 2030 | BH6: 2030 | BI6: 2030 | BJ6: 2030 | BK6: 2030
B7: Period | D7: 1 | E7: 2 | F7: 3 | G7: 4 | H7: 5 | I7: 6 | J7: 7 | K7: 8 | L7: 9 | M7: 10 | N7: 11 | O7: 12 | P7: 13 | Q7: 14 | R7: 15 | S7: 16 | T7: 17 | U7: 18 | V7: 19 | W7: 20 | X7: 21 | Y7: 22 | Z7: 23 | AA7: 24 | AB7: 25 | AC7: 26 | AD7: 27 | AE7: 28 | AF7: 29 | AG7: 30 | AH7: 31 | AI7: 32 | AJ7: 33 | AK7: 34 | AL7: 35 | AM7: 36 | AN7: 37 | AO7: 38 | AP7: 39 | AQ7: 40 | AR7: 41 | AS7: 42 | AT7: 43 | AU7: 44 | AV7: 45 | AW7: 46 | AX7: 47 | AY7: 48 | AZ7: 49 | BA7: 50 | BB7: 51 | BC7: 52 | BD7: 53 | BE7: 54 | BF7: 55 | BG7: 56 | BH7: 57 | BI7: 58 | BJ7: 59 | BK7: 60
B9: RETENTION
B10: Net revenue retention, trailing twelve months | C10: % | D10: ="" | E10: ="" | F10: ="" | G10: ="" | H10: ="" | I10: ="" | J10: ="" | K10: ="" | ... O10: ="" | P10: =(SUM('Rev-Cohorts'!P18:P29)+SUM('Rev-Cohorts'!P31:P31))/(SUM('Rev-Cohorts'!D18:D29)+SUM('Rev-Cohorts'!D31:D31)) | Q10: =(SUM('Rev-Cohorts'!Q18:Q29)+SUM('Rev-Cohorts'!Q31:Q32))/(SUM('Rev-Cohorts'!E18:E29)+SUM('Rev-Cohorts'!E31:E32)) | R10: =(SUM('Rev-Cohorts'!R18:R29)+SUM('Rev-Cohorts'!R31:R33))/(SUM('Rev-Cohorts'!F18:F29)+SUM('Rev-Cohorts'!F31:F33)) | S10: =(SUM('Rev-Cohorts'!S18:S29)+SUM('Rev-Cohorts'!S31:S34))/(SUM('Rev-Cohorts'!G18:G29)+SUM('Rev-Cohorts'!G31:G34)) | T10: =(SUM('Rev-Cohorts'!T18:T29)+SUM('Rev-Cohorts'!T31:T35))/(SUM('Rev-Cohorts'!H18:H29)+SUM('Rev-Cohorts'!H31:H35)) | U10: =(SUM('Rev-Cohorts'!U18:U29)+SUM('Rev-Cohorts'!U31:U36))/(SUM('Rev-Cohorts'!I18:I29)+SUM('Rev-Cohorts'!I31:I36)) | V10: =(SUM('Rev-Cohorts'!V18:V29)+SUM('Rev-Cohorts'!V31:V37))/(SUM('Rev-Cohorts'!J18:J29)+SUM('Rev-Cohorts'!J31:J37)) | W10: =(SUM('Rev-Cohorts'!W18:W29)+SUM('Rev-Cohorts'!W31:W38))/(SUM('Rev-Cohorts'!K18:K29)+SUM('Rev-Cohorts'!K31:K38)) | X10: =(SUM('Rev-Cohorts'!X18:X29)+SUM('Rev-Cohorts'!X31:X39))/(SUM('Rev-Cohorts'!L18:L29)+SUM('Rev-Cohorts'!L31:L39)) | Y10: =(SUM('Rev-Cohorts'!Y18:Y29)+SUM('Rev-Cohorts'!Y31:Y40))/(SUM('Rev-Cohorts'!M18:M29)+SUM('Rev-Cohorts'!M31:M40)) | Z10: =(SUM('Rev-Cohorts'!Z18:Z29)+SUM('Rev-Cohorts'!Z31:Z41))/(SUM('Rev-Cohorts'!N18:N29)+SUM('Rev-Cohorts'!N31:N41)) | AA10: =(SUM('Rev-Cohorts'!AA18:AA29)+SUM('Rev-Cohorts'!AA31:AA42))/(SUM('Rev-Cohorts'!O18:O29)+SUM('Rev-Cohorts'!O31:O42)) | AB10: =(SUM('Rev-Cohorts'!AB18:AB29)+SUM('Rev-Cohorts'!AB31:AB43))/(SUM('Rev-Cohorts'!P18:P29)+SUM('Rev-Cohorts'!P31:P43)) | AC10: =(SUM('Rev-Cohorts'!AC18:AC29)+SUM('Rev-Cohorts'!AC31:AC44))/(SUM('Rev-Cohorts'!Q18:Q29)+SUM('Rev-Cohorts'!Q31:Q44)) | AD10: =(SUM('Rev-Cohorts'!AD18:AD29)+SUM('Rev-Cohorts'!AD31:AD45))/(SUM('Rev-Cohorts'!R18:R29)+SUM('Rev-Cohorts'!R31:R45)) | AE10: =(SUM('Rev-Cohorts'!AE18:AE29)+SUM('Rev-Cohorts'!AE31:AE46))/(SUM('Rev-Cohorts'!S18:S29)+SUM('Rev-Cohorts'!S31:S46)) | AF10: =(SUM('Rev-Cohorts'!AF18:AF29)+SUM('Rev-Cohorts'!AF31:AF47))/(SUM('Rev-Cohorts'!T18:T29)+SUM('Rev-Cohorts'!T31:T47)) | AG10: =(SUM('Rev-Cohorts'!AG18:AG29)+SUM('Rev-Cohorts'!AG31:AG48))/(SUM('Rev-Cohorts'!U18:U29)+SUM('Rev-Cohorts'!U31:U48)) | AH10: =(SUM('Rev-Cohorts'!AH18:AH29)+SUM('Rev-Cohorts'!AH31:AH49))/(SUM('Rev-Cohorts'!V18:V29)+SUM('Rev-Cohorts'!V31:V49)) | AI10: =(SUM('Rev-Cohorts'!AI18:AI29)+SUM('Rev-Cohorts'!AI31:AI50))/(SUM('Rev-Cohorts'!W18:W29)+SUM('Rev-Cohorts'!W31:W50)) | AJ10: =(SUM('Rev-Cohorts'!AJ18:AJ29)+SUM('Rev-Cohorts'!AJ31:AJ51))/(SUM('Rev-Cohorts'!X18:X29)+SUM('Rev-Cohorts'!X31:X51)) | AK10: =(SUM('Rev-Cohorts'!AK18:AK29)+SUM('Rev-Cohorts'!AK31:AK52))/(SUM('Rev-Cohorts'!Y18:Y29)+SUM('Rev-Cohorts'!Y31:Y52)) | AL10: =(SUM('Rev-Cohorts'!AL18:AL29)+SUM('Rev-Cohorts'!AL31:AL53))/(SUM('Rev-Cohorts'!Z18:Z29)+SUM('Rev-Cohorts'!Z31:Z53)) | AM10: =(SUM('Rev-Cohorts'!AM18:AM29)+SUM('Rev-Cohorts'!AM31:AM54))/(SUM('Rev-Cohorts'!AA18:AA29)+SUM('Rev-Cohorts'!AA31:AA54)) | AN10: =(SUM('Rev-Cohorts'!AN18:AN29)+SUM('Rev-Cohorts'!AN31:AN55))/(SUM('Rev-Cohorts'!AB18:AB29)+SUM('Rev-Cohorts'!AB31:AB55)) | AO10: =(SUM('Rev-Cohorts'!AO18:AO29)+SUM('Rev-Cohorts'!AO31:AO56))/(SUM('Rev-Cohorts'!AC18:AC29)+SUM('Rev-Cohorts'!AC31:AC56)) | AP10: =(SUM('Rev-Cohorts'!AP18:AP29)+SUM('Rev-Cohorts'!AP31:AP57))/(SUM('Rev-Cohorts'!AD18:AD29)+SUM('Rev-Cohorts'!AD31:AD57)) | AQ10: =(SUM('Rev-Cohorts'!AQ18:AQ29)+SUM('Rev-Cohorts'!AQ31:AQ58))/(SUM('Rev-Cohorts'!AE18:AE29)+SUM('Rev-Cohorts'!AE31:AE58)) | AR10: =(SUM('Rev-Cohorts'!AR18:AR29)+SUM('Rev-Cohorts'!AR31:AR59))/(SUM('Rev-Cohorts'!AF18:AF29)+SUM('Rev-Cohorts'!AF31:AF59)) | AS10: =(SUM('Rev-Cohorts'!AS18:AS29)+SUM('Rev-Cohorts'!AS31:AS60))/(SUM('Rev-Cohorts'!AG18:AG29)+SUM('Rev-Cohorts'!AG31:AG60)) | AT10: =(SUM('Rev-Cohorts'!AT18:AT29)+SUM('Rev-Cohorts'!AT31:AT61))/(SUM('Rev-Cohorts'!AH18:AH29)+SUM('Rev-Cohorts'!AH31:AH61)) | AU10: =(SUM('Rev-Cohorts'!AU18:AU29)+SUM('Rev-Cohorts'!AU31:AU62))/(SUM('Rev-Cohorts'!AI18:AI29)+SUM('Rev-Cohorts'!AI31:AI62)) | AV10: =(SUM('Rev-Cohorts'!AV18:AV29)+SUM('Rev-Cohorts'!AV31:AV63))/(SUM('Rev-Cohorts'!AJ18:AJ29)+SUM('Rev-Cohorts'!AJ31:AJ63)) | AW10: =(SUM('Rev-Cohorts'!AW18:AW29)+SUM('Rev-Cohorts'!AW31:AW64))/(SUM('Rev-Cohorts'!AK18:AK29)+SUM('Rev-Cohorts'!AK31:AK64)) | AX10: =(SUM('Rev-Cohorts'!AX18:AX29)+SUM('Rev-Cohorts'!AX31:AX65))/(SUM('Rev-Cohorts'!AL18:AL29)+SUM('Rev-Cohorts'!AL31:AL65)) | AY10: =(SUM('Rev-Cohorts'!AY18:AY29)+SUM('Rev-Cohorts'!AY31:AY66))/(SUM('Rev-Cohorts'!AM18:AM29)+SUM('Rev-Cohorts'!AM31:AM66)) | AZ10: =(SUM('Rev-Cohorts'!AZ18:AZ29)+SUM('Rev-Cohorts'!AZ31:AZ67))/(SUM('Rev-Cohorts'!AN18:AN29)+SUM('Rev-Cohorts'!AN31:AN67)) | BA10: =(SUM('Rev-Cohorts'!BA18:BA29)+SUM('Rev-Cohorts'!BA31:BA68))/(SUM('Rev-Cohorts'!AO18:AO29)+SUM('Rev-Cohorts'!AO31:AO68)) | BB10: =(SUM('Rev-Cohorts'!BB18:BB29)+SUM('Rev-Cohorts'!BB31:BB69))/(SUM('Rev-Cohorts'!AP18:AP29)+SUM('Rev-Cohorts'!AP31:AP69)) | BC10: =(SUM('Rev-Cohorts'!BC18:BC29)+SUM('Rev-Cohorts'!BC31:BC70))/(SUM('Rev-Cohorts'!AQ18:AQ29)+SUM('Rev-Cohorts'!AQ31:AQ70)) | BD10: =(SUM('Rev-Cohorts'!BD18:BD29)+SUM('Rev-Cohorts'!BD31:BD71))/(SUM('Rev-Cohorts'!AR18:AR29)+SUM('Rev-Cohorts'!AR31:AR71)) | BE10: =(SUM('Rev-Cohorts'!BE18:BE29)+SUM('Rev-Cohorts'!BE31:BE72))/(SUM('Rev-Cohorts'!AS18:AS29)+SUM('Rev-Cohorts'!AS31:AS72)) | BF10: =(SUM('Rev-Cohorts'!BF18:BF29)+SUM('Rev-Cohorts'!BF31:BF73))/(SUM('Rev-Cohorts'!AT18:AT29)+SUM('Rev-Cohorts'!AT31:AT73)) | BG10: =(SUM('Rev-Cohorts'!BG18:BG29)+SUM('Rev-Cohorts'!BG31:BG74))/(SUM('Rev-Cohorts'!AU18:AU29)+SUM('Rev-Cohorts'!AU31:AU74)) | BH10: =(SUM('Rev-Cohorts'!BH18:BH29)+SUM('Rev-Cohorts'!BH31:BH75))/(SUM('Rev-Cohorts'!AV18:AV29)+SUM('Rev-Cohorts'!AV31:AV75)) | BI10: =(SUM('Rev-Cohorts'!BI18:BI29)+SUM('Rev-Cohorts'!BI31:BI76))/(SUM('Rev-Cohorts'!AW18:AW29)+SUM('Rev-Cohorts'!AW31:AW76)) | BJ10: =(SUM('Rev-Cohorts'!BJ18:BJ29)+SUM('Rev-Cohorts'!BJ31:BJ77))/(SUM('Rev-Cohorts'!AX18:AX29)+SUM('Rev-Cohorts'!AX31:AX77)) | BK10: =(SUM('Rev-Cohorts'!BK18:BK29)+SUM('Rev-Cohorts'!BK31:BK78))/(SUM('Rev-Cohorts'!AY18:AY29)+SUM('Rev-Cohorts'!AY31:AY78)) | BM10: =O10 | BN10: =AA10 | BO10: =AM10 | BP10: =AY10 | BQ10: =BK10
B11: Gross revenue retention, trailing twelve months | C11: % | D11: ="" | E11: ="" | F11: ="" | G11: ="" | H11: ="" | I11: ="" | J11: ="" | K11: ="" | ... O11: ="" | P11: =1+SUM('Rev-ARR Bridge'!E13:P13)/'Rev-ARR Bridge'!D26 | Q11: =1+SUM('Rev-ARR Bridge'!F13:Q13)/'Rev-ARR Bridge'!E26 | R11: =1+SUM('Rev-ARR Bridge'!G13:R13)/'Rev-ARR Bridge'!F26 | S11: =1+SUM('Rev-ARR Bridge'!H13:S13)/'Rev-ARR Bridge'!G26 | T11: =1+SUM('Rev-ARR Bridge'!I13:T13)/'Rev-ARR Bridge'!H26 | U11: =1+SUM('Rev-ARR Bridge'!J13:U13)/'Rev-ARR Bridge'!I26 | V11: =1+SUM('Rev-ARR Bridge'!K13:V13)/'Rev-ARR Bridge'!J26 | W11: =1+SUM('Rev-ARR Bridge'!L13:W13)/'Rev-ARR Bridge'!K26 | ... BK11: =1+SUM('Rev-ARR Bridge'!AZ13:BK13)/'Rev-ARR Bridge'!AY26 | BM11: =O11 | BN11: =AA11 | BO11: =AM11 | BP11: =AY11 | BQ11: =BK11
B12: Benchmark: median 89%, top quartile 94%
B14: EFFICIENCY
B15: Gross margin | C15: % | D15: ='P&L'!D25 | E15: ='P&L'!E25 | F15: ='P&L'!F25 | G15: ='P&L'!G25 | H15: ='P&L'!H25 | I15: ='P&L'!I25 | J15: ='P&L'!J25 | K15: ='P&L'!K25 | ... BK15: ='P&L'!BK25 | BM15: =O15 | BN15: =AA15 | BO15: =AM15 | BP15: =AY15 | BQ15: =BK15
B16: Burn multiple, net burn over net new ARR | C16: x | D16: ="" | E16: ="" | F16: ="" | G16: ="" | H16: ="" | I16: ="" | J16: ="" | K16: ="" | ... O16: ="" | P16: =IF(OR('Rev-ARR Bridge'!P26-'Rev-ARR Bridge'!D26<=0,SUM('Cash Flow'!E33:P33)>=0),"",-SUM('Cash Flow'!E33:P33)/('Rev-ARR Bridge'!P26-'Rev-ARR Bridge'!D26)) | Q16: =IF(OR('Rev-ARR Bridge'!Q26-'Rev-ARR Bridge'!E26<=0,SUM('Cash Flow'!F33:Q33)>=0),"",-SUM('Cash Flow'!F33:Q33)/('Rev-ARR Bridge'!Q26-'Rev-ARR Bridge'!E26)) | R16: =IF(OR('Rev-ARR Bridge'!R26-'Rev-ARR Bridge'!F26<=0,SUM('Cash Flow'!G33:R33)>=0),"",-SUM('Cash Flow'!G33:R33)/('Rev-ARR Bridge'!R26-'Rev-ARR Bridge'!F26)) | S16: =IF(OR('Rev-ARR Bridge'!S26-'Rev-ARR Bridge'!G26<=0,SUM('Cash Flow'!H33:S33)>=0),"",-SUM('Cash Flow'!H33:S33)/('Rev-ARR Bridge'!S26-'Rev-ARR Bridge'!G26)) | T16: =IF(OR('Rev-ARR Bridge'!T26-'Rev-ARR Bridge'!H26<=0,SUM('Cash Flow'!I33:T33)>=0),"",-SUM('Cash Flow'!I33:T33)/('Rev-ARR Bridge'!T26-'Rev-ARR Bridge'!H26)) | U16: =IF(OR('Rev-ARR Bridge'!U26-'Rev-ARR Bridge'!I26<=0,SUM('Cash Flow'!J33:U33)>=0),"",-SUM('Cash Flow'!J33:U33)/('Rev-ARR Bridge'!U26-'Rev-ARR Bridge'!I26)) | V16: =IF(OR('Rev-ARR Bridge'!V26-'Rev-ARR Bridge'!J26<=0,SUM('Cash Flow'!K33:V33)>=0),"",-SUM('Cash Flow'!K33:V33)/('Rev-ARR Bridge'!V26-'Rev-ARR Bridge'!J26)) | W16: =IF(OR('Rev-ARR Bridge'!W26-'Rev-ARR Bridge'!K26<=0,SUM('Cash Flow'!L33:W33)>=0),"",-SUM('Cash Flow'!L33:W33)/('Rev-ARR Bridge'!W26-'Rev-ARR Bridge'!K26)) | ... BK16: =IF(OR('Rev-ARR Bridge'!BK26-'Rev-ARR Bridge'!AY26<=0,SUM('Cash Flow'!AZ33:BK33)>=0),"",-SUM('Cash Flow'!AZ33:BK33)/('Rev-ARR Bridge'!BK26-'Rev-ARR Bridge'!AY26)) | BM16: =O16 | BN16: =AA16 | BO16: =AM16 | BP16: =AY16 | BQ16: =BK16
B17: ARR per full time employee | C17: $ | D17: ='Rev-ARR Bridge'!D26/Headcount!D20 | E17: ='Rev-ARR Bridge'!E26/Headcount!E20 | F17: ='Rev-ARR Bridge'!F26/Headcount!F20 | G17: ='Rev-ARR Bridge'!G26/Headcount!G20 | H17: ='Rev-ARR Bridge'!H26/Headcount!H20 | I17: ='Rev-ARR Bridge'!I26/Headcount!I20 | J17: ='Rev-ARR Bridge'!J26/Headcount!J20 | K17: ='Rev-ARR Bridge'!K26/Headcount!K20 | ... BK17: ='Rev-ARR Bridge'!BK26/Headcount!BK20 | BM17: =O17 | BN17: =AA17 | BO17: =AM17 | BP17: =AY17 | BQ17: =BK17
B18: Rule of 40, growth plus EBITDA margin | C18: % | D18: ="" | E18: ="" | F18: ="" | G18: ="" | H18: ="" | I18: ="" | J18: ="" | K18: ="" | ... O18: ="" | P18: ='Rev-ARR Bridge'!P27+SUM('P&L'!E43:P43)/SUM('P&L'!E13:P13) | Q18: ='Rev-ARR Bridge'!Q27+SUM('P&L'!F43:Q43)/SUM('P&L'!F13:Q13) | R18: ='Rev-ARR Bridge'!R27+SUM('P&L'!G43:R43)/SUM('P&L'!G13:R13) | S18: ='Rev-ARR Bridge'!S27+SUM('P&L'!H43:S43)/SUM('P&L'!H13:S13) | T18: ='Rev-ARR Bridge'!T27+SUM('P&L'!I43:T43)/SUM('P&L'!I13:T13) | U18: ='Rev-ARR Bridge'!U27+SUM('P&L'!J43:U43)/SUM('P&L'!J13:U13) | V18: ='Rev-ARR Bridge'!V27+SUM('P&L'!K43:V43)/SUM('P&L'!K13:V13) | W18: ='Rev-ARR Bridge'!W27+SUM('P&L'!L43:W43)/SUM('P&L'!L13:W13) | ... BK18: ='Rev-ARR Bridge'!BK27+SUM('P&L'!AZ43:BK43)/SUM('P&L'!AZ13:BK13) | BM18: =O18 | BN18: =AA18 | BO18: =AM18 | BP18: =AY18 | BQ18: =BK18
B19: CAC per new logo, excluding customer success | C19: $ | D19: ="" | E19: ="" | F19: ="" | G19: =IF(SUM('Rev-Capacity'!E30:G30)=0,"",(SUM('P&L'!E37:G37)-SUM('P&L'!E36:G36))/SUM('Rev-Capacity'!E30:G30)) | H19: =IF(SUM('Rev-Capacity'!F30:H30)=0,"",(SUM('P&L'!F37:H37)-SUM('P&L'!F36:H36))/SUM('Rev-Capacity'!F30:H30)) | I19: =IF(SUM('Rev-Capacity'!G30:I30)=0,"",(SUM('P&L'!G37:I37)-SUM('P&L'!G36:I36))/SUM('Rev-Capacity'!G30:I30)) | J19: =IF(SUM('Rev-Capacity'!H30:J30)=0,"",(SUM('P&L'!H37:J37)-SUM('P&L'!H36:J36))/SUM('Rev-Capacity'!H30:J30)) | K19: =IF(SUM('Rev-Capacity'!I30:K30)=0,"",(SUM('P&L'!I37:K37)-SUM('P&L'!I36:K36))/SUM('Rev-Capacity'!I30:K30)) | L19: =IF(SUM('Rev-Capacity'!J30:L30)=0,"",(SUM('P&L'!J37:L37)-SUM('P&L'!J36:L36))/SUM('Rev-Capacity'!J30:L30)) | M19: =IF(SUM('Rev-Capacity'!K30:M30)=0,"",(SUM('P&L'!K37:M37)-SUM('P&L'!K36:M36))/SUM('Rev-Capacity'!K30:M30)) | N19: =IF(SUM('Rev-Capacity'!L30:N30)=0,"",(SUM('P&L'!L37:N37)-SUM('P&L'!L36:N36))/SUM('Rev-Capacity'!L30:N30)) | ... BK19: =IF(SUM('Rev-Capacity'!BI30:BK30)=0,"",(SUM('P&L'!BI37:BK37)-SUM('P&L'!BI36:BK36))/SUM('Rev-Capacity'!BI30:BK30)) | BM19: =O19 | BN19: =AA19 | BO19: =AM19 | BP19: =AY19 | BQ19: =BK19
B20: CAC payback, new business | C20: months | D20: ="" | E20: ="" | F20: ="" | G20: =IF(SUM('Rev-Capacity'!E29:G29)*'P&L'!G25=0,"",(SUM('P&L'!E37:G37)-SUM('P&L'!E36:G36))/(SUM('Rev-Capacity'!E29:G29)*'P&L'!G25)*12) | H20: =IF(SUM('Rev-Capacity'!F29:H29)*'P&L'!H25=0,"",(SUM('P&L'!F37:H37)-SUM('P&L'!F36:H36))/(SUM('Rev-Capacity'!F29:H29)*'P&L'!H25)*12) | I20: =IF(SUM('Rev-Capacity'!G29:I29)*'P&L'!I25=0,"",(SUM('P&L'!G37:I37)-SUM('P&L'!G36:I36))/(SUM('Rev-Capacity'!G29:I29)*'P&L'!I25)*12) | J20: =IF(SUM('Rev-Capacity'!H29:J29)*'P&L'!J25=0,"",(SUM('P&L'!H37:J37)-SUM('P&L'!H36:J36))/(SUM('Rev-Capacity'!H29:J29)*'P&L'!J25)*12) | K20: =IF(SUM('Rev-Capacity'!I29:K29)*'P&L'!K25=0,"",(SUM('P&L'!I37:K37)-SUM('P&L'!I36:K36))/(SUM('Rev-Capacity'!I29:K29)*'P&L'!K25)*12) | L20: =IF(SUM('Rev-Capacity'!J29:L29)*'P&L'!L25=0,"",(SUM('P&L'!J37:L37)-SUM('P&L'!J36:L36))/(SUM('Rev-Capacity'!J29:L29)*'P&L'!L25)*12) | M20: =IF(SUM('Rev-Capacity'!K29:M29)*'P&L'!M25=0,"",(SUM('P&L'!K37:M37)-SUM('P&L'!K36:M36))/(SUM('Rev-Capacity'!K29:M29)*'P&L'!M25)*12) | N20: =IF(SUM('Rev-Capacity'!L29:N29)*'P&L'!N25=0,"",(SUM('P&L'!L37:N37)-SUM('P&L'!L36:N36))/(SUM('Rev-Capacity'!L29:N29)*'P&L'!N25)*12) | ... BK20: =IF(SUM('Rev-Capacity'!BI29:BK29)*'P&L'!BK25=0,"",(SUM('P&L'!BI37:BK37)-SUM('P&L'!BI36:BK36))/(SUM('Rev-Capacity'!BI29:BK29)*'P&L'!BK25)*12) | BM20: =O20 | BN20: =AA20 | BO20: =AM20 | BP20: =AY20 | BQ20: =BK20
B21: CAC payback, blended | C21: months | D21: ="" | E21: ="" | F21: ="" | G21: =IF(SUM('Rev-Capacity'!E29:G29)*'P&L'!G25=0,"",SUM('P&L'!E37:G37)/(SUM('Rev-Capacity'!E29:G29)*'P&L'!G25)*12) | H21: =IF(SUM('Rev-Capacity'!F29:H29)*'P&L'!H25=0,"",SUM('P&L'!F37:H37)/(SUM('Rev-Capacity'!F29:H29)*'P&L'!H25)*12) | I21: =IF(SUM('Rev-Capacity'!G29:I29)*'P&L'!I25=0,"",SUM('P&L'!G37:I37)/(SUM('Rev-Capacity'!G29:I29)*'P&L'!I25)*12) | J21: =IF(SUM('Rev-Capacity'!H29:J29)*'P&L'!J25=0,"",SUM('P&L'!H37:J37)/(SUM('Rev-Capacity'!H29:J29)*'P&L'!J25)*12) | K21: =IF(SUM('Rev-Capacity'!I29:K29)*'P&L'!K25=0,"",SUM('P&L'!I37:K37)/(SUM('Rev-Capacity'!I29:K29)*'P&L'!K25)*12) | L21: =IF(SUM('Rev-Capacity'!J29:L29)*'P&L'!L25=0,"",SUM('P&L'!J37:L37)/(SUM('Rev-Capacity'!J29:L29)*'P&L'!L25)*12) | M21: =IF(SUM('Rev-Capacity'!K29:M29)*'P&L'!M25=0,"",SUM('P&L'!K37:M37)/(SUM('Rev-Capacity'!K29:M29)*'P&L'!M25)*12) | N21: =IF(SUM('Rev-Capacity'!L29:N29)*'P&L'!N25=0,"",SUM('P&L'!L37:N37)/(SUM('Rev-Capacity'!L29:N29)*'P&L'!N25)*12) | ... BK21: =IF(SUM('Rev-Capacity'!BI29:BK29)*'P&L'!BK25=0,"",SUM('P&L'!BI37:BK37)/(SUM('Rev-Capacity'!BI29:BK29)*'P&L'!BK25)*12) | BM21: =O21 | BN21: =AA21 | BO21: =AM21 | BP21: =AY21 | BQ21: =BK21
B23: Magic number | C23: x | D23: ="" | E23: ="" | F23: ="" | G23: ="" | H23: ="" | I23: ="" | J23: =(SUM('P&L'!H13:J13)-SUM('P&L'!E13:G13))*4/SUM('P&L'!E37:G37) | K23: =(SUM('P&L'!I13:K13)-SUM('P&L'!F13:H13))*4/SUM('P&L'!F37:H37) | L23: =(SUM('P&L'!J13:L13)-SUM('P&L'!G13:I13))*4/SUM('P&L'!G37:I37) | M23: =(SUM('P&L'!K13:M13)-SUM('P&L'!H13:J13))*4/SUM('P&L'!H37:J37) | N23: =(SUM('P&L'!L13:N13)-SUM('P&L'!I13:K13))*4/SUM('P&L'!I37:K37) | O23: =(SUM('P&L'!M13:O13)-SUM('P&L'!J13:L13))*4/SUM('P&L'!J37:L37) | P23: =(SUM('P&L'!N13:P13)-SUM('P&L'!K13:M13))*4/SUM('P&L'!K37:M37) | Q23: =(SUM('P&L'!O13:Q13)-SUM('P&L'!L13:N13))*4/SUM('P&L'!L37:N37) | ... BK23: =(SUM('P&L'!BI13:BK13)-SUM('P&L'!BF13:BH13))*4/SUM('P&L'!BF37:BH37) | BM23: =O23 | BN23: =AA23 | BO23: =AM23 | BP23: =AY23 | BQ23: =BK23
B25: RUNWAY AND THE RAISE DECISION
B26: Trailing three month average burn | C26: $ | D26: =-AVERAGE('Cash Flow'!D33:D33) | E26: =-AVERAGE('Cash Flow'!D33:E33) | F26: =-AVERAGE('Cash Flow'!D33:F33) | G26: =-AVERAGE('Cash Flow'!E33:G33) | H26: =-AVERAGE('Cash Flow'!F33:H33) | I26: =-AVERAGE('Cash Flow'!G33:I33) | J26: =-AVERAGE('Cash Flow'!H33:J33) | K26: =-AVERAGE('Cash Flow'!I33:K33) | L26: =-AVERAGE('Cash Flow'!J33:L33) | M26: =-AVERAGE('Cash Flow'!K33:M33) | ... BK26: =-AVERAGE('Cash Flow'!BI33:BK33)
B27: Months of runway to the minimum balance | C27: # | D27: =IF(D26<=0,"",MAX('Cash Flow'!D35/D26,0)) | E27: =IF(E26<=0,"",MAX('Cash Flow'!E35/E26,0)) | F27: =IF(F26<=0,"",MAX('Cash Flow'!F35/F26,0)) | G27: =IF(G26<=0,"",MAX('Cash Flow'!G35/G26,0)) | H27: =IF(H26<=0,"",MAX('Cash Flow'!H35/H26,0)) | I27: =IF(I26<=0,"",MAX('Cash Flow'!I35/I26,0)) | J27: =IF(J26<=0,"",MAX('Cash Flow'!J35/J26,0)) | K27: =IF(K26<=0,"",MAX('Cash Flow'!K35/K26,0)) | ... BK27: =IF(BK26<=0,"",MAX('Cash Flow'!BK35/BK26,0))
B28: Below minimum balance | C28: flag | D28: =IF('Cash Flow'!D34<Inputs!$D$12,"BREACH","") | E28: =IF('Cash Flow'!E34<Inputs!$D$12,"BREACH","") | F28: =IF('Cash Flow'!F34<Inputs!$D$12,"BREACH","") | G28: =IF('Cash Flow'!G34<Inputs!$D$12,"BREACH","") | H28: =IF('Cash Flow'!H34<Inputs!$D$12,"BREACH","") | I28: =IF('Cash Flow'!I34<Inputs!$D$12,"BREACH","") | J28: =IF('Cash Flow'!J34<Inputs!$D$12,"BREACH","") | K28: =IF('Cash Flow'!K34<Inputs!$D$12,"BREACH","") | ... BK28: =IF('Cash Flow'!BK34<Inputs!$D$12,"BREACH","")
B29: Raise process should be live | C29: flag | D29: =IF(AND(ISNUMBER(D27),D27<=Inputs!$D$193,D27>0),"RAISE WINDOW","") | E29: =IF(AND(ISNUMBER(E27),E27<=Inputs!$D$193,E27>0),"RAISE WINDOW","") | F29: =IF(AND(ISNUMBER(F27),F27<=Inputs!$D$193,F27>0),"RAISE WINDOW","") | G29: =IF(AND(ISNUMBER(G27),G27<=Inputs!$D$193,G27>0),"RAISE WINDOW","") | H29: =IF(AND(ISNUMBER(H27),H27<=Inputs!$D$193,H27>0),"RAISE WINDOW","") | I29: =IF(AND(ISNUMBER(I27),I27<=Inputs!$D$193,I27>0),"RAISE WINDOW","") | J29: =IF(AND(ISNUMBER(J27),J27<=Inputs!$D$193,J27>0),"RAISE WINDOW","") | K29: =IF(AND(ISNUMBER(K27),K27<=Inputs!$D$193,K27>0),"RAISE WINDOW","") | ... BK29: =IF(AND(ISNUMBER(BK27),BK27<=Inputs!$D$193,BK27>0),"RAISE WINDOW","")
B31: SUMMARY
